Workbook

Sheet Main Page

Sheet Summary
A1: Main Page | E1: Data Source: ACEMF
A6: Fund Barometer
A7: Categories Average (Weighted) Returns of Mutual Funds (%) | F7: As on 30 Apr 2026
A8: Categories | B8: No. Of Funds | C8: Category AUM | D8: 1 Month | E8: 3 Months | F8: 6 Months | G8: YTD | H8: 1 Year | I8: 2 Years | J8: 3 Years | K8: 4 Years | L8: 5 Years | M8: 7 Years | N8: 10 Years | O8: 15 Years | P8: Since Inception | Q8: Riskometer | R8: Ideal Investment Horizon
A9: DEBT FUNDS
A10: OVERNIGHT FUND | B10: =COUNTA('Overnight Fund'!$A$12:A48) -> 35 | C10: =SUM('Overnight Fund'!$D$12:D48) -> 72684.159 | D10: ='Overnight Fund'!I49 -> 5.018624 | E10: ='Overnight Fund'!J49 -> 4.9608537 | F10: ='Overnight Fund'!K49 -> 5.1175713 | G10: ='Overnight Fund'!L49 -> 5.0309286 | H10: ='Overnight Fund'!M49 -> 5.3245389 | I10: ='Overnight Fund'!N49 -> 5.9064812 | J10: ='Overnight Fund'!O49 -> 6.1674722 | K10: ='Overnight Fund'!P49 -> 6.0284285 | ... P10: ='Overnight Fund'!U49 -> 5.5358493 | Q10: Low Risk | R10: 1 - 91 days
A11: MONEY MARKET FUND | B11: =COUNTA('Money Market Fund'!$A$12:A36) -> 25 | C11: =SUM('Money Market Fund'!$D$12:D36) -> 308493.18 | D11: ='Money Market Fund'!I37 -> 7.3410383 | E11: ='Money Market Fund'!J37 -> 6.2039874 | F11: ='Money Market Fund'!K37 -> 5.6947229 | G11: ='Money Market Fund'!L37 -> 5.5733219 | H11: ='Money Market Fund'!M37 -> 6.2367853 | I11: ='Money Market Fund'!N37 -> 7.0529306 | J11: ='Money Market Fund'!O37 -> 7.1494399 | K11: ='Money Market Fund'!P37 -> 6.8261301 | ... P11: ='Money Market Fund'!U37 -> 6.8677068 | Q11: Low to Moderate Risk | R11: 3 months and above
A12: LIQUID FUND | B12: =COUNTA('Liquid Fund'!$A$12:A50) -> 38 | C12: =SUM('Liquid Fund'!$D$12:D50) -> 458154.96 | D12: ='Liquid Fund'!I51 -> 7.9599094 | E12: ='Liquid Fund'!J51 -> 6.8154609 | F12: ='Liquid Fund'!K51 -> 6.2662544 | G12: ='Liquid Fund'!L51 -> 6.4296043 | H12: ='Liquid Fund'!M51 -> 6.1864692 | I12: ='Liquid Fund'!N51 -> 6.7179117 | J12: ='Liquid Fund'!O51 -> 6.8792412 | K12: ='Liquid Fund'!P51 -> 6.6344019 | ... P12: ='Liquid Fund'!U51 -> 6.7419505 | Q12: Low to Moderate Risk | R12: 1 - 91 days
A13: ULTRA SHORT DURATION FUND | B13: =COUNTA('Ultra Short Duration Fund'!$A$12:A36) -> 25 | C13: =SUM('Ultra Short Duration Fund'!$D$12:D36) -> 113337 | D13: ='Ultra Short Duration Fund'!I37 -> 6.8498355 | E13: ='Ultra Short Duration Fund'!J37 -> 6.4333905 | F13: ='Ultra Short Duration Fund'!K37 -> 5.6790969 | G13: ='Ultra Short Duration Fund'!L37 -> 5.6679864 | H13: ='Ultra Short Duration Fund'!M37 -> 6.160709 | I13: ='Ultra Short Duration Fund'!N37 -> 6.8293665 | J13: ='Ultra Short Duration Fund'!O37 -> 6.9113077 | K13: ='Ultra Short Duration Fund'!P37 -> 6.5679239 | ... P13: ='Ultra Short Duration Fund'!U37 -> 6.7398272 | Q13: Low to Moderate Risk | R13: 3 months and above
A14: LOW DURATION FUND | B14: =COUNTA('Low Duration Fund'!$A$12:A34) -> 23 | C14: =SUM('Low Duration Fund'!$D$12:D34) -> 129126.12 | D14: ='Low Duration Fund'!I35 -> 6.2826502 | E14: ='Low Duration Fund'!J35 -> 5.6493069 | F14: ='Low Duration Fund'!K35 -> 5.0344819 | G14: ='Low Duration Fund'!L35 -> 4.8411689 | H14: ='Low Duration Fund'!M35 -> 5.9325712 | I14: ='Low Duration Fund'!N35 -> 6.8932018 | J14: ='Low Duration Fund'!O35 -> 6.9622771 | K14: ='Low Duration Fund'!P35 -> 6.5944796 | ... P14: ='Low Duration Fund'!U35 -> 7.1690639 | Q14: Moderate Risk | R14: 6 months and above
A15: SHORT DURATION FUND | B15: =COUNTA('Short Duration Fund'!$A$12:A36) -> 24 | C15: =SUM('Short Duration Fund'!$D$12:D36) -> 110552.79 | D15: ='Short Duration Fund'!F37 -> 6.1822316 | E15: ='Short Duration Fund'!G37 -> 3.9319393 | F15: ='Short Duration Fund'!H37 -> 3.5250385 | G15: ='Short Duration Fund'!I37 -> 3.0670165 | H15: ='Short Duration Fund'!J37 -> 4.9511693 | I15: ='Short Duration Fund'!K37 -> 7.086151 | J15: ='Short Duration Fund'!L37 -> 6.931984 | K15: ='Short Duration Fund'!M37 -> 6.5584103 | ... P15: ='Short Duration Fund'!R37 -> 7.3413065 | Q15: Low to Moderate Risk | R15: 1 year and above
A16: MEDIUM DURATION FUND | B16: =COUNTA('Medium Duration Fund'!$A$12:A26) -> 13 | C16: =SUM('Medium Duration Fund'!$D$12:D26) -> 25528.301 | D16: ='Medium Duration Fund'!F27 -> 8.5009605 | E16: ='Medium Duration Fund'!G27 -> 4.0224072 | F16: ='Medium Duration Fund'!H27 -> 4.5107225 | G16: ='Medium Duration Fund'!I27 -> 3.974827 | H16: ='Medium Duration Fund'!J27 -> 5.4872556 | I16: ='Medium Duration Fund'!K27 -> 7.8764285 | J16: ='Medium Duration Fund'!L27 -> 7.4098555 | K16: ='Medium Duration Fund'!M27 -> 7.458557 | ... P16: ='Medium Duration Fund'!R27 -> 7.6597404 | Q16: Moderate Risk | R16: 2.5 years and above
A17: MEDIUM TO LONG DURATION FUND | B17: =COUNTA('Medium to Long Duration Fund'!$A$12:A24) -> 13 | C17: =SUM('Medium to Long Duration Fund'!$D$12:D24) -> 10769.245 | D17: ='Medium to Long Duration Fund'!F25 -> 10.498611 | E17: ='Medium to Long Duration Fund'!G25 -> 0.91890742 | F17: ='Medium to Long Duration Fund'!H25 -> 1.4010366 | G17: ='Medium to Long Duration Fund'!I25 -> 0.48000972 | H17: ='Medium to Long Duration Fund'!J25 -> 1.5405364 | I17: ='Medium to Long Duration Fund'!K25 -> 6.0061813 | J17: ='Medium to Long Duration Fund'!L25 -> 6.0290164 | K17: ='Medium to Long Duration Fund'!M25 -> 6.0377419 | ... P17: ='Medium to Long Duration Fund'!R25 -> 7.9637896 | Q17: Moderate Risk | R17: 2.5 years and above
A18: LONG DURATION FUND | B18: =COUNTA('Long Duration Fund'!$A$12:A22) -> 11 | C18: =SUM('Long Duration Fund'!$D$12:D22) -> 14158.737 | D18: ='Long Duration Fund'!F23 -> 19.964692 | E18: ='Long Duration Fund'!G23 -> -3.8485619 | F18: ='Long Duration Fund'!H23 -> -1.7235176 | G18: ='Long Duration Fund'!I23 -> -3.7805508 | H18: ='Long Duration Fund'!J23 -> -2.4856437 | I18: ='Long Duration Fund'!K23 -> 5.0270957 | J18: ='Long Duration Fund'!L23 -> 5.4909075 | K18: ='Long Duration Fund'!M23 -> 6.1419103 | ... P18: ='Long Duration Fund'!R23 -> 6.9479264 | Q18: Moderate Risk | R18: 5 years and above
A19: DYNAMIC BOND | B19: =COUNTA('Dynamic Bond'!$A$12:A34) -> 22 | C19: =SUM('Dynamic Bond'!$D$12:D34) -> 32385.878 | D19: ='Dynamic Bond'!F35 -> 10.145502 | E19: ='Dynamic Bond'!G35 -> 2.6479533 | F19: ='Dynamic Bond'!H35 -> 2.7748929 | G19: ='Dynamic Bond'!I35 -> 2.3191601 | H19: ='Dynamic Bond'!J35 -> 2.7805517 | I19: ='Dynamic Bond'!K35 -> 6.7680068 | J19: ='Dynamic Bond'!L35 -> 6.6749393 | K19: ='Dynamic Bond'!M35 -> 6.6131558 | ... P19: ='Dynamic Bond'!R35 -> 7.6110802 | Q19: Moderate Risk | R19: 2.5 years and above
A20: CORPORATE BOND FUND | B20: =COUNTA('Corporate Bond Fund'!$A$12:A32) -> 21 | C20: =SUM('Corporate Bond Fund'!$D$12:D32) -> 178530.72 | D20: ='Corporate Bond Fund'!F33 -> 6.6762327 | E20: ='Corporate Bond Fund'!G33 -> 3.2485229 | F20: ='Corporate Bond Fund'!H33 -> 2.8656602 | G20: ='Corporate Bond Fund'!I33 -> 2.1860598 | H20: ='Corporate Bond Fund'!J33 -> 4.4176321 | I20: ='Corporate Bond Fund'!K33 -> 7.0266031 | J20: ='Corporate Bond Fund'!L33 -> 6.9654242 | K20: ='Corporate Bond Fund'!M33 -> 6.5835124 | ... P20: ='Corporate Bond Fund'!R33 -> 7.4193768 | Q20: Low to Moderate Risk | R20: 1 year and above
A21: CREDIT RISK FUND | B21: =COUNTA('Credit Risk Fund'!$A$12:A25) -> 14 | C21: =SUM('Credit Risk Fund'!$D$12:D25) -> 19611.245 | D21: ='Credit Risk Fund'!F26 -> 10.133821 | E21: ='Credit Risk Fund'!G26 -> 6.2123875 | F21: ='Credit Risk Fund'!H26 -> 6.0516744 | G21: ='Credit Risk Fund'!I26 -> 6.0437784 | H21: ='Credit Risk Fund'!J26 -> 7.0956037 | I21: ='Credit Risk Fund'!K26 -> 8.5523855 | J21: ='Credit Risk Fund'!L26 -> 8.0274158 | K21: ='Credit Risk Fund'!M26 -> 7.4859902 | ... P21: ='Credit Risk Fund'!R26 -> 7.7701852 | Q21: Moderately High Risk | R21: 1 year and above
A22: BANKING AND PSU FUND | B22: =COUNTA('Banking and PSU Fund'!$A$12:A33) -> 21 | C22: =SUM('Banking and PSU Fund'!$D$12:D33) -> 74620.536 | D22: ='Banking and PSU Fund'!F34 -> 6.0849562 | E22: ='Banking and PSU Fund'!G34 -> 3.5933696 | F22: ='Banking and PSU Fund'!H34 -> 3.0352178 | G22: ='Banking and PSU Fund'!I34 -> 2.513271 | H22: ='Banking and PSU Fund'!J34 -> 4.4528002 | I22: ='Banking and PSU Fund'!K34 -> 6.8126548 | J22: ='Banking and PSU Fund'!L34 -> 6.6931729 | K22: ='Banking and PSU Fund'!M34 -> 6.3625287 | ... P22: ='Banking and PSU Fund'!R34 -> 7.3254755 | Q22: Moderate Risk | R22: 2.5 years and above
A23: GILT FUND | B23: =COUNTA('Gilt Fund'!$A$12:A34) -> 23 | C23: =SUM('Gilt Fund'!$D$12:D34) -> 33620.329 | D23: ='Gilt Fund'!F35 -> 14.78146 | E23: ='Gilt Fund'!G35 -> -0.11857476 | F23: ='Gilt Fund'!H35 -> 0.98249071 | G23: ='Gilt Fund'!I35 -> 0.10199944 | H23: ='Gilt Fund'!J35 -> -0.0099855513 | I23: ='Gilt Fund'!K35 -> 5.6803783 | J23: ='Gilt Fund'!L35 -> 5.9714539 | K23: ='Gilt Fund'!M35 -> 6.1390739 | ... P23: ='Gilt Fund'!R35 -> 8.1304676 | Q23: Low to Moderate Risk | R23: 2.5 years and above
A24: GILT FUND WITH 10 YR CONSTANT | B24: =COUNTA('Gilt Fund with 10 yr constant'!$A$12:A16) -> 5 | C24: =SUM('Gilt Fund with 10 yr constant'!D12:D16) -> 4520.8901 | D24: ='Gilt Fund with 10 yr constant'!F17 -> 8.5289767 | E24: ='Gilt Fund with 10 yr constant'!G17 -> -0.93472053 | F24: ='Gilt Fund with 10 yr constant'!H17 -> 1.238809 | G24: ='Gilt Fund with 10 yr constant'!I17 -> -0.68249692 | H24: ='Gilt Fund with 10 yr constant'!J17 -> 1.6709096 | I24: ='Gilt Fund with 10 yr constant'!K17 -> 6.9372475 | J24: ='Gilt Fund with 10 yr constant'!L17 -> 6.660324 | K24: ='Gilt Fund with 10 yr constant'!M17 -> 6.7053704 | ... P24: ='Gilt Fund with 10 yr constant'!R17 -> 7.8424381 | Q24: Low to Moderate Risk | R24: 5 years and above
A25: TARGET MATURITY FUND | B25: =COUNTA('Target Maturity Fund'!$A$12:A121) -> 110 | C25: =SUM('Target Maturity Fund'!$D$12:D121) -> 106289.12 | D25: ='Target Maturity Fund'!F122 -> 6.6095209 | E25: ='Target Maturity Fund'!G122 -> 4.8366798 | F25: ='Target Maturity Fund'!H122 -> 4.7994433 | G25: ='Target Maturity Fund'!I122 -> 4.5572008 | H25: ='Target Maturity Fund'!J122 -> 5.4502887 | I25: ='Target Maturity Fund'!K122 -> 7.3818032 | J25: ='Target Maturity Fund'!L122 -> 7.0781904 | K25: ='Target Maturity Fund'!M122 -> 6.6980808 | ... P25: ='Target Maturity Fund'!R122 -> 6.4879947 | Q25: Moderate Risk | R25: As per maturity date of bonds held
A26: FLOATER FUND | B26: =COUNTA('Floater Fund'!$A$12:A23) -> 12 | C26: =SUM('Floater Fund'!$D$12:D23) -> 51282.888 | D26: ='Floater Fund'!F24 -> 6.0248833 | E26: ='Floater Fund'!G24 -> 5.3090118 | F26: ='Floater Fund'!H24 -> 4.813167 | G26: ='Floater Fund'!I24 -> 4.443736 | H26: ='Floater Fund'!J24 -> 5.9245256 | I26: ='Floater Fund'!K24 -> 7.296562 | J26: ='Floater Fund'!L24 -> 7.4170374 | K26: ='Floater Fund'!M24 -> 6.9993243 | ... P26: ='Floater Fund'!R24 -> 7.5375418 | Q26: Moderate Risk | R26: 1 year and above
A27: HYBRID FUNDS
A28: ARBITRAGE FUND | B28: =COUNTA('Arbitrage Fund'!$A$12:A46) -> 35 | C28: =SUM('Arbitrage Fund'!$D$12:D46) -> 316264.9 | D28: ='Arbitrage Fund'!F47 -> 0.38603361 | E28: ='Arbitrage Fund'!G47 -> 1.3408641 | F28: ='Arbitrage Fund'!H47 -> 3.0020475 | G28: ='Arbitrage Fund'!I47 -> 1.9167655 | H28: ='Arbitrage Fund'!J47 -> 5.8299355 | I28: ='Arbitrage Fund'!K47 -> 6.5697518 | J28: ='Arbitrage Fund'!L47 -> 6.932793 | K28: ='Arbitrage Fund'!M47 -> 6.5479746 | ... P28: ='Arbitrage Fund'!R47 -> 6.522343 | Q28: Low Risk | R28: 3 months and above
A29: CONSERVATIVE HYBRID FUND | B29: =COUNTA('Conservative Hybrid Fund'!$A$12:A29) -> 18 | C29: =SUM('Conservative Hybrid Fund'!$D$12:D29) -> 28692.195 | D29: ='Conservative Hybrid Fund'!F30 -> 2.3874139 | E29: ='Conservative Hybrid Fund'!G30 -> 0.33351821 | F29: ='Conservative Hybrid Fund'!H30 -> 0.10700642 | G29: ='Conservative Hybrid Fund'!I30 -> -0.22014263 | H29: ='Conservative Hybrid Fund'!J30 -> 3.7205085 | I29: ='Conservative Hybrid Fund'!K30 -> 6.4932836 | J29: ='Conservative Hybrid Fund'!L30 -> 9.009678 | K29: ='Conservative Hybrid Fund'!M30 -> 8.4181219 | ... P29: ='Conservative Hybrid Fund'!R30 -> 8.8121181 | Q29: Moderately High Risk | R29: 3 years and above
A30: AGGRESSIVE HYBRID FUND | B30: =COUNTA('Aggressive Hybrid Fund'!$A$12:A40) -> 29 | C30: =SUM('Aggressive Hybrid Fund'!$D$12:D40) -> 232271.45 | D30: ='Aggressive Hybrid Fund'!F41 -> 7.6163049 | E30: ='Aggressive Hybrid Fund'!G41 -> -0.59283167 | F30: ='Aggressive Hybrid Fund'!H41 -> -2.9346608 | G30: ='Aggressive Hybrid Fund'!I41 -> -2.9265187 | H30: ='Aggressive Hybrid Fund'!J41 -> 4.1078665 | I30: ='Aggressive Hybrid Fund'!K41 -> 6.998415 | J30: ='Aggressive Hybrid Fund'!L41 -> 14.012681 | K30: ='Aggressive Hybrid Fund'!M41 -> 11.763209 | ... P30: ='Aggressive Hybrid Fund'!R41 -> 13.895832 | Q30: High Risk | R30: 5 years & above
A31: DYNAMIC ASSET ALLOCATION | B31: =COUNTA('Dynamic Asset Allocation'!$A$12:A27) -> 16 | C31: =SUM('Dynamic Asset Allocation'!$D$12:D27) -> 37266.174 | D31: ='Dynamic Asset Allocation'!F28 -> 4.8642424 | E31: ='Dynamic Asset Allocation'!G28 -> -0.9786927 | F31: ='Dynamic Asset Allocation'!H28 -> -2.4011682 | G31: ='Dynamic Asset Allocation'!I28 -> -2.6562467 | H31: ='Dynamic Asset Allocation'!J28 -> 2.6507188 | I31: ='Dynamic Asset Allocation'!K28 -> 4.9470138 | J31: ='Dynamic Asset Allocation'!L28 -> 10.681231 | K31: ='Dynamic Asset Allocation'!M28 -> 8.7216101 | ... P31: ='Dynamic Asset Allocation'!R28 -> 9.4508622 | Q31: High Risk | R31: 5 years & above
A32: BALANCED ADVANTAGE FUND | B32: =COUNTA('Balanced Advantage'!$A$12:A32) -> 21 | C32: =SUM('Balanced Advantage'!$D$12:D32) -> 268035.58 | D32: ='Balanced Advantage'!F33 -> 5.9049473 | E32: ='Balanced Advantage'!G33 -> -1.4483063 | F32: ='Balanced Advantage'!H33 -> -2.0691659 | G32: ='Balanced Advantage'!I33 -> -2.9181291 | H32: ='Balanced Advantage'!J33 -> 3.8616497 | I32: ='Balanced Advantage'!K33 -> 6.0305338 | J32: ='Balanced Advantage'!L33 -> 13.109438 | K32: ='Balanced Advantage'!M33 -> 12.431201 | ... P32: ='Balanced Advantage'!R33 -> 12.743303 | Q32: High Risk | R32: 5 years & above
A33: BALANCED HYBRID FUND | B33: =COUNTA('Balanced Hybrid'!$A$12:A19) -> 8 | C33: =SUM('Balanced Hybrid'!$D$12:D19) -> 8357.2743 | D33: ='Balanced Hybrid'!F20 -> 3.3640252 | E33: ='Balanced Hybrid'!G20 -> 1.1851306 | F33: ='Balanced Hybrid'!H20 -> 2.3993399 | G33: ='Balanced Hybrid'!I20 -> 0.58183722 | H33: ='Balanced Hybrid'!J20 -> 2.6752259 | I33: ='Balanced Hybrid'!K20 -> 5.81279 | J33: ='Balanced Hybrid'!L20 -> #DIV/0! | K33: ='Balanced Hybrid'!M20 -> #DIV/0! | ... P33: ='Balanced Hybrid'!R20 -> 5.9348923 | Q33: High Risk | R33: 5 years & above
A34: EQUITY SAVINGS | B34: =COUNTA('Equity Savings'!$A$12:A35) -> 24 | C34: =SUM('Equity Savings'!$D$12:D35) -> 52215.468 | D34: ='Equity Savings'!F36 -> 2.6114186 | E34: ='Equity Savings'!G36 -> -0.24175387 | F34: ='Equity Savings'!H36 -> -0.14099753 | G34: ='Equity Savings'!I36 -> -1.0711586 | H34: ='Equity Savings'!J36 -> 4.5534241 | I34: ='Equity Savings'!K36 -> 6.2264232 | J34: ='Equity Savings'!L36 -> 9.2913251 | K34: ='Equity Savings'!M36 -> 8.3564707 | ... P34: ='Equity Savings'!R36 -> 8.267142 | Q34: Moderate Risk | R34: 3 years & above
A35: MULTI ASSET ALLOCATION | B35: =COUNTA('Multi Asset Allocation'!$A$12:A45) -> 34 | C35: =SUM('Multi Asset Allocation'!$D$12:D45) -> 190131.77 | D35: ='Multi Asset Allocation'!F46 -> 5.91913 | E35: ='Multi Asset Allocation'!G46 -> -2.1312043 | F35: ='Multi Asset Allocation'!H46 -> 2.3641828 | G35: ='Multi Asset Allocation'!I46 -> -0.8070121 | H35: ='Multi Asset Allocation'!J46 -> 13.283958 | I35: ='Multi Asset Allocation'!K46 -> 11.833144 | J35: ='Multi Asset Allocation'!L46 -> 17.723547 | K35: ='Multi Asset Allocation'!M46 -> 15.742604 | ... P35: ='Multi Asset Allocation'!R46 -> 16.755659 | Q35: High Risk | R35: 5 years & above
A36: SOLUTION ORIENTED FUNDS
A37: RETIREMENT FUND | B37: =COUNTA('Retirement Fund'!$A$12:A41) -> 29 | C37: =SUM('Retirement Fund'!$D$12:D41) -> 29365.849 | D37: ='Retirement Fund'!F42 -> 8.2195103 | E37: ='Retirement Fund'!G42 -> -1.4903603 | F37: ='Retirement Fund'!H42 -> -3.9273743 | G37: ='Retirement Fund'!I42 -> -3.8227414 | H37: ='Retirement Fund'!J42 -> 2.8911129 | I37: ='Retirement Fund'!K42 -> 4.8892269 | J37: ='Retirement Fund'!L42 -> 13.625051 | K37: ='Retirement Fund'!M42 -> 12.174144 | ... P37: ='Retirement Fund'!R42 -> 13.047159 | Q37: -- | R37: --
A38: CHILDRENS FUNDS | B38: =COUNTA('Childrens Funds'!$A$12:A23) -> 12 | C38: =SUM('Childrens Funds'!$D$12:D23) -> 23680.665 | D38: ='Childrens Funds'!F24 -> 8.2546376 | E38: ='Childrens Funds'!G24 -> -0.34609214 | F38: ='Childrens Funds'!H24 -> -3.3071288 | G38: ='Childrens Funds'!I24 -> -2.771338 | H38: ='Childrens Funds'!J24 -> 4.4030584 | I38: ='Childrens Funds'!K24 -> 6.4217826 | J38: ='Childrens Funds'!L24 -> 13.629282 | K38: ='Childrens Funds'!M24 -> 12.167997 | ... P38: ='Childrens Funds'!R24 -> 16.870995 | Q38: -- | R38: --
A39: EQUITY FUNDS
A40: MULTI CAP FUND | B40: =COUNTA('Multi Cap Fund'!$A$12:A43) -> 32 | C40: =SUM('Multi Cap Fund'!$D$12:D43) -> 201314.63 | D40: ='Multi Cap Fund'!F44 -> 11.696746 | E40: ='Multi Cap Fund'!G44 -> 1.5328805 | F40: ='Multi Cap Fund'!H44 -> -3.8070371 | G40: ='Multi Cap Fund'!I44 -> -2.3902283 | H40: ='Multi Cap Fund'!J44 -> 6.2765106 | I40: ='Multi Cap Fund'!K44 -> 5.9915714 | J40: ='Multi Cap Fund'!L44 -> 19.008077 | K40: ='Multi Cap Fund'!M44 -> 16.320301 | ... P40: ='Multi Cap Fund'!R44 -> 14.831759 | Q40: Very High Risk | R40: 5 years & above
A41: FLEXI CAP FUND | B41: =COUNTA('Flexi Cap Fund'!$A$12:A54) -> 43 | C41: =SUM('Flexi Cap Fund'!$D$12:D54) -> 504339.78 | D41: ='Flexi Cap Fund'!F55 -> 8.5565035 | E41: ='Flexi Cap Fund'!G55 -> -2.6766087 | F41: ='Flexi Cap Fund'!H55 -> -5.482381 | G41: ='Flexi Cap Fund'!I55 -> -4.9709928 | H41: ='Flexi Cap Fund'!J55 -> 2.8068011 | I41: ='Flexi Cap Fund'!K55 -> 6.522511 | J41: ='Flexi Cap Fund'!L55 -> 16.180062 | K41: ='Flexi Cap Fund'!M55 -> 13.906942 | ... P41: ='Flexi Cap Fund'!R55 -> 15.934371 | Q41: Very High Risk | R41: 5 years & above
A42: LARGE CAP FUND | B42: =COUNTA('Large Cap Fund'!$A$12:A45) -> 34 | C42: =SUM('Large Cap Fund'!$D$12:D45) -> 367888.15 | D42: ='Large Cap Fund'!F46 -> 7.9215138 | E42: ='Large Cap Fund'!G46 -> -4.1328772 | F42: ='Large Cap Fund'!H46 -> -6.329386 | G42: ='Large Cap Fund'!I46 -> -6.939118 | H42: ='Large Cap Fund'!J46 -> 0.33237781 | I42: ='Large Cap Fund'!K46 -> 4.3173211 | J42: ='Large Cap Fund'!L46 -> 13.191695 | K42: ='Large Cap Fund'!M46 -> 11.712268 | ... P42: ='Large Cap Fund'!R46 -> 13.919457 | Q42: Very High Risk | R42: 5 years & above
A43: LARGE & MID CAP FUND | B43: =COUNTA('Large & Mid Cap Fund'!$A$12:A44) -> 33 | C43: =SUM('Large & Mid Cap Fund'!$D$12:D44) -> 299876.38 | D43: ='Large & Mid Cap Fund'!F45 -> 10.345332 | E43: ='Large & Mid Cap Fund'!G45 -> -0.7974009 | F43: ='Large & Mid Cap Fund'!H45 -> -4.075991 | G43: ='Large & Mid Cap Fund'!I45 -> -3.7412171 | H43: ='Large & Mid Cap Fund'!J45 -> 5.9366458 | I43: ='Large & Mid Cap Fund'!K45 -> 6.7070286 | J43: ='Large & Mid Cap Fund'!L45 -> 17.774746 | K43: ='Large & Mid Cap Fund'!M45 -> 14.744133 | ... P43: ='Large & Mid Cap Fund'!R45 -> 15.870797 | Q43: Very High Risk | R43: 5 years & above
A44: MID CAP FUND | B44: =COUNTA('Mid Cap Fund'!$A$12:A42) -> 31 | C44: =SUM('Mid Cap Fund'!$D$12:D42) -> 418987.58 | D44: ='Mid Cap Fund'!F43 -> 11.846896 | E44: ='Mid Cap Fund'!G43 -> 1.9883406 | F44: ='Mid Cap Fund'!H43 -> -2.297054 | G44: ='Mid Cap Fund'!I43 -> -1.2981203 | H44: ='Mid Cap Fund'!J43 -> 10.018814 | I44: ='Mid Cap Fund'!K43 -> 9.221867 | J44: ='Mid Cap Fund'!L43 -> 21.817156 | K44: ='Mid Cap Fund'!M43 -> 17.842843 | ... P44: ='Mid Cap Fund'!R43 -> 17.506018 | Q44: Very High Risk | R44: 5 years & above
A45: SMALL CAP FUND | B45: =COUNTA('Small Cap Fund'!$A$12:A47) -> 36 | C45: =SUM('Small Cap Fund'!$D$12:D47) -> 334825.68 | D45: ='Small Cap Fund'!F48 -> 15.125663 | E45: ='Small Cap Fund'!G48 -> 5.5750257 | F45: ='Small Cap Fund'!H48 -> -2.936266 | G45: ='Small Cap Fund'!I48 -> 0.64872643 | H45: ='Small Cap Fund'!J48 -> 9.3523188 | I45: ='Small Cap Fund'!K48 -> 4.9179861 | J45: ='Small Cap Fund'!L48 -> 19.082073 | K45: ='Small Cap Fund'!M48 -> 16.15617 | ... P45: ='Small Cap Fund'!R48 -> 18.250239 | Q45: Very High Risk | R45: 5 years & above
A46: DIVIDEND YIELD FUND | B46: =COUNTA('Dividend Yield Fund'!$A$12:A22) -> 11 | C46: =SUM('Dividend Yield Fund'!$D$12:D22) -> 29076.32 | D46: ='Dividend Yield Fund'!F23 -> 8.4457475 | E46: ='Dividend Yield Fund'!G23 -> -2.5895443 | F46: ='Dividend Yield Fund'!H23 -> -3.7206938 | G46: ='Dividend Yield Fund'!I23 -> -3.9396369 | H46: ='Dividend Yield Fund'!J23 -> 3.83086 | I46: ='Dividend Yield Fund'!K23 -> 4.5382097 | J46: ='Dividend Yield Fund'!L23 -> 16.452254 | K46: ='Dividend Yield Fund'!M23 -> 15.38061 | ... P46: ='Dividend Yield Fund'!R23 -> 14.447183 | Q46: Very High Risk | R46: 5 years & above
A47: VALUE / CONTRA FUND | B47: =COUNTA('Value Fund'!$A$12:A36) -> 25 | C47: =SUM('Value Fund'!$D$12:D36) -> 194063.8 | D47: ='Value Fund'!F37 -> 8.1726452 | E47: ='Value Fund'!G37 -> -3.3271803 | F47: ='Value Fund'!H37 -> -4.7347736 | G47: ='Value Fund'!I37 -> -5.8876871 | H47: ='Value Fund'!J37 -> 2.9510852 | I47: ='Value Fund'!K37 -> 5.2656871 | J47: ='Value Fund'!L37 -> 17.690105 | K47: ='Value Fund'!M37 -> 15.702258 | ... P47: ='Value Fund'!R37 -> 17.144313 | Q47: Very High Risk | R47: 5 years & above
A48: FOCUSED FUND | B48: =COUNTA('Focused Fund'!$A$12:A39) -> 28 | C48: =SUM('Focused Fund'!$D$12:D39) -> 156095.38 | D48: ='Focused Fund'!F40 -> 10.5548 | E48: ='Focused Fund'!G40 -> -1.6603989 | F48: ='Focused Fund'!H40 -> -3.9694406 | G48: ='Focused Fund'!I40 -> -4.2543117 | H48: ='Focused Fund'!J40 -> 5.0241263 | I48: ='Focused Fund'!K40 -> 7.1694582 | J48: ='Focused Fund'!L40 -> 16.270803 | K48: ='Focused Fund'!M40 -> 13.380514 | ... P48: ='Focused Fund'!R40 -> 15.105453 | Q48: Very High Risk | R48: 5 years & above
A49: SECTOR-BANKING FUND | B49: =COUNTA('Sec-Bank'!$A$12:A39) -> 28 | C49: =SUM('Sec-Bank'!$D$12:D39) -> 50091.02 | D49: ='Sec-Bank'!F40 -> 9.9592877 | E49: ='Sec-Bank'!G40 -> -5.2978653 | F49: ='Sec-Bank'!H40 -> -4.2406457 | G49: ='Sec-Bank'!I40 -> -5.9745262 | H49: ='Sec-Bank'!J40 -> 3.4695438 | I49: ='Sec-Bank'!K40 -> 8.6455551 | J49: ='Sec-Bank'!L40 -> 14.865067 | K49: ='Sec-Bank'!M40 -> 14.442691 | ... P49: ='Sec-Bank'!R40 -> 14.763679 | Q49: Very High Risk | R49: 5 years & above
A50: SECTOR-CONSUMPTION FUND | B50: =COUNTA('Sec-Consumption'!$A$12:A36) -> 25 | C50: =SUM('Sec-Consumption'!$D$12:D36) -> 35928.478 | D50: ='Sec-Consumption'!F37 -> 10.782145 | E50: ='Sec-Consumption'!G37 -> -0.19646211 | F50: ='Sec-Consumption'!H37 -> -9.0190888 | G50: ='Sec-Consumption'!I37 -> -6.9492711 | H50: ='Sec-Consumption'!J37 -> -1.6123257 | I50: ='Sec-Consumption'!K37 -> 3.0008618 | J50: ='Sec-Consumption'!L37 -> 12.728986 | K50: ='Sec-Consumption'!M37 -> 11.700674 | ... P50: ='Sec-Consumption'!R37 -> 10.270667 | Q50: Very High Risk | R50: 5 years & above
A51: SECTOR-ENERGY & POWER FUND | B51: =COUNTA('Sec-Energy & Power'!$A$11:A17) -> 7 | C51: =SUM('Sec-Energy & Power'!$D$11:D17) -> 27235.769 | D51: ='Sec-Energy & Power'!F18 -> 14.609436 | E51: ='Sec-Energy & Power'!G18 -> 10.314132 | F51: ='Sec-Energy & Power'!H18 -> 6.7771544 | G51: ='Sec-Energy & Power'!I18 -> 8.4242416 | H51: ='Sec-Energy & Power'!J18 -> 17.423337 | I51: ='Sec-Energy & Power'!K18 -> 6.1299196 | J51: ='Sec-Energy & Power'!L18 -> 25.40598 | K51: ='Sec-Energy & Power'!M18 -> 22.442147 | ... P51: ='Sec-Energy & Power'!R18 -> 11.140507 | Q51: Very High Risk | R51: 5 years & above
A52: SECTOR-MNC FUND | B52: =COUNTA('Sec-MNC'!$A$12:A18) -> 7 | C52: =SUM('Sec-MNC'!$D$12:D18) -> 14976.747 | D52: ='Sec-MNC'!F19 -> 11.719214 | E52: ='Sec-MNC'!G19 -> 3.6315349 | F52: ='Sec-MNC'!H19 -> -0.73601726 | G52: ='Sec-MNC'!I19 -> 0.3350666 | H52: ='Sec-MNC'!J19 -> 8.2248045 | I52: ='Sec-MNC'!K19 -> 3.6647681 | J52: ='Sec-MNC'!L19 -> 10.768951 | K52: ='Sec-MNC'!M19 -> 9.2617877 | ... P52: ='Sec-MNC'!R19 -> 13.546925 | Q52: Very High Risk | R52: 5 years & above
A53: SECTOR-PHARMA & HEALTHCARE FUND | B53: =COUNTA('Sec-Pharma'!$A$11:A28) -> 18 | C53: =SUM('Sec-Pharma'!$D$11:D28) -> 31810.024 | D53: ='Sec-Pharma'!F29 -> 6.8958706 | E53: ='Sec-Pharma'!G29 -> 7.1108111 | F53: ='Sec-Pharma'!H29 -> 0.40219496 | G53: ='Sec-Pharma'!I29 -> 2.1053313 | H53: ='Sec-Pharma'!J29 -> 6.217294 | I53: ='Sec-Pharma'!K29 -> 12.29694 | J53: ='Sec-Pharma'!L29 -> 23.877008 | K53: ='Sec-Pharma'!M29 -> 17.150727 | ... P53: ='Sec-Pharma'!R29 -> 17.962507 | Q53: Very High Risk | R53: 5 years & above
A54: SECTOR-SERVICE INDUSTRY FUND | B54: =COUNTA('Sec-Service'!$A$11:A15) -> 5 | C54: =SUM('Sec-Service'!$D$11:D15) -> 7648.4743 | D54: ='Sec-Service'!F16 -> 9.7604084 | E54: ='Sec-Service'!G16 -> -3.1037567 | F54: ='Sec-Service'!H16 -> -7.8580829 | G54: ='Sec-Service'!I16 -> -6.991788 | H54: ='Sec-Service'!J16 -> 1.6786348 | I54: ='Sec-Service'!K16 -> 7.7134918 | J54: ='Sec-Service'!L16 -> 16.400645 | K54: ='Sec-Service'!M16 -> 13.725393 | ... P54: ='Sec-Service'!R16 -> 10.387646 | Q54: Very High Risk | R54: 5 years & above
A55: SECTOR-TECHNOLOGY | B55: =COUNTA('Sec-Tech'!$A$12:A24) -> 13 | C55: =SUM('Sec-Tech'!$D$12:D24) -> 34919.857 | D55: ='Sec-Tech'!F25 -> 5.5775298 | E55: ='Sec-Tech'!G25 -> -16.517905 | F55: ='Sec-Tech'!H25 -> -16.681429 | G55: ='Sec-Tech'!I25 -> -18.652959 | H55: ='Sec-Tech'!J25 -> -9.3340938 | I55: ='Sec-Tech'!K25 -> -0.39949855 | J55: ='Sec-Tech'!L25 -> 9.5211843 | K55: ='Sec-Tech'!M25 -> 4.5836005 | ... P55: ='Sec-Tech'!R25 -> 11.632915 | Q55: Very High Risk | R55: 5 years & above
A56: THEMATIC FUND | B56: =COUNTA(Thematic!$A$12:A131) -> 120 | C56: =SUM(Thematic!$D$12:D131) -> 225597.51 | D56: =Thematic!F132 -> 10.649814 | E56: =Thematic!G132 -> 0.026909389 | F56: =Thematic!H132 -> -2.619184 | G56: =Thematic!I132 -> -2.3581758 | H56: =Thematic!J132 -> 8.2077644 | I56: =Thematic!K132 -> 7.1964723 | J56: =Thematic!L132 -> 20.492523 | K56: =Thematic!M132 -> 17.72248 | ... P56: =Thematic!R132 -> 13.346533 | Q56: Very High Risk | R56: 5 years & above
A57: THEMATIC-INFRASTRUCTURE FUND | B57: =COUNTA('Them-Infra'!$A$12:A31) -> 20 | C57: =SUM('Them-Infra'!$D$12:D31) -> 39171.41 | D57: ='Them-Infra'!F32 -> 15.556829 | E57: ='Them-Infra'!G32 -> 7.2324376 | F57: ='Them-Infra'!H32 -> 1.4349968 | G57: ='Them-Infra'!I32 -> 4.1292512 | H57: ='Them-Infra'!J32 -> 12.137248 | I57: ='Them-Infra'!K32 -> 5.3847347 | J57: ='Them-Infra'!L32 -> 23.337276 | K57: ='Them-Infra'!M32 -> 21.173655 | ... P57: ='Them-Infra'!R32 -> 13.032611 | Q57: Very High Risk | R57: 5 years & above
A58: ELSS FUND | B58: =COUNTA(ELSS!$A$12:A51) -> 40 | C58: =SUM(ELSS!$D$12:D51) -> 217121.77 | D58: =ELSS!F52 -> 9.6220752 | E58: =ELSS!G52 -> -1.859368 | F58: =ELSS!H52 -> -5.1319947 | G58: =ELSS!I52 -> -4.7795689 | H58: =ELSS!J52 -> 2.7734438 | I58: =ELSS!K52 -> 4.8791701 | J58: =ELSS!L52 -> 16.075764 | K58: =ELSS!M52 -> 13.120158 | ... P58: =ELSS!R52 -> 15.596213 | Q58: Very High Risk | R58: 5 years & above
A59: INTERNATIONAL FUND | B59: =COUNTA(Global!$A$12:A19) -> 6 | C59: =SUM(Global!$D$12:D19) -> 5740.788 | D59: =Global!F20 -> 9.3789092 | E59: =Global!G20 -> 6.638354 | F59: =Global!H20 -> 16.851241 | G59: =Global!I20 -> 11.691292 | H59: =Global!J20 -> 51.000628 | I59: =Global!K20 -> 21.384238 | J59: =Global!L20 -> 20.638402 | K59: =Global!M20 -> 17.498265 | ... P59: =Global!R20 -> 15.683717
A60: OTHER FUNDS
A61: INDEX FUNDS | B61: =COUNTA('Index Funds'!$A$12:A252) -> 241 | C61: =SUM('Index Funds'!$D$12:D252) -> 701794.25 | D61: ='Index Funds'!F253 -> 7.7677971 | E61: ='Index Funds'!G253 -> -4.7504861 | F61: ='Index Funds'!H253 -> -6.2617222 | G61: ='Index Funds'!I253 -> -7.0983887 | H61: ='Index Funds'!J253 -> 0.54848248 | I61: ='Index Funds'!K253 -> 4.0944422 | J61: ='Index Funds'!L253 -> 11.97633 | K61: ='Index Funds'!M253 -> 11.015172 | ... P61: ='Index Funds'!R253 -> 12.600588 | Q61: Very High Risk | R61: 5 years & above
A62: INDEX NIFTY FUND | B62: =COUNTA('Index Nifty'!$A$12:A37) -> 26 | C62: =SUM('Index Nifty'!$D$12:D37) -> 87170.565 | D62: ='Index Nifty'!F38 -> 7.4382534 | E62: ='Index Nifty'!G38 -> -5.2485262 | F62: ='Index Nifty'!H38 -> -7.2728344 | G62: ='Index Nifty'!I38 -> -8.1551603 | H62: ='Index Nifty'!J38 -> -0.66742874 | I62: ='Index Nifty'!K38 -> 3.8137033 | J62: ='Index Nifty'!L38 -> 10.691061 | K62: ='Index Nifty'!M38 -> 9.6110422 | ... P62: ='Index Nifty'!R38 -> 12.503799 | Q62: Very High Risk | R62: 5 years & above
A63: INDEX NIFTY NEXT 50 FUND | B63: =COUNTA('Index-Nifty Next 50'!$A$12:A30) -> 19 | C63: =SUM('Index-Nifty Next 50'!$D$12:D30) -> 21519.112 | D63: ='Index-Nifty Next 50'!F31 -> 15.354981 | E63: ='Index-Nifty Next 50'!G31 -> 2.7886334 | F63: ='Index-Nifty Next 50'!H31 -> -0.60608913 | G63: ='Index-Nifty Next 50'!I31 -> 0.49508342 | H63: ='Index-Nifty Next 50'!J31 -> 8.2023908 | I63: ='Index-Nifty Next 50'!K31 -> 3.6058769 | J63: ='Index-Nifty Next 50'!L31 -> 20.672481 | K63: ='Index-Nifty Next 50'!M31 -> 13.048741 | ... P63: ='Index-Nifty Next 50'!R31 -> 12.449341 | Q63: Very High Risk | R63: 5 years & above
A64: INDEX SENSEX FUND | B64: =COUNTA('Index - Sensex'!$A$12:A22) -> 11 | C64: =SUM('Index - Sensex'!$D$12:D22) -> 11466.098 | D64: ='Index - Sensex'!F23 -> 6.9005154 | E64: ='Index - Sensex'!G23 -> -6.5325612 | F64: ='Index - Sensex'!H23 -> -8.9200741 | G64: ='Index - Sensex'!I23 -> -9.7702754 | H64: ='Index - Sensex'!J23 -> -3.4386501 | I64: ='Index - Sensex'!K23 -> 2.3754818 | J64: ='Index - Sensex'!L23 -> 8.796018 | K64: ='Index - Sensex'!M23 -> 8.5904349 | ... P64: ='Index - Sensex'!R23 -> 12.845086 | Q64: Very High Risk | R64: 5 years & above
A65: INDEX OTHERS FUND | B65: =COUNTA('Index Fund Others'!$A$12:A209) -> 198 | C65: =SUM('Index Fund Others'!$D$12:D209) -> 80592.542 | D65: ='Index Fund Others'!F210 -> 12.779515 | E65: ='Index Fund Others'!G210 -> 1.0781074 | F65: ='Index Fund Others'!H210 -> -1.3863277 | G65: ='Index Fund Others'!I210 -> -0.75563327 | H65: ='Index Fund Others'!J210 -> 10.403252 | I65: ='Index Fund Others'!K210 -> 5.8378109 | J65: ='Index Fund Others'!L210 -> 19.004024 | K65: ='Index Fund Others'!M210 -> 14.945471 | ... P65: ='Index Fund Others'!R210 -> 12.553026 | Q65: Very High Risk | R65: 5 years & above
A66: ETFS - GOLD FUND | B66: =COUNTA('ETFs - Gold'!$A$12:A66) -> 55 | C66: =SUM('ETFs - Gold'!$D$12:D66) -> 237716.27 | D66: ='ETFs - Gold'!F67 -> 2.3777457 | E66: ='ETFs - Gold'!G67 -> -8.5409608 | F66: ='ETFs - Gold'!H67 -> 24.683895 | G66: ='ETFs - Gold'!I67 -> 12.187232 | H66: ='ETFs - Gold'!J67 -> 58.018304 | I66: ='ETFs - Gold'!K67 -> 43.274056 | J66: ='ETFs - Gold'!L67 -> 34.207324 | K66: ='ETFs - Gold'!M67 -> 28.73752 | ... P66: ='ETFs - Gold'!R67 -> 17.843729 | Q66: High Risk | R66: 3 years & above
A67: ETFS - SILVER FUND | B67: =COUNTA('ETFs - Silver'!$A$12:A45) -> 34 | C67: =SUM('ETFs - Silver'!$D$12:D45) -> 103635.34 | D67: ='ETFs - Silver'!F46 -> 4.7738584 | E67: ='ETFs - Silver'!G46 -> -26.710599 | F67: ='ETFs - Silver'!H46 -> 61.868545 | G67: ='ETFs - Silver'!I46 -> 4.3878694 | H67: ='ETFs - Silver'!J46 -> 148.55489 | I67: ='ETFs - Silver'!K46 -> 70.234408 | J67: ='ETFs - Silver'!L46 -> 45.780293 | K67: ='ETFs - Silver'!M46 -> 36.795587 | ... P67: ='ETFs - Silver'!R46 -> 47.28171 | Q67: High Risk | R67: 3 years & above
A68: ETFS - OTHERS | B68: =COUNTA('ETFs - Others'!$A$12:A18) -> 6 | C68: =SUM('ETFs - Others'!$D$12:D18) -> 16656.745 | D68: ='ETFs - Others'!F19 -> 19.067063 | E68: ='ETFs - Others'!G19 -> 9.0725757 | F68: ='ETFs - Others'!H19 -> 10.623085 | G68: ='ETFs - Others'!I19 -> 12.24881 | H68: ='ETFs - Others'!J19 -> 52.081317 | I68: ='ETFs - Others'!K19 -> 33.928773 | J68: ='ETFs - Others'!L19 -> 34.428131 | K68: ='ETFs - Others'!M19 -> 27.172307 | ... P68: ='ETFs - Others'!R19 -> 22.305152 | Q68: -- | R68: --
A69: FOF - DEBT ORIENTED FUND | B69: =COUNTA('FOF-Debt Oriented'!$A$12:A31) -> 20 | C69: =SUM('FOF-Debt Oriented'!$D$12:D31) -> 27504.801 | D69: ='FOF-Debt Oriented'!F32 -> 1.7388595 | E69: ='FOF-Debt Oriented'!G32 -> 0.28695067 | F69: ='FOF-Debt Oriented'!H32 -> 0.20173881 | G69: ='FOF-Debt Oriented'!I32 -> -0.3468234 | H69: ='FOF-Debt Oriented'!J32 -> 3.3556706 | I69: ='FOF-Debt Oriented'!K32 -> 7.0418435 | J69: ='FOF-Debt Oriented'!L32 -> 7.669575 | K69: ='FOF-Debt Oriented'!M32 -> 7.5134894 | ... P69: ='FOF-Debt Oriented'!R32 -> 7.4466876 | Q69: Very High Risk | R69: 5 years & above
A70: FOF - EQUITY ORIENTED FUND | B70: =COUNTA('FOF-Equity Oriented'!$A$12:A73) -> 61 | C70: =SUM('FOF-Equity Oriented'!$D$12:D73) -> 35204.499 | D70: ='FOF-Equity Oriented'!F74 -> 9.4388455 | E70: ='FOF-Equity Oriented'!G74 -> -1.1612333 | F70: ='FOF-Equity Oriented'!H74 -> -3.6224015 | G70: ='FOF-Equity Oriented'!I74 -> -3.4750972 | H70: ='FOF-Equity Oriented'!J74 -> 4.5295087 | I70: ='FOF-Equity Oriented'!K74 -> 4.814328 | J70: ='FOF-Equity Oriented'!L74 -> 15.714668 | K70: ='FOF-Equity Oriented'!M74 -> 13.924855 | ... P70: ='FOF-Equity Oriented'!R74 -> 13.314906 | Q70: Very High Risk | R70: 5 years & above
A71: FOF - OVERSEAS / ETFs | B71: =COUNTA('FoF - Overseas'!$A$12:A67) -> 56 | C71: =SUM('FoF - Overseas'!$D$12:D67) -> 45728.876 | D71: ='FoF - Overseas'!F68 -> 17.147409 | E71: ='FoF - Overseas'!G68 -> 10.506189 | F71: ='FoF - Overseas'!H68 -> 13.354204 | G71: ='FoF - Overseas'!I68 -> 14.692972 | H71: ='FoF - Overseas'!J68 -> 53.687903 | I71: ='FoF - Overseas'!K68 -> 29.993186 | J71: ='FoF - Overseas'!L68 -> 29.49912 | K71: ='FoF - Overseas'!M68 -> 22.302082 | ... P71: ='FoF - Overseas'!R68 -> 17.273003 | Q71: Very High Risk | R71: 5 years & above
A72: FOF - DOMESTIC / ETFs | B72: =COUNTA('FOF-Domestic'!$A$12:A57) -> 46 | C72: =SUM('FOF-Domestic'!$D$12:D57) -> 75789.412 | D72: ='FOF-Domestic'!F58 -> 3.7016658 | E72: ='FOF-Domestic'!G58 -> -1.0336194 | F72: ='FOF-Domestic'!H58 -> -0.56002188 | G72: ='FOF-Domestic'!I58 -> -1.2307349 | H72: ='FOF-Domestic'!J58 -> 5.2634606 | I72: ='FOF-Domestic'!K58 -> 8.2160865 | J72: ='FOF-Domestic'!L58 -> 12.395784 | K72: ='FOF-Domestic'!M58 -> 11.917226 | ... P72: ='FOF-Domestic'!R58 -> 10.693597 | Q72: -- | R72: --

Sheet Overnight Fund
A1: Main Page | E1: Data Source: ACEMF | CA1: Quartile code | CB1: 7 Days | CC1: 14 Days | CD1: 21 Days | CE1: 1 Month | CF1: 3 Month | CG1: 6 Months | CH1: YTD | CI1: 1 Year | CJ1: 2 Year | CK1: 3 Year | CL1: 4 Years | CM1: 5 Years | CN1: 7 Years | CO1: 10 Years | CP1: 15 Years | CQ1: Inception
CA2: 0 | CB2: =_xlfn.QUARTILE.INC(F$12:F$48,$CA2) -> 4.6846 | CC2: =_xlfn.QUARTILE.INC(G$12:G$48,$CA2) -> 4.6803 | CD2: =_xlfn.QUARTILE.INC(H$12:H$48,$CA2) -> 4.5315 | CE2: =_xlfn.QUARTILE.INC(I$12:I$48,$CA2) -> 4.4993 | CF2: =_xlfn.QUARTILE.INC(J$12:J$48,$CA2) -> 4.4888 | CG2: =_xlfn.QUARTILE.INC(K$12:K$48,$CA2) -> 4.6815 | CH2: =_xlfn.QUARTILE.INC(L$12:L$48,$CA2) -> 4.5711 | CI2: =_xlfn.QUARTILE.INC(M$12:M$48,$CA2) -> 4.9267 | ... CQ2: =_xlfn.QUARTILE.INC(U$12:U$48,$CA2) -> 4.825
CA3: 1 | CB3: =_xlfn.QUARTILE.INC(F$12:F$48,$CA3) -> 4.84975 | CC3: =_xlfn.QUARTILE.INC(G$12:G$48,$CA3) -> 4.84805 | CD3: =_xlfn.QUARTILE.INC(H$12:H$48,$CA3) -> 4.79775 | CE3: =_xlfn.QUARTILE.INC(I$12:I$48,$CA3) -> 4.9181 | CF3: =_xlfn.QUARTILE.INC(J$12:J$48,$CA3) -> 4.867 | CG3: =_xlfn.QUARTILE.INC(K$12:K$48,$CA3) -> 5.0508 | CH3: =_xlfn.QUARTILE.INC(L$12:L$48,$CA3) -> 4.93475 | CI3: =_xlfn.QUARTILE.INC(M$12:M$48,$CA3) -> 5.268725 | ... CQ3: =_xlfn.QUARTILE.INC(U$12:U$48,$CA3) -> 5.01595
CA4: 2 | CB4: =_xlfn.QUARTILE.INC(F$12:F$48,$CA4) -> 4.8991 | CC4: =_xlfn.QUARTILE.INC(G$12:G$48,$CA4) -> 4.8905 | CD4: =_xlfn.QUARTILE.INC(H$12:H$48,$CA4) -> 4.8663 | CE4: =_xlfn.QUARTILE.INC(I$12:I$48,$CA4) -> 5.0043 | CF4: =_xlfn.QUARTILE.INC(J$12:J$48,$CA4) -> 4.9435 | CG4: =_xlfn.QUARTILE.INC(K$12:K$48,$CA4) -> 5.1061 | CH4: =_xlfn.QUARTILE.INC(L$12:L$48,$CA4) -> 5.0136 | CI4: =_xlfn.QUARTILE.INC(M$12:M$48,$CA4) -> 5.3073 | ... CQ4: =_xlfn.QUARTILE.INC(U$12:U$48,$CA4) -> 5.0823
CA5: 3 | CB5: =_xlfn.QUARTILE.INC(F$12:F$48,$CA5) -> 4.9409 | CC5: =_xlfn.QUARTILE.INC(G$12:G$48,$CA5) -> 4.93095 | CD5: =_xlfn.QUARTILE.INC(H$12:H$48,$CA5) -> 4.9063 | CE5: =_xlfn.QUARTILE.INC(I$12:I$48,$CA5) -> 5.0422 | CF5: =_xlfn.QUARTILE.INC(J$12:J$48,$CA5) -> 4.98285 | CG5: =_xlfn.QUARTILE.INC(K$12:K$48,$CA5) -> 5.13935 | CH5: =_xlfn.QUARTILE.INC(L$12:L$48,$CA5) -> 5.04955 | CI5: =_xlfn.QUARTILE.INC(M$12:M$48,$CA5) -> 5.337625 | ... CQ5: =_xlfn.QUARTILE.INC(U$12:U$48,$CA5) -> 5.85415
CB6: =_xlfn.QUARTILE.INC(F$12:F$48,$CA6) -> 4.6846 | CC6: =_xlfn.QUARTILE.INC(G$12:G$48,$CA6) -> 4.6803 | CD6: =_xlfn.QUARTILE.INC(H$12:H$48,$CA6) -> 4.5315 | CE6: =_xlfn.QUARTILE.INC(I$12:I$48,$CA6) -> 4.4993 | CF6: =_xlfn.QUARTILE.INC(J$12:J$48,$CA6) -> 4.4888 | CG6: =_xlfn.QUARTILE.INC(K$12:K$48,$CA6) -> 4.6815 | CH6: =_xlfn.QUARTILE.INC(L$12:L$48,$CA6) -> 4.5711 | CI6: =_xlfn.QUARTILE.INC(M$12:M$48,$CA6) -> 4.9267 | ... CQ6: =_xlfn.QUARTILE.INC(U$12:U$48,$CA6) -> 4.825
A7: Fund Barometer - Overnight Fund | CA7: 4 | CB7: =_xlfn.QUARTILE.INC(F$12:F$48,$CA7) -> 5.0353 | CC7: =_xlfn.QUARTILE.INC(G$12:G$48,$CA7) -> 5.0483 | CD7: =_xlfn.QUARTILE.INC(H$12:H$48,$CA7) -> 4.952 | CE7: =_xlfn.QUARTILE.INC(I$12:I$48,$CA7) -> 5.1492 | CF7: =_xlfn.QUARTILE.INC(J$12:J$48,$CA7) -> 5.0749 | CG7: =_xlfn.QUARTILE.INC(K$12:K$48,$CA7) -> 5.231 | CH7: =_xlfn.QUARTILE.INC(L$12:L$48,$CA7) -> 5.1515 | CI7: =_xlfn.QUARTILE.INC(M$12:M$48,$CA7) -> 5.4694 | ... CQ7: =_xlfn.QUARTILE.INC(U$12:U$48,$CA7) -> 6.4118
A8: ='Money Market Fund'!A8 -> (As on 30 Apr 2026) | B8: Value Information | F8: Simple Annualized (%) | M8: Compound Annualized (%) | U8: Since Inception | V8: Quartile | AL8: Credit Quality | AO8: Modified Duration (Years) | AP8: Average Maturity (Years) | AQ8: YTM | AR8: Expense Ratio(%)
A9: Scheme Name | B9: Launch Date | C9: Fund Size (Rs Crs) Feb26 | D9: Fund Size (Rs Crs) Mar26 | E9: Latest NAV(Rs) | F9: 7 Days | G9: 14 Days | H9: 21 Days | I9: 1 Month | J9: 3 Months | K9: 6 Months | L9: YTD | M9: 1 Year | N9: 2 Years | O9: 3 Years | P9: 4 Years | Q9: 5 Years | R9: 7 Years | S9: 10 Years | T9: 15 Years | V9: 7 Days | W9: 14 Days | X9: 21 Days | Y9: 1 Month | Z9: 3 Months | AA9: 6 Months | AB9: YTD | AC9: 1 Year | AD9: 2 Years | AE9: 3 Years | AF9: 4 Years | AG9: 5 Years | AH9: 7 Years | AI9: 10 Years | AJ9: 15 Years | AK9: Since Inception | AL9: AA minus and Above | AM9: Below AA minus | AN9: Cash & Cash Equivalent
A10: To view Exit Loads of any Scheme in this group please click here
A11: Overnight Fund
A12: 360 ONE Overnight Fund-Reg(G) | B12: 45848 | C12: 316.1342 | D12: 443.5598 | E12: 1043.0495 | F12: 4.9533 | G12: 5.0483 | H12: 4.952 | I12: 5.0611 | J12: 5.0247 | K12: 5.2046 | L12: 5.1009 | U12: 5.3721 | V12: =IF(F12="",0,IF(F12<=CB$3,4,IF(F12>=CB$5,1,IF(F12>=CB$4,2,3)))) -> 1 | W12: =IF(G12="",0,IF(G12<=CC$3,4,IF(G12>=CC$5,1,IF(G12>=CC$4,2,3)))) -> 1 | X12: =IF(H12="",0,IF(H12<=CD$3,4,IF(H12>=CD$5,1,IF(H12>=CD$4,2,3)))) -> 1 | Y12: =IF(I12="",0,IF(I12<=CE$3,4,IF(I12>=CE$5,1,IF(I12>=CE$4,2,3)))) -> 1 | Z12: =IF(J12="",0,IF(J12<=CF$3,4,IF(J12>=CF$5,1,IF(J12>=CF$4,2,3)))) -> 1 | AA12: =IF(K12="",0,IF(K12<=CG$3,4,IF(K12>=CG$5,1,IF(K12>=CG$4,2,3)))) -> 1 | AB12: =IF(L12="",0,IF(L12<=CH$3,4,IF(L12>=CH$5,1,IF(L12>=CH$4,2,3)))) -> 1 | AC12: =IF(M12="",0,IF(M12<=CI$3,4,IF(M12>=CI$5,1,IF(M12>=CI$4,2,3)))) -> 0 | ... AK12: =IF(U12="",0,IF(U12<=CQ$3,4,IF(U12>=CQ$5,1,IF(U12>=CQ$4,2,3)))) -> 2 | AL12: 11.2692 | AN12: 88.7308 | AP12: 0.006 | AQ12: 7.61 | AR12: 0.15
A13: Aditya Birla SL Overnight Fund-Reg(G) | B13: 43405 | C13: 9405.2675 | D13: 4930.5333 | E13: 1450.2454 | F13: 4.8613 | G13: 4.8579 | H13: 4.818 | I13: 4.9739 | J13: 4.9138 | K13: 5.078 | L13: 4.9895 | M13: 5.2849 | N13: 5.8782 | O13: 6.1443 | P13: 6.0098 | Q13: 5.4447 | R13: 4.997 | U13: 5.0823 | V13: =IF(F13="",0,IF(F13<=CB$3,4,IF(F13>=CB$5,1,IF(F13>=CB$4,2,3)))) -> 3 | W13: =IF(G13="",0,IF(G13<=CC$3,4,IF(G13>=CC$5,1,IF(G13>=CC$4,2,3)))) -> 3 | X13: =IF(H13="",0,IF(H13<=CD$3,4,IF(H13>=CD$5,1,IF(H13>=CD$4,2,3)))) -> 3 | Y13: =IF(I13="",0,IF(I13<=CE$3,4,IF(I13>=CE$5,1,IF(I13>=CE$4,2,3)))) -> 3 | Z13: =IF(J13="",0,IF(J13<=CF$3,4,IF(J13>=CF$5,1,IF(J13>=CF$4,2,3)))) -> 3 | AA13: =IF(K13="",0,IF(K13<=CG$3,4,IF(K13>=CG$5,1,IF(K13>=CG$4,2,3)))) -> 3 | AB13: =IF(L13="",0,IF(L13<=CH$3,4,IF(L13>=CH$5,1,IF(L13>=CH$4,2,3)))) -> 3 | AC13: =IF(M13="",0,IF(M13<=CI$3,4,IF(M13>=CI$5,1,IF(M13>=CI$4,2,3)))) -> 3 | ... AK13: =IF(U13="",0,IF(U13<=CQ$3,4,IF(U13>=CQ$5,1,IF(U13>=CQ$4,2,3)))) -> 2 | AL13: 11.6352 | AN13: 88.3648 | AO13: 0.01 | AP13: 0.01 | AQ13: 6.95 | AR13: 0.19
A14: Axis Overnight Fund-Reg(G) | B14: 43539 | C14: 10565.678 | D14: 7849.1927 | E14: 1426.3331 | F14: 4.9677 | G14: 4.9571 | H14: 4.9206 | I14: 5.1004 | J14: 5.0444 | K14: 5.1944 | L14: 5.1154 | M14: 5.3978 | N14: 5.9861 | O14: 6.247 | P14: 6.1067 | Q14: 5.5354 | R14: 5.0845 | U14: 5.1055 | V14: =IF(F14="",0,IF(F14<=CB$3,4,IF(F14>=CB$5,1,IF(F14>=CB$4,2,3)))) -> 1 | W14: =IF(G14="",0,IF(G14<=CC$3,4,IF(G14>=CC$5,1,IF(G14>=CC$4,2,3)))) -> 1 | X14: =IF(H14="",0,IF(H14<=CD$3,4,IF(H14>=CD$5,1,IF(H14>=CD$4,2,3)))) -> 1 | Y14: =IF(I14="",0,IF(I14<=CE$3,4,IF(I14>=CE$5,1,IF(I14>=CE$4,2,3)))) -> 1 | Z14: =IF(J14="",0,IF(J14<=CF$3,4,IF(J14>=CF$5,1,IF(J14>=CF$4,2,3)))) -> 1 | AA14: =IF(K14="",0,IF(K14<=CG$3,4,IF(K14>=CG$5,1,IF(K14>=CG$4,2,3)))) -> 1 | AB14: =IF(L14="",0,IF(L14<=CH$3,4,IF(L14>=CH$5,1,IF(L14>=CH$4,2,3)))) -> 1 | AC14: =IF(M14="",0,IF(M14<=CI$3,4,IF(M14>=CI$5,1,IF(M14>=CI$4,2,3)))) -> 1 | ... AK14: =IF(U14="",0,IF(U14<=CQ$3,4,IF(U14>=CQ$5,1,IF(U14>=CQ$4,2,3)))) -> 2 | AL14: 9.3436 | AN14: 90.6564 | AO14: 0.0082 | AP14: 0.0082 | AQ14: 7.24 | AR14: 0.1
A15: Bajaj Finserv Overnight Fund-Reg(G) | B15: 45112 | C15: 1256.7598 | D15: 348.7189 | E15: 1184.9619 | F15: 4.9728 | G15: 4.9618 | H15: 4.9175 | I15: 5.0159 | J15: 4.9917 | K15: 5.2219 | L15: 5.0693 | M15: 5.4055 | N15: 5.9672 | U15: 6.1916 | V15: =IF(F15="",0,IF(F15<=CB$3,4,IF(F15>=CB$5,1,IF(F15>=CB$4,2,3)))) -> 1 | W15: =IF(G15="",0,IF(G15<=CC$3,4,IF(G15>=CC$5,1,IF(G15>=CC$4,2,3)))) -> 1 | X15: =IF(H15="",0,IF(H15<=CD$3,4,IF(H15>=CD$5,1,IF(H15>=CD$4,2,3)))) -> 1 | Y15: =IF(I15="",0,IF(I15<=CE$3,4,IF(I15>=CE$5,1,IF(I15>=CE$4,2,3)))) -> 2 | Z15: =IF(J15="",0,IF(J15<=CF$3,4,IF(J15>=CF$5,1,IF(J15>=CF$4,2,3)))) -> 1 | AA15: =IF(K15="",0,IF(K15<=CG$3,4,IF(K15>=CG$5,1,IF(K15>=CG$4,2,3)))) -> 1 | AB15: =IF(L15="",0,IF(L15<=CH$3,4,IF(L15>=CH$5,1,IF(L15>=CH$4,2,3)))) -> 1 | AC15: =IF(M15="",0,IF(M15<=CI$3,4,IF(M15>=CI$5,1,IF(M15>=CI$4,2,3)))) -> 1 | ... AK15: =IF(U15="",0,IF(U15<=CQ$3,4,IF(U15>=CQ$5,1,IF(U15>=CQ$4,2,3)))) -> 1 | AL15: 30.0779 | AN15: 69.9221 | AO15: 0.011 | AP15: 0.011 | AQ15: 6.48 | AR15: 0.13
A16: Bandhan Overnight Fund-Reg(G) | B16: 43483 | C16: 891.1468 | D16: 556.6238 | E16: 1431.1249 | F16: 4.9004 | G16: 4.8905 | H16: 4.8616 | I16: 4.9782 | J16: 4.9261 | K16: 5.0921 | L16: 4.9981 | M16: 5.3033 | N16: 5.8895 | O16: 6.1528 | P16: 6.0156 | Q16: 5.4468 | R16: 4.9913 | U16: 5.0436 | V16: =IF(F16="",0,IF(F16<=CB$3,4,IF(F16>=CB$5,1,IF(F16>=CB$4,2,3)))) -> 2 | W16: =IF(G16="",0,IF(G16<=CC$3,4,IF(G16>=CC$5,1,IF(G16>=CC$4,2,3)))) -> 2 | X16: =IF(H16="",0,IF(H16<=CD$3,4,IF(H16>=CD$5,1,IF(H16>=CD$4,2,3)))) -> 3 | Y16: =IF(I16="",0,IF(I16<=CE$3,4,IF(I16>=CE$5,1,IF(I16>=CE$4,2,3)))) -> 3 | Z16: =IF(J16="",0,IF(J16<=CF$3,4,IF(J16>=CF$5,1,IF(J16>=CF$4,2,3)))) -> 3 | AA16: =IF(K16="",0,IF(K16<=CG$3,4,IF(K16>=CG$5,1,IF(K16>=CG$4,2,3)))) -> 3 | AB16: =IF(L16="",0,IF(L16<=CH$3,4,IF(L16>=CH$5,1,IF(L16>=CH$4,2,3)))) -> 3 | AC16: =IF(M16="",0,IF(M16<=CI$3,4,IF(M16>=CI$5,1,IF(M16>=CI$4,2,3)))) -> 3 | ... AK16: =IF(U16="",0,IF(U16<=CQ$3,4,IF(U16>=CQ$5,1,IF(U16>=CQ$4,2,3)))) -> 3 | AL16: 8.9701 | AN16: 91.0299 | AO16: 0.011 | AP16: 0.011 | AQ16: 6.7 | AR16: 0.15
A17: Bank of India Overnight Fund-Reg(G) | B17: 43858 | C17: 81.6952 | D17: 36.6657 | E17: 1369.4937 | F17: 4.9155 | G17: 4.9054 | H17: 4.9148 | I17: 5.0825 | J17: 5.0749 | K17: 5.2295 | L17: 5.1308 | M17: 5.4694 | N17: 6.0592 | O17: 6.319 | P17: 6.1772 | Q17: 5.6083 | U17: 5.1513 | V17: =IF(F17="",0,IF(F17<=CB$3,4,IF(F17>=CB$5,1,IF(F17>=CB$4,2,3)))) -> 2 | W17: =IF(G17="",0,IF(G17<=CC$3,4,IF(G17>=CC$5,1,IF(G17>=CC$4,2,3)))) -> 2 | X17: =IF(H17="",0,IF(H17<=CD$3,4,IF(H17>=CD$5,1,IF(H17>=CD$4,2,3)))) -> 1 | Y17: =IF(I17="",0,IF(I17<=CE$3,4,IF(I17>=CE$5,1,IF(I17>=CE$4,2,3)))) -> 1 | Z17: =IF(J17="",0,IF(J17<=CF$3,4,IF(J17>=CF$5,1,IF(J17>=CF$4,2,3)))) -> 1 | AA17: =IF(K17="",0,IF(K17<=CG$3,4,IF(K17>=CG$5,1,IF(K17>=CG$4,2,3)))) -> 1 | AB17: =IF(L17="",0,IF(L17<=CH$3,4,IF(L17>=CH$5,1,IF(L17>=CH$4,2,3)))) -> 1 | AC17: =IF(M17="",0,IF(M17<=CI$3,4,IF(M17>=CI$5,1,IF(M17>=CI$4,2,3)))) -> 1 | ... AK17: =IF(U17="",0,IF(U17<=CQ$3,4,IF(U17>=CQ$5,1,IF(U17>=CQ$4,2,3)))) -> 2 | AL17: 8.1725 | AN17: 91.8275 | AO17: 0.0027 | AP17: 0.0027 | AQ17: 7.53 | AR17: 0.1
A18: Baroda BNP Paribas Overnight Fund-Reg(G) | B18: 43580 | C18: 766.2343 | D18: 389.2413 | E18: 1413.9736 | F18: 4.9735 | G18: 4.9629 | H18: 4.9029 | I18: 5.0302 | J18: 4.9657 | K18: 5.1359 | L18: 5.0371 | M18: 5.3371 | N18: 5.9219 | O18: 6.1829 | P18: 6.0506 | Q18: 5.4844 | R18: 5.0537 | U18: 5.0564 | V18: =IF(F18="",0,IF(F18<=CB$3,4,IF(F18>=CB$5,1,IF(F18>=CB$4,2,3)))) -> 1 | W18: =IF(G18="",0,IF(G18<=CC$3,4,IF(G18>=CC$5,1,IF(G18>=CC$4,2,3)))) -> 1 | X18: =IF(H18="",0,IF(H18<=CD$3,4,IF(H18>=CD$5,1,IF(H18>=CD$4,2,3)))) -> 2 | Y18: =IF(I18="",0,IF(I18<=CE$3,4,IF(I18>=CE$5,1,IF(I18>=CE$4,2,3)))) -> 2 | Z18: =IF(J18="",0,IF(J18<=CF$3,4,IF(J18>=CF$5,1,IF(J18>=CF$4,2,3)))) -> 2 | AA18: =IF(K18="",0,IF(K18<=CG$3,4,IF(K18>=CG$5,1,IF(K18>=CG$4,2,3)))) -> 2 | AB18: =IF(L18="",0,IF(L18<=CH$3,4,IF(L18>=CH$5,1,IF(L18>=CH$4,2,3)))) -> 2 | AC18: =IF(M18="",0,IF(M18<=CI$3,4,IF(M18>=CI$5,1,IF(M18>=CI$4,2,3)))) -> 2 | ... AK18: =IF(U18="",0,IF(U18<=CQ$3,4,IF(U18>=CQ$5,1,IF(U18>=CQ$4,2,3)))) -> 3 | AL18: 14.1059 | AN18: 85.8941 | AO18: 0.011 | AP18: 0.011 | AQ18: 6.71 | AR18: 0.13
A19: Canara Rob Overnight Fund-Reg(G) | B19: 43670 | C19: 314.9518 | D19: 264.1286 | E19: 1394.5434 | F19: 4.9537 | G19: 4.9312 | H19: 4.8828 | I19: 5.0062 | J19: 4.9422 | K19: 5.1061 | L19: 5.0105 | M19: 5.3325 | N19: 5.8925 | O19: 6.1581 | P19: 6.0344 | Q19: 5.4786 | U19: 5.03 | V19: =IF(F19="",0,IF(F19<=CB$3,4,IF(F19>=CB$5,1,IF(F19>=CB$4,2,3)))) -> 1 | W19: =IF(G19="",0,IF(G19<=CC$3,4,IF(G19>=CC$5,1,IF(G19>=CC$4,2,3)))) -> 1 | X19: =IF(H19="",0,IF(H19<=CD$3,4,IF(H19>=CD$5,1,IF(H19>=CD$4,2,3)))) -> 2 | Y19: =IF(I19="",0,IF(I19<=CE$3,4,IF(I19>=CE$5,1,IF(I19>=CE$4,2,3)))) -> 2 | Z19: =IF(J19="",0,IF(J19<=CF$3,4,IF(J19>=CF$5,1,IF(J19>=CF$4,2,3)))) -> 3 | AA19: =IF(K19="",0,IF(K19<=CG$3,4,IF(K19>=CG$5,1,IF(K19>=CG$4,2,3)))) -> 2 | AB19: =IF(L19="",0,IF(L19<=CH$3,4,IF(L19>=CH$5,1,IF(L19>=CH$4,2,3)))) -> 3 | AC19: =IF(M19="",0,IF(M19<=CI$3,4,IF(M19>=CI$5,1,IF(M19>=CI$4,2,3)))) -> 2 | ... AK19: =IF(U19="",0,IF(U19<=CQ$3,4,IF(U19>=CQ$5,1,IF(U19>=CQ$4,2,3)))) -> 3 | AL19: 7.5547 | AN19: 92.4453 | AO19: 0.01 | AP19: 0.01 | AQ19: 6.46 | AR19: 0.09
A20: DSP Overnight Fund-Reg(G) | B20: 43474 | C20: 3139.7261 | D20: 2254.6319 | E20: 1440.2778 | F20: 4.8968 | G20: 4.8897 | H20: 4.8492 | I20: 4.9959 | J20: 4.9762 | K20: 5.1389 | L20: 5.0438 | M20: 5.3342 | N20: 5.9186 | O20: 6.1867 | P20: 6.0479 | Q20: 5.4819 | R20: 5.0605 | U20: 5.1153 | V20: =IF(F20="",0,IF(F20<=CB$3,4,IF(F20>=CB$5,1,IF(F20>=CB$4,2,3)))) -> 3 | W20: =IF(G20="",0,IF(G20<=CC$3,4,IF(G20>=CC$5,1,IF(G20>=CC$4,2,3)))) -> 3 | X20: =IF(H20="",0,IF(H20<=CD$3,4,IF(H20>=CD$5,1,IF(H20>=CD$4,2,3)))) -> 3 | Y20: =IF(I20="",0,IF(I20<=CE$3,4,IF(I20>=CE$5,1,IF(I20>=CE$4,2,3)))) -> 3 | Z20: =IF(J20="",0,IF(J20<=CF$3,4,IF(J20>=CF$5,1,IF(J20>=CF$4,2,3)))) -> 2 | AA20: =IF(K20="",0,IF(K20<=CG$3,4,IF(K20>=CG$5,1,IF(K20>=CG$4,2,3)))) -> 2 | AB20: =IF(L20="",0,IF(L20<=CH$3,4,IF(L20>=CH$5,1,IF(L20>=CH$4,2,3)))) -> 2 | AC20: =IF(M20="",0,IF(M20<=CI$3,4,IF(M20>=CI$5,1,IF(M20>=CI$4,2,3)))) -> 2 | ... AK20: =IF(U20="",0,IF(U20<=CQ$3,4,IF(U20>=CQ$5,1,IF(U20>=CQ$4,2,3)))) -> 2 | AL20: 17.2757 | AN20: 82.7243 | AP20: 0.01 | AQ20: 7.13 | AR20: 0.13
A21: Edelweiss Overnight Fund-Reg(G) | B21: 43670 | C21: 210.2846 | D21: 127.253 | E21: 1393.7985 | F21: 4.9223 | G21: 4.9316 | H21: 4.9202 | I21: 5.0156 | J21: 4.958 | K21: 5.1085 | L21: 5.0279 | M21: 5.3048 | N21: 5.8778 | O21: 6.1544 | P21: 6.011 | Q21: 5.4442 | U21: 5.0224 | V21: =IF(F21="",0,IF(F21<=CB$3,4,IF(F21>=CB$5,1,IF(F21>=CB$4,2,3)))) -> 2 | W21: =IF(G21="",0,IF(G21<=CC$3,4,IF(G21>=CC$5,1,IF(G21>=CC$4,2,3)))) -> 1 | X21: =IF(H21="",0,IF(H21<=CD$3,4,IF(H21>=CD$5,1,IF(H21>=CD$4,2,3)))) -> 1 | Y21: =IF(I21="",0,IF(I21<=CE$3,4,IF(I21>=CE$5,1,IF(I21>=CE$4,2,3)))) -> 2 | Z21: =IF(J21="",0,IF(J21<=CF$3,4,IF(J21>=CF$5,1,IF(J21>=CF$4,2,3)))) -> 2 | AA21: =IF(K21="",0,IF(K21<=CG$3,4,IF(K21>=CG$5,1,IF(K21>=CG$4,2,3)))) -> 2 | AB21: =IF(L21="",0,IF(L21<=CH$3,4,IF(L21>=CH$5,1,IF(L21>=CH$4,2,3)))) -> 2 | AC21: =IF(M21="",0,IF(M21<=CI$3,4,IF(M21>=CI$5,1,IF(M21>=CI$4,2,3)))) -> 3 | ... AK21: =IF(U21="",0,IF(U21<=CQ$3,4,IF(U21>=CQ$5,1,IF(U21>=CQ$4,2,3)))) -> 3 | AL21: 3.9246 | AN21: 96.0754 | AO21: 0.0055 | AP21: 0.0055 | AQ21: 6.77 | AR21: 0.16
A22: Franklin India Overnight Fund(G) | B22: 43593 | C22: 758.3724 | D22: 527.0681 | E22: 1405.9737 | F22: 5.0353 | G22: 4.9975 | H22: 4.952 | I22: 5.1492 | J22: 5.0652 | K22: 5.231 | L22: 5.1515 | M22: 5.4121 | N22: 5.9514 | O22: 6.193 | P22: 6.0439 | Q22: 5.4724 | U22: 5 | V22: =IF(F22="",0,IF(F22<=CB$3,4,IF(F22>=CB$5,1,IF(F22>=CB$4,2,3)))) -> 1 | W22: =IF(G22="",0,IF(G22<=CC$3,4,IF(G22>=CC$5,1,IF(G22>=CC$4,2,3)))) -> 1 | X22: =IF(H22="",0,IF(H22<=CD$3,4,IF(H22>=CD$5,1,IF(H22>=CD$4,2,3)))) -> 1 | Y22: =IF(I22="",0,IF(I22<=CE$3,4,IF(I22>=CE$5,1,IF(I22>=CE$4,2,3)))) -> 1 | Z22: =IF(J22="",0,IF(J22<=CF$3,4,IF(J22>=CF$5,1,IF(J22>=CF$4,2,3)))) -> 1 | AA22: =IF(K22="",0,IF(K22<=CG$3,4,IF(K22>=CG$5,1,IF(K22>=CG$4,2,3)))) -> 1 | AB22: =IF(L22="",0,IF(L22<=CH$3,4,IF(L22>=CH$5,1,IF(L22>=CH$4,2,3)))) -> 1 | AC22: =IF(M22="",0,IF(M22<=CI$3,4,IF(M22>=CI$5,1,IF(M22>=CI$4,2,3)))) -> 1 | ... AK22: =IF(U22="",0,IF(U22<=CQ$3,4,IF(U22>=CQ$5,1,IF(U22>=CQ$4,2,3)))) -> 4 | AL22: 7.756 | AN22: 92.244 | AO22: 0.0055 | AP22: 0.0055 | AQ22: 7.62 | AR22: 0.11
A23: Groww Overnight Fund-Reg(G) | B23: 43654 | C23: 125.94 | D23: 113.2972 | E23: 1384.4933 | F23: 4.8094 | G23: 4.8076 | H23: 4.7722 | I23: 4.9064 | J23: 4.8506 | K23: 4.9915 | L23: 4.9014 | M23: 5.2051 | N23: 5.8116 | O23: 6.0409 | P23: 5.8843 | Q23: 5.3258 | U23: 4.8885 | V23: =IF(F23="",0,IF(F23<=CB$3,4,IF(F23>=CB$5,1,IF(F23>=CB$4,2,3)))) -> 4 | W23: =IF(G23="",0,IF(G23<=CC$3,4,IF(G23>=CC$5,1,IF(G23>=CC$4,2,3)))) -> 4 | X23: =IF(H23="",0,IF(H23<=CD$3,4,IF(H23>=CD$5,1,IF(H23>=CD$4,2,3)))) -> 4 | Y23: =IF(I23="",0,IF(I23<=CE$3,4,IF(I23>=CE$5,1,IF(I23>=CE$4,2,3)))) -> 4 | Z23: =IF(J23="",0,IF(J23<=CF$3,4,IF(J23>=CF$5,1,IF(J23>=CF$4,2,3)))) -> 4 | AA23: =IF(K23="",0,IF(K23<=CG$3,4,IF(K23>=CG$5,1,IF(K23>=CG$4,2,3)))) -> 4 | AB23: =IF(L23="",0,IF(L23<=CH$3,4,IF(L23>=CH$5,1,IF(L23>=CH$4,2,3)))) -> 4 | AC23: =IF(M23="",0,IF(M23<=CI$3,4,IF(M23>=CI$5,1,IF(M23>=CI$4,2,3)))) -> 4 | ... AK23: =IF(U23="",0,IF(U23<=CQ$3,4,IF(U23>=CQ$5,1,IF(U23>=CQ$4,2,3)))) -> 4 | AN23: 100 | AQ23: 7.09 | AR23: 0.24
A24: HDFC Overnight Fund(G) | B24: 37293 | C24: 10920.158 | D24: 7433.8935 | E24: 3967.7817 | F24: 4.7786 | G24: 4.7908 | H24: 4.7653 | I24: 5.0039 | J24: 4.9169 | K24: 5.0645 | L24: 4.9853 | M24: 5.2694 | N24: 5.8487 | O24: 6.1171 | P24: 5.9783 | Q24: 5.4144 | R24: 4.9683 | S24: 5.2992 | T24: 6.1562 | U24: 5.8495 | V24: =IF(F24="",0,IF(F24<=CB$3,4,IF(F24>=CB$5,1,IF(F24>=CB$4,2,3)))) -> 4 | W24: =IF(G24="",0,IF(G24<=CC$3,4,IF(G24>=CC$5,1,IF(G24>=CC$4,2,3)))) -> 4 | X24: =IF(H24="",0,IF(H24<=CD$3,4,IF(H24>=CD$5,1,IF(H24>=CD$4,2,3)))) -> 4 | Y24: =IF(I24="",0,IF(I24<=CE$3,4,IF(I24>=CE$5,1,IF(I24>=CE$4,2,3)))) -> 3 | Z24: =IF(J24="",0,IF(J24<=CF$3,4,IF(J24>=CF$5,1,IF(J24>=CF$4,2,3)))) -> 3 | AA24: =IF(K24="",0,IF(K24<=CG$3,4,IF(K24>=CG$5,1,IF(K24>=CG$4,2,3)))) -> 3 | AB24: =IF(L24="",0,IF(L24<=CH$3,4,IF(L24>=CH$5,1,IF(L24>=CH$4,2,3)))) -> 3 | AC24: =IF(M24="",0,IF(M24<=CI$3,4,IF(M24>=CI$5,1,IF(M24>=CI$4,2,3)))) -> 3 | ... AK24: =IF(U24="",0,IF(U24<=CQ$3,4,IF(U24>=CQ$5,1,IF(U24>=CQ$4,2,3)))) -> 2 | AL24: 9.3903 | AN24: 90.6097 | AO24: 0.0096 | AP24: 0.0101 | AQ24: 7.91 | AR24: 0.22
A25: Helios Overnight Fund-Reg(G) | B25: 45224 | C25: 282.5171 | D25: 257.9164 | E25: 1158.4719 | F25: 4.8372 | G25: 4.8187 | H25: 4.8076 | I25: 4.9101 | J25: 4.8036 | K25: 4.9632 | L25: 4.8783 | M25: 5.1927 | N25: 5.8032 | U25: 5.9944 | V25: =IF(F25="",0,IF(F25<=CB$3,4,IF(F25>=CB$5,1,IF(F25>=CB$4,2,3)))) -> 4 | W25: =IF(G25="",0,IF(G25<=CC$3,4,IF(G25>=CC$5,1,IF(G25>=CC$4,2,3)))) -> 4 | X25: =IF(H25="",0,IF(H25<=CD$3,4,IF(H25>=CD$5,1,IF(H25>=CD$4,2,3)))) -> 3 | Y25: =IF(I25="",0,IF(I25<=CE$3,4,IF(I25>=CE$5,1,IF(I25>=CE$4,2,3)))) -> 4 | Z25: =IF(J25="",0,IF(J25<=CF$3,4,IF(J25>=CF$5,1,IF(J25>=CF$4,2,3)))) -> 4 | AA25: =IF(K25="",0,IF(K25<=CG$3,4,IF(K25>=CG$5,1,IF(K25>=CG$4,2,3)))) -> 4 | AB25: =IF(L25="",0,IF(L25<=CH$3,4,IF(L25>=CH$5,1,IF(L25>=CH$4,2,3)))) -> 4 | AC25: =IF(M25="",0,IF(M25<=CI$3,4,IF(M25>=CI$5,1,IF(M25>=CI$4,2,3)))) -> 4 | ... AK25: =IF(U25="",0,IF(U25<=CQ$3,4,IF(U25>=CQ$5,1,IF(U25>=CQ$4,2,3)))) -> 1 | AN25: 100 | AO25: 0.0027 | AP25: 0.0027 | AQ25: 6.42 | AR25: 0.19
A26: HSBC Overnight Fund-Reg(G) | B26: 43607 | C26: 4360.5363 | D26: 2589.0747 | E26: 1403.4294 | F26: 4.8352 | G26: 4.8518 | H26: 4.8684 | I26: 5.0499 | J26: 5.0249 | K26: 5.1576 | L26: 5.0826 | M26: 5.3411 | N26: 5.9092 | O26: 6.1701 | P26: 6.0248 | Q26: 5.4588 | U26: 4.9986 | V26: =IF(F26="",0,IF(F26<=CB$3,4,IF(F26>=CB$5,1,IF(F26>=CB$4,2,3)))) -> 4 | W26: =IF(G26="",0,IF(G26<=CC$3,4,IF(G26>=CC$5,1,IF(G26>=CC$4,2,3)))) -> 3 | X26: =IF(H26="",0,IF(H26<=CD$3,4,IF(H26>=CD$5,1,IF(H26>=CD$4,2,3)))) -> 2 | Y26: =IF(I26="",0,IF(I26<=CE$3,4,IF(I26>=CE$5,1,IF(I26>=CE$4,2,3)))) -> 1 | Z26: =IF(J26="",0,IF(J26<=CF$3,4,IF(J26>=CF$5,1,IF(J26>=CF$4,2,3)))) -> 1 | AA26: =IF(K26="",0,IF(K26<=CG$3,4,IF(K26>=CG$5,1,IF(K26>=CG$4,2,3)))) -> 1 | AB26: =IF(L26="",0,IF(L26<=CH$3,4,IF(L26>=CH$5,1,IF(L26>=CH$4,2,3)))) -> 1 | AC26: =IF(M26="",0,IF(M26<=CI$3,4,IF(M26>=CI$5,1,IF(M26>=CI$4,2,3)))) -> 1 | ... AK26: =IF(U26="",0,IF(U26<=CQ$3,4,IF(U26>=CQ$5,1,IF(U26>=CQ$4,2,3)))) -> 4 | AL26: 9.4423 | AN26: 90.5577 | AO26: 0.0081 | AP26: 0.0081 | AQ26: 6.74 | AR26: 0.14
A27: ICICI Pru Overnight Fund(G) | B27: 43419 | C27: 11394.694 | D27: 8823.6046 | E27: 1448.4445 | F27: 4.8991 | G27: 4.9071 | H27: 4.8744 | I27: 5.0347 | J27: 4.9803 | K27: 5.1398 | L27: 5.0502 | M27: 5.3378 | N27: 5.913 | O27: 6.1824 | P27: 6.0366 | Q27: 5.4653 | R27: 5.0103 | U27: 5.0894 | V27: =IF(F27="",0,IF(F27<=CB$3,4,IF(F27>=CB$5,1,IF(F27>=CB$4,2,3)))) -> 2 | W27: =IF(G27="",0,IF(G27<=CC$3,4,IF(G27>=CC$5,1,IF(G27>=CC$4,2,3)))) -> 2 | X27: =IF(H27="",0,IF(H27<=CD$3,4,IF(H27>=CD$5,1,IF(H27>=CD$4,2,3)))) -> 2 | Y27: =IF(I27="",0,IF(I27<=CE$3,4,IF(I27>=CE$5,1,IF(I27>=CE$4,2,3)))) -> 2 | Z27: =IF(J27="",0,IF(J27<=CF$3,4,IF(J27>=CF$5,1,IF(J27>=CF$4,2,3)))) -> 2 | AA27: =IF(K27="",0,IF(K27<=CG$3,4,IF(K27>=CG$5,1,IF(K27>=CG$4,2,3)))) -> 1 | AB27: =IF(L27="",0,IF(L27<=CH$3,4,IF(L27>=CH$5,1,IF(L27>=CH$4,2,3)))) -> 1 | AC27: =IF(M27="",0,IF(M27<=CI$3,4,IF(M27>=CI$5,1,IF(M27>=CI$4,2,3)))) -> 1 | ... AK27: =IF(U27="",0,IF(U27<=CQ$3,4,IF(U27>=CQ$5,1,IF(U27>=CQ$4,2,3)))) -> 2 | AL27: 7.4754 | AN27: 92.5246 | AO27: 0.0062 | AP27: 0.0093 | AQ27: 7.23 | AR27: 0.15
A28: Invesco India Overnight Fund-Reg(G) | B28: 43838 | C28: 331.7019 | D28: 316.2587 | E28: 1361.617 | F28: 4.9305 | G28: 4.9198 | H28: 4.8829 | I28: 5.0361 | J28: 4.986 | K28: 5.1412 | L28: 5.0539 | M28: 5.3463 | N28: 5.9305 | O28: 6.2026 | P28: 6.0574 | Q28: 5.4877 | U28: 5.0115 | V28: =IF(F28="",0,IF(F28<=CB$3,4,IF(F28>=CB$5,1,IF(F28>=CB$4,2,3)))) -> 2 | W28: =IF(G28="",0,IF(G28<=CC$3,4,IF(G28>=CC$5,1,IF(G28>=CC$4,2,3)))) -> 2 | X28: =IF(H28="",0,IF(H28<=CD$3,4,IF(H28>=CD$5,1,IF(H28>=CD$4,2,3)))) -> 2 | Y28: =IF(I28="",0,IF(I28<=CE$3,4,IF(I28>=CE$5,1,IF(I28>=CE$4,2,3)))) -> 2 | Z28: =IF(J28="",0,IF(J28<=CF$3,4,IF(J28>=CF$5,1,IF(J28>=CF$4,2,3)))) -> 1 | AA28: =IF(K28="",0,IF(K28<=CG$3,4,IF(K28>=CG$5,1,IF(K28>=CG$4,2,3)))) -> 1 | AB28: =IF(L28="",0,IF(L28<=CH$3,4,IF(L28>=CH$5,1,IF(L28>=CH$4,2,3)))) -> 1 | AC28: =IF(M28="",0,IF(M28<=CI$3,4,IF(M28>=CI$5,1,IF(M28>=CI$4,2,3)))) -> 1 | ... AK28: =IF(U28="",0,IF(U28<=CQ$3,4,IF(U28>=CQ$5,1,IF(U28>=CQ$4,2,3)))) -> 4 | AL28: 13.5594 | AN28: 86.4406 | AO28: 0.0082 | AP28: 0.011 | AQ28: 6.97 | AR28: 0.12
A29: ITI Overnight Fund-Reg(G) | B29: 43762 | C29: 15.0267 | D29: 24.7077 | E29: 1359.7005 | F29: 4.7584 | G29: 4.741 | H29: 4.666 | I29: 4.7151 | J29: 4.6655 | K29: 4.8353 | L29: 4.7481 | M29: 5.0912 | N29: 5.659 | O29: 5.9225 | P29: 5.8044 | Q29: 5.2708 | U29: 4.825 | V29: =IF(F29="",0,IF(F29<=CB$3,4,IF(F29>=CB$5,1,IF(F29>=CB$4,2,3)))) -> 4 | W29: =IF(G29="",0,IF(G29<=CC$3,4,IF(G29>=CC$5,1,IF(G29>=CC$4,2,3)))) -> 4 | X29: =IF(H29="",0,IF(H29<=CD$3,4,IF(H29>=CD$5,1,IF(H29>=CD$4,2,3)))) -> 4 | Y29: =IF(I29="",0,IF(I29<=CE$3,4,IF(I29>=CE$5,1,IF(I29>=CE$4,2,3)))) -> 4 | Z29: =IF(J29="",0,IF(J29<=CF$3,4,IF(J29>=CF$5,1,IF(J29>=CF$4,2,3)))) -> 4 | AA29: =IF(K29="",0,IF(K29<=CG$3,4,IF(K29>=CG$5,1,IF(K29>=CG$4,2,3)))) -> 4 | AB29: =IF(L29="",0,IF(L29<=CH$3,4,IF(L29>=CH$5,1,IF(L29>=CH$4,2,3)))) -> 4 | AC29: =IF(M29="",0,IF(M29<=CI$3,4,IF(M29>=CI$5,1,IF(M29>=CI$4,2,3)))) -> 4 | ... AK29: =IF(U29="",0,IF(U29<=CQ$3,4,IF(U29>=CQ$5,1,IF(U29>=CQ$4,2,3)))) -> 4 | AN29: 100 | AO29: 0.0055 | AP29: 0.0055 | AQ29: 6.14 | AR29: 0.18
A30: JM Overnight Fund-Reg(G) | B30: 43802 | C30: 89.3495 | D30: 52.6808 | E30: 1364.521 | F30: 4.7428 | G30: 4.7133 | H30: 4.6667 | I30: 4.8126 | J30: 4.7687 | K30: 4.9571 | L30: 4.8602 | M30: 5.1937 | N30: 5.8052 | O30: 6.0918 | P30: 5.9723 | Q30: 5.4221 | U30: 4.9674 | V30: =IF(F30="",0,IF(F30<=CB$3,4,IF(F30>=CB$5,1,IF(F30>=CB$4,2,3)))) -> 4 | W30: =IF(G30="",0,IF(G30<=CC$3,4,IF(G30>=CC$5,1,IF(G30>=CC$4,2,3)))) -> 4 | X30: =IF(H30="",0,IF(H30<=CD$3,4,IF(H30>=CD$5,1,IF(H30>=CD$4,2,3)))) -> 4 | Y30: =IF(I30="",0,IF(I30<=CE$3,4,IF(I30>=CE$5,1,IF(I30>=CE$4,2,3)))) -> 4 | Z30: =IF(J30="",0,IF(J30<=CF$3,4,IF(J30>=CF$5,1,IF(J30>=CF$4,2,3)))) -> 4 | AA30: =IF(K30="",0,IF(K30<=CG$3,4,IF(K30>=CG$5,1,IF(K30>=CG$4,2,3)))) -> 4 | AB30: =IF(L30="",0,IF(L30<=CH$3,4,IF(L30>=CH$5,1,IF(L30>=CH$4,2,3)))) -> 4 | AC30: =IF(M30="",0,IF(M30<=CI$3,4,IF(M30>=CI$5,1,IF(M30>=CI$4,2,3)))) -> 4 | ... AK30: =IF(U30="",0,IF(U30<=CQ$3,4,IF(U30>=CQ$5,1,IF(U30>=CQ$4,2,3)))) -> 4 | AN30: 100 | AO30: 0.0055 | AP30: 0.0055 | AQ30: 6.72 | AR30: 0.15
A31: Kotak Overnight Fund-Reg(G) | B31: 43480 | C31: 7093.1994 | D31: 5066.8514 | E31: 1433.4649 | F31: 4.8814 | G31: 4.8951 | H31: 4.8663 | I31: 5.0253 | J31: 4.9778 | K31: 5.1309 | L31: 5.0489 | M31: 5.3355 | N31: 5.9199 | O31: 6.1728 | P31: 6.0267 | Q31: 5.4573 | R31: 5.0113 | U31: 5.0614 | V31: =IF(F31="",0,IF(F31<=CB$3,4,IF(F31>=CB$5,1,IF(F31>=CB$4,2,3)))) -> 3 | W31: =IF(G31="",0,IF(G31<=CC$3,4,IF(G31>=CC$5,1,IF(G31>=CC$4,2,3)))) -> 2 | X31: =IF(H31="",0,IF(H31<=CD$3,4,IF(H31>=CD$5,1,IF(H31>=CD$4,2,3)))) -> 2 | Y31: =IF(I31="",0,IF(I31<=CE$3,4,IF(I31>=CE$5,1,IF(I31>=CE$4,2,3)))) -> 2 | Z31: =IF(J31="",0,IF(J31<=CF$3,4,IF(J31>=CF$5,1,IF(J31>=CF$4,2,3)))) -> 2 | AA31: =IF(K31="",0,IF(K31<=CG$3,4,IF(K31>=CG$5,1,IF(K31>=CG$4,2,3)))) -> 2 | AB31: =IF(L31="",0,IF(L31<=CH$3,4,IF(L31>=CH$5,1,IF(L31>=CH$4,2,3)))) -> 2 | AC31: =IF(M31="",0,IF(M31<=CI$3,4,IF(M31>=CI$5,1,IF(M31>=CI$4,2,3)))) -> 2 | ... AK31: =IF(U31="",0,IF(U31<=CQ$3,4,IF(U31>=CQ$5,1,IF(U31>=CQ$4,2,3)))) -> 3 | AL31: 4.6267 | AN31: 95.3733 | AO31: 0.0068 | AP31: 0.0075 | AQ31: 7.16 | AR31: 0.16
A32: LIC MF Overnight Fund-Reg(G) | B32: 43664 | C32: 549.6373 | D32: 902.4863 | E32: 1390.3509 | F32: 4.9473 | G32: 4.9307 | H32: 4.904 | I32: 5.056 | J32: 4.9568 | K32: 5.123 | L32: 5.0336 | M32: 5.3264 | N32: 5.8893 | O32: 6.139 | P32: 6.0007 | Q32: 5.4376 | U32: 4.9655 | V32: =IF(F32="",0,IF(F32<=CB$3,4,IF(F32>=CB$5,1,IF(F32>=CB$4,2,3)))) -> 1 | W32: =IF(G32="",0,IF(G32<=CC$3,4,IF(G32>=CC$5,1,IF(G32>=CC$4,2,3)))) -> 2 | X32: =IF(H32="",0,IF(H32<=CD$3,4,IF(H32>=CD$5,1,IF(H32>=CD$4,2,3)))) -> 2 | Y32: =IF(I32="",0,IF(I32<=CE$3,4,IF(I32>=CE$5,1,IF(I32>=CE$4,2,3)))) -> 1 | Z32: =IF(J32="",0,IF(J32<=CF$3,4,IF(J32>=CF$5,1,IF(J32>=CF$4,2,3)))) -> 2 | AA32: =IF(K32="",0,IF(K32<=CG$3,4,IF(K32>=CG$5,1,IF(K32>=CG$4,2,3)))) -> 2 | AB32: =IF(L32="",0,IF(L32<=CH$3,4,IF(L32>=CH$5,1,IF(L32>=CH$4,2,3)))) -> 2 | AC32: =IF(M32="",0,IF(M32<=CI$3,4,IF(M32>=CI$5,1,IF(M32>=CI$4,2,3)))) -> 2 | ... AK32: =IF(U32="",0,IF(U32<=CQ$3,4,IF(U32>=CQ$5,1,IF(U32>=CQ$4,2,3)))) -> 4 | AL32: 4.9754 | AN32: 95.0246 | AO32: 0.0074 | AP32: 0.0074 | AQ32: 7.08 | AR32: 0.15
A33: Mahindra Manulife Overnight Fund-Reg(G) | B33: 43669 | C33: 213.6509 | D33: 27.085 | E33: 1390.3659 | F33: 4.8382 | G33: 4.8358 | H33: 4.7595 | I33: 4.8541 | J33: 4.9163 | K33: 5.0908 | L33: 4.9957 | M33: 5.3025 | N33: 5.8871 | O33: 6.148 | P33: 6.0155 | Q33: 5.4587 | U33: 4.9845 | V33: =IF(F33="",0,IF(F33<=CB$3,4,IF(F33>=CB$5,1,IF(F33>=CB$4,2,3)))) -> 4 | W33: =IF(G33="",0,IF(G33<=CC$3,4,IF(G33>=CC$5,1,IF(G33>=CC$4,2,3)))) -> 4 | X33: =IF(H33="",0,IF(H33<=CD$3,4,IF(H33>=CD$5,1,IF(H33>=CD$4,2,3)))) -> 4 | Y33: =IF(I33="",0,IF(I33<=CE$3,4,IF(I33>=CE$5,1,IF(I33>=CE$4,2,3)))) -> 4 | Z33: =IF(J33="",0,IF(J33<=CF$3,4,IF(J33>=CF$5,1,IF(J33>=CF$4,2,3)))) -> 3 | AA33: =IF(K33="",0,IF(K33<=CG$3,4,IF(K33>=CG$5,1,IF(K33>=CG$4,2,3)))) -> 3 | AB33: =IF(L33="",0,IF(L33<=CH$3,4,IF(L33>=CH$5,1,IF(L33>=CH$4,2,3)))) -> 3 | AC33: =IF(M33="",0,IF(M33<=CI$3,4,IF(M33>=CI$5,1,IF(M33>=CI$4,2,3)))) -> 3 | ... AK33: =IF(U33="",0,IF(U33<=CQ$3,4,IF(U33>=CQ$5,1,IF(U33>=CQ$4,2,3)))) -> 4 | AL33: 34.6476 | AN33: 65.3524 | AO33: 0.0166 | AP33: 0.0167 | AQ33: 6.32 | AR33: 0.19
A34: Mirae Asset Overnight Fund-Reg(G) | B34: 43753 | C34: 1530.4354 | D34: 708.1232 | E34: 1378.7749 | F34: 4.8907 | G34: 4.8898 | H34: 4.8676 | I34: 4.9638 | J34: 4.9319 | K34: 5.115 | L34: 5.0136 | M34: 5.3365 | N34: 5.9202 | O34: 6.183 | P34: 6.0461 | Q34: 5.4884 | U34: 5.0297 | V34: =IF(F34="",0,IF(F34<=CB$3,4,IF(F34>=CB$5,1,IF(F34>=CB$4,2,3)))) -> 3 | W34: =IF(G34="",0,IF(G34<=CC$3,4,IF(G34>=CC$5,1,IF(G34>=CC$4,2,3)))) -> 3 | X34: =IF(H34="",0,IF(H34<=CD$3,4,IF(H34>=CD$5,1,IF(H34>=CD$4,2,3)))) -> 2 | Y34: =IF(I34="",0,IF(I34<=CE$3,4,IF(I34>=CE$5,1,IF(I34>=CE$4,2,3)))) -> 3 | Z34: =IF(J34="",0,IF(J34<=CF$3,4,IF(J34>=CF$5,1,IF(J34>=CF$4,2,3)))) -> 3 | AA34: =IF(K34="",0,IF(K34<=CG$3,4,IF(K34>=CG$5,1,IF(K34>=CG$4,2,3)))) -> 2 | AB34: =IF(L34="",0,IF(L34<=CH$3,4,IF(L34>=CH$5,1,IF(L34>=CH$4,2,3)))) -> 2 | AC34: =IF(M34="",0,IF(M34<=CI$3,4,IF(M34>=CI$5,1,IF(M34>=CI$4,2,3)))) -> 2 | ... AK34: =IF(U34="",0,IF(U34<=CQ$3,4,IF(U34>=CQ$5,1,IF(U34>=CQ$4,2,3)))) -> 3 | AL34: 7.0572 | AN34: 92.9428 | AO34: 0.01 | AP34: 0.0072 | AQ34: 6.39 | AR34: 0.17
A35: Nippon India Overnight Fund-Reg(G) | B35: 43452 | C35: 6730.1801 | D35: 3903.1226 | E35: 144.31 | F35: 4.8969 | G35: 4.907 | H35: 4.8856 | I35: 5.0483 | J35: 4.9755 | K35: 5.1327 | L35: 5.0441 | M35: 5.3384 | N35: 5.9313 | O35: 6.1884 | P35: 6.0487 | Q35: 5.4806 | R35: 5.0383 | U35: 5.1029 | V35: =IF(F35="",0,IF(F35<=CB$3,4,IF(F35>=CB$5,1,IF(F35>=CB$4,2,3)))) -> 3 | W35: =IF(G35="",0,IF(G35<=CC$3,4,IF(G35>=CC$5,1,IF(G35>=CC$4,2,3)))) -> 2 | X35: =IF(H35="",0,IF(H35<=CD$3,4,IF(H35>=CD$5,1,IF(H35>=CD$4,2,3)))) -> 2 | Y35: =IF(I35="",0,IF(I35<=CE$3,4,IF(I35>=CE$5,1,IF(I35>=CE$4,2,3)))) -> 1 | Z35: =IF(J35="",0,IF(J35<=CF$3,4,IF(J35>=CF$5,1,IF(J35>=CF$4,2,3)))) -> 2 | AA35: =IF(K35="",0,IF(K35<=CG$3,4,IF(K35>=CG$5,1,IF(K35>=CG$4,2,3)))) -> 2 | AB35: =IF(L35="",0,IF(L35<=CH$3,4,IF(L35>=CH$5,1,IF(L35>=CH$4,2,3)))) -> 2 | AC35: =IF(M35="",0,IF(M35<=CI$3,4,IF(M35>=CI$5,1,IF(M35>=CI$4,2,3)))) -> 1 | ... AK35: =IF(U35="",0,IF(U35<=CQ$3,4,IF(U35>=CQ$5,1,IF(U35>=CQ$4,2,3)))) -> 2 | AL35: 12.7874 | AN35: 87.2126 | AO35: 0.011 | AP35: 0.011 | AQ35: 7.14 | AR35: 0.16
A36: NJ Overnight Fund-Reg(G) | B36: 44774 | C36: 409.2044 | D36: 360.8746 | E36: 1247.029 | F36: 4.8811 | G36: 4.8586 | H36: 4.7803 | I36: 4.9261 | J36: 4.8519 | K36: 4.9922 | L36: 4.9189 | M36: 5.2231 | N36: 5.8039 | O36: 6.0781 | U36: 6.0633 | V36: =IF(F36="",0,IF(F36<=CB$3,4,IF(F36>=CB$5,1,IF(F36>=CB$4,2,3)))) -> 3 | W36: =IF(G36="",0,IF(G36<=CC$3,4,IF(G36>=CC$5,1,IF(G36>=CC$4,2,3)))) -> 3 | X36: =IF(H36="",0,IF(H36<=CD$3,4,IF(H36>=CD$5,1,IF(H36>=CD$4,2,3)))) -> 4 | Y36: =IF(I36="",0,IF(I36<=CE$3,4,IF(I36>=CE$5,1,IF(I36>=CE$4,2,3)))) -> 3 | Z36: =IF(J36="",0,IF(J36<=CF$3,4,IF(J36>=CF$5,1,IF(J36>=CF$4,2,3)))) -> 4 | AA36: =IF(K36="",0,IF(K36<=CG$3,4,IF(K36>=CG$5,1,IF(K36>=CG$4,2,3)))) -> 4 | AB36: =IF(L36="",0,IF(L36<=CH$3,4,IF(L36>=CH$5,1,IF(L36>=CH$4,2,3)))) -> 4 | AC36: =IF(M36="",0,IF(M36<=CI$3,4,IF(M36>=CI$5,1,IF(M36>=CI$4,2,3)))) -> 4 | ... AK36: =IF(U36="",0,IF(U36<=CQ$3,4,IF(U36>=CQ$5,1,IF(U36>=CQ$4,2,3)))) -> 1 | AN36: 100 | AO36: 0.0055 | AP36: 0.0055 | AQ36: 6.31 | AR36: 0.15
A37: PGIM India Overnight Fund-Reg(G) | B37: 43704 | C37: 46.465 | D37: 40.8329 | E37: 1388.1307 | F37: 4.892 | G37: 4.8443 | H37: 4.8014 | I37: 4.8261 | J37: 4.8143 | K37: 5.0493 | L37: 4.9028 | M37: 5.2723 | N37: 5.9096 | O37: 6.1703 | P37: 6.0317 | Q37: 5.481 | U37: 5.0325 | V37: =IF(F37="",0,IF(F37<=CB$3,4,IF(F37>=CB$5,1,IF(F37>=CB$4,2,3)))) -> 3 | W37: =IF(G37="",0,IF(G37<=CC$3,4,IF(G37>=CC$5,1,IF(G37>=CC$4,2,3)))) -> 4 | X37: =IF(H37="",0,IF(H37<=CD$3,4,IF(H37>=CD$5,1,IF(H37>=CD$4,2,3)))) -> 3 | Y37: =IF(I37="",0,IF(I37<=CE$3,4,IF(I37>=CE$5,1,IF(I37>=CE$4,2,3)))) -> 4 | Z37: =IF(J37="",0,IF(J37<=CF$3,4,IF(J37>=CF$5,1,IF(J37>=CF$4,2,3)))) -> 4 | AA37: =IF(K37="",0,IF(K37<=CG$3,4,IF(K37>=CG$5,1,IF(K37>=CG$4,2,3)))) -> 4 | AB37: =IF(L37="",0,IF(L37<=CH$3,4,IF(L37>=CH$5,1,IF(L37>=CH$4,2,3)))) -> 4 | AC37: =IF(M37="",0,IF(M37<=CI$3,4,IF(M37>=CI$5,1,IF(M37>=CI$4,2,3)))) -> 3 | ... AK37: =IF(U37="",0,IF(U37<=CQ$3,4,IF(U37>=CQ$5,1,IF(U37>=CQ$4,2,3)))) -> 3 | AL37: 4.8823 | AN37: 95.1177 | AO37: 0.0027 | AP37: 0.0027 | AQ37: 5.53 | AR37: 0.18
A38: Quant Overnight Fund-Reg(G) | B38: 44900 | C38: 54.2887 | D38: 55.9234 | E38: 12.3166 | F38: 4.7459 | G38: 4.7502 | H38: 4.6836 | I38: 4.7222 | J38: 4.673 | K38: 4.8598 | L38: 4.7631 | M38: 5.1443 | N38: 5.8564 | O38: 6.2993 | U38: 6.3101 | V38: =IF(F38="",0,IF(F38<=CB$3,4,IF(F38>=CB$5,1,IF(F38>=CB$4,2,3)))) -> 4 | W38: =IF(G38="",0,IF(G38<=CC$3,4,IF(G38>=CC$5,1,IF(G38>=CC$4,2,3)))) -> 4 | X38: =IF(H38="",0,IF(H38<=CD$3,4,IF(H38>=CD$5,1,IF(H38>=CD$4,2,3)))) -> 4 | Y38: =IF(I38="",0,IF(I38<=CE$3,4,IF(I38>=CE$5,1,IF(I38>=CE$4,2,3)))) -> 4 | Z38: =IF(J38="",0,IF(J38<=CF$3,4,IF(J38>=CF$5,1,IF(J38>=CF$4,2,3)))) -> 4 | AA38: =IF(K38="",0,IF(K38<=CG$3,4,IF(K38>=CG$5,1,IF(K38>=CG$4,2,3)))) -> 4 | AB38: =IF(L38="",0,IF(L38<=CH$3,4,IF(L38>=CH$5,1,IF(L38>=CH$4,2,3)))) -> 4 | AC38: =IF(M38="",0,IF(M38<=CI$3,4,IF(M38>=CI$5,1,IF(M38>=CI$4,2,3)))) -> 4 | ... AK38: =IF(U38="",0,IF(U38<=CQ$3,4,IF(U38>=CQ$5,1,IF(U38>=CQ$4,2,3)))) -> 1 | AN38: 100 | AO38: 0.0082 | AP38: 0.0082 | AQ38: 5.05 | AR38: 0.24
A39: Samco Overnight Fund-Reg(G) | B39: 44846 | C39: 30.8868 | D39: 22.7412 | E39: 1225.58 | F39: 4.6846 | G39: 4.6803 | H39: 4.5315 | I39: 4.4993 | J39: 4.4888 | K39: 4.6815 | L39: 4.5711 | M39: 4.9267 | N39: 5.5223 | O39: 5.8298 | U39: 5.8962 | V39: =IF(F39="",0,IF(F39<=CB$3,4,IF(F39>=CB$5,1,IF(F39>=CB$4,2,3)))) -> 4 | W39: =IF(G39="",0,IF(G39<=CC$3,4,IF(G39>=CC$5,1,IF(G39>=CC$4,2,3)))) -> 4 | X39: =IF(H39="",0,IF(H39<=CD$3,4,IF(H39>=CD$5,1,IF(H39>=CD$4,2,3)))) -> 4 | Y39: =IF(I39="",0,IF(I39<=CE$3,4,IF(I39>=CE$5,1,IF(I39>=CE$4,2,3)))) -> 4 | Z39: =IF(J39="",0,IF(J39<=CF$3,4,IF(J39>=CF$5,1,IF(J39>=CF$4,2,3)))) -> 4 | AA39: =IF(K39="",0,IF(K39<=CG$3,4,IF(K39>=CG$5,1,IF(K39>=CG$4,2,3)))) -> 4 | AB39: =IF(L39="",0,IF(L39<=CH$3,4,IF(L39>=CH$5,1,IF(L39>=CH$4,2,3)))) -> 4 | AC39: =IF(M39="",0,IF(M39<=CI$3,4,IF(M39>=CI$5,1,IF(M39>=CI$4,2,3)))) -> 4 | ... AK39: =IF(U39="",0,IF(U39<=CQ$3,4,IF(U39>=CQ$5,1,IF(U39>=CQ$4,2,3)))) -> 1 | AN39: 100 | AO39: 0.0055 | AP39: 0.0055 | AQ39: 5.01 | AR39: 0.33
A40: SBI Overnight Fund-Reg(G) | B40: 37523 | C40: 28880.19 | D40: 17848.677 | E40: 4338.4369 | F40: 4.9312 | G40: 4.9148 | H40: 4.8611 | I40: 4.9767 | J40: 4.9298 | K40: 5.0888 | L40: 4.9997 | M40: 5.3098 | N40: 5.8886 | O40: 6.1426 | P40: 6.007 | Q40: 5.4451 | R40: 5.0051 | S40: 5.3316 | T40: 6.4202 | U40: 6.4118 | V40: =IF(F40="",0,IF(F40<=CB$3,4,IF(F40>=CB$5,1,IF(F40>=CB$4,2,3)))) -> 2 | W40: =IF(G40="",0,IF(G40<=CC$3,4,IF(G40>=CC$5,1,IF(G40>=CC$4,2,3)))) -> 2 | X40: =IF(H40="",0,IF(H40<=CD$3,4,IF(H40>=CD$5,1,IF(H40>=CD$4,2,3)))) -> 3 | Y40: =IF(I40="",0,IF(I40<=CE$3,4,IF(I40>=CE$5,1,IF(I40>=CE$4,2,3)))) -> 3 | Z40: =IF(J40="",0,IF(J40<=CF$3,4,IF(J40>=CF$5,1,IF(J40>=CF$4,2,3)))) -> 3 | AA40: =IF(K40="",0,IF(K40<=CG$3,4,IF(K40>=CG$5,1,IF(K40>=CG$4,2,3)))) -> 3 | AB40: =IF(L40="",0,IF(L40<=CH$3,4,IF(L40>=CH$5,1,IF(L40>=CH$4,2,3)))) -> 3 | AC40: =IF(M40="",0,IF(M40<=CI$3,4,IF(M40>=CI$5,1,IF(M40>=CI$4,2,3)))) -> 2 | ... AK40: =IF(U40="",0,IF(U40<=CQ$3,4,IF(U40>=CQ$5,1,IF(U40>=CQ$4,2,3)))) -> 1 | AL40: 5.9586 | AN40: 94.0414 | AO40: 0.0027 | AP40: 0.0027 | AQ40: 6.5 | AR40: 0.14
A41: Shriram Overnight Fund-Reg(G) | B41: 44799 | C41: 123.7008 | D41: 108.3626 | E41: 12.451 | F41: 4.9044 | G41: 4.888 | H41: 4.8434 | I41: 5.0143 | J41: 4.9854 | K41: 5.1173 | L41: 5.0312 | M41: 5.3028 | N41: 5.837 | O41: 6.1064 | U41: 6.1389 | V41: =IF(F41="",0,IF(F41<=CB$3,4,IF(F41>=CB$5,1,IF(F41>=CB$4,2,3)))) -> 2 | W41: =IF(G41="",0,IF(G41<=CC$3,4,IF(G41>=CC$5,1,IF(G41>=CC$4,2,3)))) -> 3 | X41: =IF(H41="",0,IF(H41<=CD$3,4,IF(H41>=CD$5,1,IF(H41>=CD$4,2,3)))) -> 3 | Y41: =IF(I41="",0,IF(I41<=CE$3,4,IF(I41>=CE$5,1,IF(I41>=CE$4,2,3)))) -> 2 | Z41: =IF(J41="",0,IF(J41<=CF$3,4,IF(J41>=CF$5,1,IF(J41>=CF$4,2,3)))) -> 1 | AA41: =IF(K41="",0,IF(K41<=CG$3,4,IF(K41>=CG$5,1,IF(K41>=CG$4,2,3)))) -> 2 | AB41: =IF(L41="",0,IF(L41<=CH$3,4,IF(L41>=CH$5,1,IF(L41>=CH$4,2,3)))) -> 2 | AC41: =IF(M41="",0,IF(M41<=CI$3,4,IF(M41>=CI$5,1,IF(M41>=CI$4,2,3)))) -> 3 | ... AK41: =IF(U41="",0,IF(U41<=CQ$3,4,IF(U41>=CQ$5,1,IF(U41>=CQ$4,2,3)))) -> 1 | AL41: 4.5995 | AN41: 95.4005 | AO41: 0.0077 | AP41: 0.0082 | AQ41: 7.4 | AR41: 0.15
A42: Sundaram Overnight Fund-Reg(G) | B42: 43544 | C42: 1116.9407 | D42: 345.8042 | E42: 1426.4825 | F42: 4.8848 | G42: 4.8659 | H42: 4.9506 | I42: 5.0043 | J42: 4.8821 | K42: 5.0523 | L42: 4.9506 | M42: 5.2685 | N42: 5.8728 | O42: 6.1377 | P42: 6.0097 | Q42: 5.4327 | R42: 5.0044 | U42: 5.1171 | V42: =IF(F42="",0,IF(F42<=CB$3,4,IF(F42>=CB$5,1,IF(F42>=CB$4,2,3)))) -> 3 | W42: =IF(G42="",0,IF(G42<=CC$3,4,IF(G42>=CC$5,1,IF(G42>=CC$4,2,3)))) -> 3 | X42: =IF(H42="",0,IF(H42<=CD$3,4,IF(H42>=CD$5,1,IF(H42>=CD$4,2,3)))) -> 1 | Y42: =IF(I42="",0,IF(I42<=CE$3,4,IF(I42>=CE$5,1,IF(I42>=CE$4,2,3)))) -> 2 | Z42: =IF(J42="",0,IF(J42<=CF$3,4,IF(J42>=CF$5,1,IF(J42>=CF$4,2,3)))) -> 3 | AA42: =IF(K42="",0,IF(K42<=CG$3,4,IF(K42>=CG$5,1,IF(K42>=CG$4,2,3)))) -> 3 | AB42: =IF(L42="",0,IF(L42<=CH$3,4,IF(L42>=CH$5,1,IF(L42>=CH$4,2,3)))) -> 3 | AC42: =IF(M42="",0,IF(M42<=CI$3,4,IF(M42>=CI$5,1,IF(M42>=CI$4,2,3)))) -> 4 | ... AK42: =IF(U42="",0,IF(U42<=CQ$3,4,IF(U42>=CQ$5,1,IF(U42>=CQ$4,2,3)))) -> 2 | AL42: 5.7712 | AN42: 94.2288 | AQ42: 6.5 | AR42: 0.18
A43: Tata Overnight Fund-Reg(G) | B43: 43551 | C43: 4055.105 | D43: 2568.8272 | E43: 1416.3076 | F43: 4.9004 | G43: 4.8758 | H43: 4.8569 | I43: 4.9932 | J43: 4.9435 | K43: 5.1037 | L43: 5.008 | M43: 5.3113 | N43: 5.8986 | O43: 6.1556 | P43: 6.0143 | Q43: 5.4463 | R43: 5.0058 | U43: 5.0204 | V43: =IF(F43="",0,IF(F43<=CB$3,4,IF(F43>=CB$5,1,IF(F43>=CB$4,2,3)))) -> 2 | W43: =IF(G43="",0,IF(G43<=CC$3,4,IF(G43>=CC$5,1,IF(G43>=CC$4,2,3)))) -> 3 | X43: =IF(H43="",0,IF(H43<=CD$3,4,IF(H43>=CD$5,1,IF(H43>=CD$4,2,3)))) -> 3 | Y43: =IF(I43="",0,IF(I43<=CE$3,4,IF(I43>=CE$5,1,IF(I43>=CE$4,2,3)))) -> 3 | Z43: =IF(J43="",0,IF(J43<=CF$3,4,IF(J43>=CF$5,1,IF(J43>=CF$4,2,3)))) -> 2 | AA43: =IF(K43="",0,IF(K43<=CG$3,4,IF(K43>=CG$5,1,IF(K43>=CG$4,2,3)))) -> 3 | AB43: =IF(L43="",0,IF(L43<=CH$3,4,IF(L43>=CH$5,1,IF(L43>=CH$4,2,3)))) -> 3 | AC43: =IF(M43="",0,IF(M43<=CI$3,4,IF(M43>=CI$5,1,IF(M43>=CI$4,2,3)))) -> 2 | ... AK43: =IF(U43="",0,IF(U43<=CQ$3,4,IF(U43>=CQ$5,1,IF(U43>=CQ$4,2,3)))) -> 3 | AL43: 7.3839 | AN43: 92.6161 | AO43: 0.011 | AP43: 0.011 | AQ43: 6.97 | AR43: 0.18
A44: TRUSTMF Overnight Fund-Reg(G) | B44: 44579 | C44: 91.5027 | D44: 14.2955 | E44: 1276.1044 | F44: 4.9697 | G44: 4.9 | H44: 4.7941 | I44: 4.8438 | J44: 4.8012 | K44: 4.9847 | L44: 4.882 | M44: 5.2507 | N44: 5.8801 | O44: 6.1532 | P44: 6.0248 | U44: 5.8588 | V44: =IF(F44="",0,IF(F44<=CB$3,4,IF(F44>=CB$5,1,IF(F44>=CB$4,2,3)))) -> 1 | W44: =IF(G44="",0,IF(G44<=CC$3,4,IF(G44>=CC$5,1,IF(G44>=CC$4,2,3)))) -> 2 | X44: =IF(H44="",0,IF(H44<=CD$3,4,IF(H44>=CD$5,1,IF(H44>=CD$4,2,3)))) -> 4 | Y44: =IF(I44="",0,IF(I44<=CE$3,4,IF(I44>=CE$5,1,IF(I44>=CE$4,2,3)))) -> 4 | Z44: =IF(J44="",0,IF(J44<=CF$3,4,IF(J44>=CF$5,1,IF(J44>=CF$4,2,3)))) -> 4 | AA44: =IF(K44="",0,IF(K44<=CG$3,4,IF(K44>=CG$5,1,IF(K44>=CG$4,2,3)))) -> 4 | AB44: =IF(L44="",0,IF(L44<=CH$3,4,IF(L44>=CH$5,1,IF(L44>=CH$4,2,3)))) -> 4 | AC44: =IF(M44="",0,IF(M44<=CI$3,4,IF(M44>=CI$5,1,IF(M44>=CI$4,2,3)))) -> 4 | ... AK44: =IF(U44="",0,IF(U44<=CQ$3,4,IF(U44>=CQ$5,1,IF(U44>=CQ$4,2,3)))) -> 1 | AL44: 11.8779 | AN44: 88.1221 | AO44: 0.0082 | AP44: 0.0082 | AQ44: 5.64 | AR44: 0.12
A45: Union Overnight Fund-Reg(G) | B45: 43551 | C45: 296.506 | D45: 398.3306 | E45: 1413.708 | F45: 4.9571 | G45: 4.9514 | H45: 4.9158 | I45: 5.0676 | J45: 4.9502 | K45: 5.0931 | L45: 5.0136 | M45: 5.2983 | N45: 5.884 | O45: 6.1475 | P45: 6.01 | Q45: 5.4468 | R45: 4.9824 | U45: 4.9958 | V45: =IF(F45="",0,IF(F45<=CB$3,4,IF(F45>=CB$5,1,IF(F45>=CB$4,2,3)))) -> 1 | W45: =IF(G45="",0,IF(G45<=CC$3,4,IF(G45>=CC$5,1,IF(G45>=CC$4,2,3)))) -> 1 | X45: =IF(H45="",0,IF(H45<=CD$3,4,IF(H45>=CD$5,1,IF(H45>=CD$4,2,3)))) -> 1 | Y45: =IF(I45="",0,IF(I45<=CE$3,4,IF(I45>=CE$5,1,IF(I45>=CE$4,2,3)))) -> 1 | Z45: =IF(J45="",0,IF(J45<=CF$3,4,IF(J45>=CF$5,1,IF(J45>=CF$4,2,3)))) -> 2 | AA45: =IF(K45="",0,IF(K45<=CG$3,4,IF(K45>=CG$5,1,IF(K45>=CG$4,2,3)))) -> 3 | AB45: =IF(L45="",0,IF(L45<=CH$3,4,IF(L45>=CH$5,1,IF(L45>=CH$4,2,3)))) -> 2 | AC45: =IF(M45="",0,IF(M45<=CI$3,4,IF(M45>=CI$5,1,IF(M45>=CI$4,2,3)))) -> 3 | ... AK45: =IF(U45="",0,IF(U45<=CQ$3,4,IF(U45>=CQ$5,1,IF(U45>=CQ$4,2,3)))) -> 4 | AL45: 12.5257 | AN45: 87.4743 | AO45: 0.0096 | AP45: 0.0102 | AQ45: 7.13 | AR45: 0.16
A46: UTI Overnight Fund-Reg(G) | B46: 37964 | C46: 5552.3161 | D46: 2972.7712 | E46: 3660.8794 | F46: 4.9345 | G46: 4.9329 | H46: 4.9086 | I46: 5.0974 | J46: 4.9953 | K46: 5.1512 | L46: 5.0689 | M46: 5.3577 | N46: 5.944 | O46: 6.2084 | P46: 6.0687 | Q46: 5.5 | R46: 5.055 | S46: 5.5149 | T46: 6.424 | U46: 5.9629 | V46: =IF(F46="",0,IF(F46<=CB$3,4,IF(F46>=CB$5,1,IF(F46>=CB$4,2,3)))) -> 2 | W46: =IF(G46="",0,IF(G46<=CC$3,4,IF(G46>=CC$5,1,IF(G46>=CC$4,2,3)))) -> 1 | X46: =IF(H46="",0,IF(H46<=CD$3,4,IF(H46>=CD$5,1,IF(H46>=CD$4,2,3)))) -> 1 | Y46: =IF(I46="",0,IF(I46<=CE$3,4,IF(I46>=CE$5,1,IF(I46>=CE$4,2,3)))) -> 1 | Z46: =IF(J46="",0,IF(J46<=CF$3,4,IF(J46>=CF$5,1,IF(J46>=CF$4,2,3)))) -> 1 | AA46: =IF(K46="",0,IF(K46<=CG$3,4,IF(K46>=CG$5,1,IF(K46>=CG$4,2,3)))) -> 1 | AB46: =IF(L46="",0,IF(L46<=CH$3,4,IF(L46>=CH$5,1,IF(L46>=CH$4,2,3)))) -> 1 | AC46: =IF(M46="",0,IF(M46<=CI$3,4,IF(M46>=CI$5,1,IF(M46>=CI$4,2,3)))) -> 1 | ... AK46: =IF(U46="",0,IF(U46<=CQ$3,4,IF(U46>=CQ$5,1,IF(U46>=CQ$4,2,3)))) -> 1 | AL46: 6.3836 | AN46: 93.0241 | AO46: 0.0055 | AP46: 0.0055 | AQ46: 6.32 | AR46: 0.12
V47: =IF(F47="",0,IF(F47<=CB$3,4,IF(F47>=CB$5,1,IF(F47>=CB$4,2,3)))) -> 0 | W47: =IF(G47="",0,IF(G47<=CC$3,4,IF(G47>=CC$5,1,IF(G47>=CC$4,2,3)))) -> 0 | X47: =IF(H47="",0,IF(H47<=CD$3,4,IF(H47>=CD$5,1,IF(H47>=CD$4,2,3)))) -> 0 | Y47: =IF(I47="",0,IF(I47<=CE$3,4,IF(I47>=CE$5,1,IF(I47>=CE$4,2,3)))) -> 0 | Z47: =IF(J47="",0,IF(J47<=CF$3,4,IF(J47>=CF$5,1,IF(J47>=CF$4,2,3)))) -> 0 | AA47: =IF(K47="",0,IF(K47<=CG$3,4,IF(K47>=CG$5,1,IF(K47>=CG$4,2,3)))) -> 0 | AB47: =IF(L47="",0,IF(L47<=CH$3,4,IF(L47>=CH$5,1,IF(L47>=CH$4,2,3)))) -> 0 | AC47: =IF(M47="",0,IF(M47<=CI$3,4,IF(M47>=CI$5,1,IF(M47>=CI$4,2,3)))) -> 0 | ... AK47: =IF(U47="",0,IF(U47<=CQ$3,4,IF(U47>=CQ$5,1,IF(U47>=CQ$4,2,3)))) -> 0
V48: =IF(F48="",0,IF(F48<=CB$3,4,IF(F48>=CB$5,1,IF(F48>=CB$4,2,3)))) -> 0 | W48: =IF(G48="",0,IF(G48<=CC$3,4,IF(G48>=CC$5,1,IF(G48>=CC$4,2,3)))) -> 0 | X48: =IF(H48="",0,IF(H48<=CD$3,4,IF(H48>=CD$5,1,IF(H48>=CD$4,2,3)))) -> 0 | Y48: =IF(I48="",0,IF(I48<=CE$3,4,IF(I48>=CE$5,1,IF(I48>=CE$4,2,3)))) -> 0 | Z48: =IF(J48="",0,IF(J48<=CF$3,4,IF(J48>=CF$5,1,IF(J48>=CF$4,2,3)))) -> 0 | AA48: =IF(K48="",0,IF(K48<=CG$3,4,IF(K48>=CG$5,1,IF(K48>=CG$4,2,3)))) -> 0 | AB48: =IF(L48="",0,IF(L48<=CH$3,4,IF(L48>=CH$5,1,IF(L48>=CH$4,2,3)))) -> 0 | AC48: =IF(M48="",0,IF(M48<=CI$3,4,IF(M48>=CI$5,1,IF(M48>=CI$4,2,3)))) -> 0 | ... AK48: =IF(U48="",0,IF(U48<=CQ$3,4,IF(U48>=CQ$5,1,IF(U48>=CQ$4,2,3)))) -> 0
A49: Category Average (Weighted) | F49: =SUMPRODUCT($D12:$D48,F12:F48)/SUMIF(F12:F48,"<>"&"",$D12:$D48) -> 4.8997275 | G49: =SUMPRODUCT($D12:$D48,G12:G48)/SUMIF(G12:G48,"<>"&"",$D12:$D48) -> 4.8968732 | H49: =SUMPRODUCT($D12:$D48,H12:H48)/SUMIF(H12:H48,"<>"&"",$D12:$D48) -> 4.8618321 | I49: =SUMPRODUCT($D12:$D48,I12:I48)/SUMIF(I12:I48,"<>"&"",$D12:$D48) -> 5.018624 | J49: =SUMPRODUCT($D12:$D48,J12:J48)/SUMIF(J12:J48,"<>"&"",$D12:$D48) -> 4.9608537 | K49: =SUMPRODUCT($D12:$D48,K12:K48)/SUMIF(K12:K48,"<>"&"",$D12:$D48) -> 5.1175713 | L49: =SUMPRODUCT($D12:$D48,L12:L48)/SUMIF(L12:L48,"<>"&"",$D12:$D48) -> 5.0309286 | M49: =SUMPRODUCT($D12:$D48,M12:M48)/SUMIF(M12:M48,"<>"&"",$D12:$D48) -> 5.3245389 | ... U49: =SUMPRODUCT($D12:$D48,U12:U48)/SUMIF(U12:U48,"<>"&"",$D12:$D48) -> 5.5358493
A50: Minimum | F50: =MIN(F12:F48) -> 4.6846 | G50: =MIN(G12:G48) -> 4.6803 | H50: =MIN(H12:H48) -> 4.5315 | I50: =MIN(I12:I48) -> 4.4993 | J50: =MIN(J12:J48) -> 4.4888 | K50: =MIN(K12:K48) -> 4.6815 | L50: =MIN(L12:L48) -> 4.5711 | M50: =MIN(M12:M48) -> 4.9267 | ... U50: =MIN(U12:U48) -> 4.825
A51: Maximum | F51: =MAX(F12:F48) -> 5.0353 | G51: =MAX(G12:G48) -> 5.0483 | H51: =MAX(H12:H48) -> 4.952 | I51: =MAX(I12:I48) -> 5.1492 | J51: =MAX(J12:J48) -> 5.0749 | K51: =MAX(K12:K48) -> 5.231 | L51: =MAX(L12:L48) -> 5.1515 | M51: =MAX(M12:M48) -> 5.4694 | ... U51: =MAX(U12:U48) -> 6.4118
A52: Median | F52: =MEDIAN(F12:F48) -> 4.8991 | G52: =MEDIAN(G12:G48) -> 4.8905 | H52: =MEDIAN(H12:H48) -> 4.8663 | I52: =MEDIAN(I12:I48) -> 5.0043 | J52: =MEDIAN(J12:J48) -> 4.9435 | K52: =MEDIAN(K12:K48) -> 5.1061 | L52: =MEDIAN(L12:L48) -> 5.0136 | M52: =MEDIAN(M12:M48) -> 5.3073 | ... U52: =MEDIAN(U12:U48) -> 5.0823
A53: Indices Performance
A54: CRISIL Liquid Overnight Index | E54: =IFERROR(INDEX(Benchmark!$A$4:$O$813,MATCH('Overnight Fund'!$A54,Benchmark!$A$4:$A$813,0),MATCH('Overnight Fund'!E$9,Benchmark!$A$3:$O$3,0)),0) -> 3571.147 | F54: =IFERROR(INDEX(Benchmark!$A$4:$O$813,MATCH('Overnight Fund'!$A54,Benchmark!$A$4:$A$813,0),MATCH('Overnight Fund'!F$9,Benchmark!$A$3:$O$3,0)),0) -> 0 | G54: =IFERROR(INDEX(Benchmark!$A$4:$O$813,MATCH('Overnight Fund'!$A54,Benchmark!$A$4:$A$813,0),MATCH('Overnight Fund'!G$9,Benchmark!$A$3:$O$3,0)),0) -> 0 | H54: =IFERROR(INDEX(Benchmark!$A$4:$O$813,MATCH('Overnight Fund'!$A54,Benchmark!$A$4:$A$813,0),MATCH('Overnight Fund'!H$9,Benchmark!$A$3:$O$3,0)),0) -> 0
A55: Nifty 1D Rate Index | E55: =IFERROR(INDEX(Benchmark!$A$4:$O$813,MATCH('Overnight Fund'!$A55,Benchmark!$A$4:$A$813,0),MATCH('Overnight Fund'!E$9,Benchmark!$A$3:$O$3,0)),0) -> 2490.7 | F55: =IFERROR(INDEX(Benchmark!$A$4:$O$813,MATCH('Overnight Fund'!$A55,Benchmark!$A$4:$A$813,0),MATCH('Overnight Fund'!F$9,Benchmark!$A$3:$O$3,0)),0) -> 0 | G55: =IFERROR(INDEX(Benchmark!$A$4:$O$813,MATCH('Overnight Fund'!$A55,Benchmark!$A$4:$A$813,0),MATCH('Overnight Fund'!G$9,Benchmark!$A$3:$O$3,0)),0) -> 0 | H55: =IFERROR(INDEX(Benchmark!$A$4:$O$813,MATCH('Overnight Fund'!$A55,Benchmark!$A$4:$A$813,0),MATCH('Overnight Fund'!H$9,Benchmark!$A$3:$O$3,0)),0) -> 0
A56: # : "In the Quartile System, the "performance range" of the entire category for a given time period, is divided into 4 parts. Schemes with returns in the top 25% of that range
A57: in the next 25% of the range have been ranked Quartile 2 and so on. Quartile 4 shows the schemes whose returns are in the bottom 25% of the range."

Sheet Money Market Fund
A1: Main Page | E1: Data Source: ACEMF | CA1: Quartile code | CB1: 7 Days | CC1: 14 Days | CD1: 21 Days | CE1: 1 Month | CF1: 3 Month | CG1: 6 Months | CH1: YTD | CI1: 1 Year | CJ1: 2 Year | CK1: 3 Year | CL1: 4 Years | CM1: 5 Years | CN1: 7 Years | CO1: 10 Years | CP1: 15 Years | CQ1: Inception
CA2: 0 | CB2: =_xlfn.QUARTILE.INC(F$12:F$36,$CA2) -> -1.9426 | CC2: =_xlfn.QUARTILE.INC(G$12:G$36,$CA2) -> -0.3119 | CD2: =_xlfn.QUARTILE.INC(H$12:H$36,$CA2) -> 2.7972 | CE2: =_xlfn.QUARTILE.INC(I$12:I$36,$CA2) -> 3.9817 | CF2: =_xlfn.QUARTILE.INC(J$12:J$36,$CA2) -> 4.7597 | CG2: =_xlfn.QUARTILE.INC(K$12:K$36,$CA2) -> 5.257 | CH2: =_xlfn.QUARTILE.INC(L$12:L$36,$CA2) -> 4.3557 | CI2: =_xlfn.QUARTILE.INC(M$12:M$36,$CA2) -> 5.7593 | ... CQ2: =_xlfn.QUARTILE.INC(U$12:U$36,$CA2) -> 4.7199
CA3: 1 | CB3: =_xlfn.QUARTILE.INC(F$12:F$36,$CA3) -> -1.5878 | CC3: =_xlfn.QUARTILE.INC(G$12:G$36,$CA3) -> 0.0722 | CD3: =_xlfn.QUARTILE.INC(H$12:H$36,$CA3) -> 3.8084 | CE3: =_xlfn.QUARTILE.INC(I$12:I$36,$CA3) -> 7.143 | CF3: =_xlfn.QUARTILE.INC(J$12:J$36,$CA3) -> 5.9717 | CG3: =_xlfn.QUARTILE.INC(K$12:K$36,$CA3) -> 5.5567 | CH3: =_xlfn.QUARTILE.INC(L$12:L$36,$CA3) -> 5.4058 | CI3: =_xlfn.QUARTILE.INC(M$12:M$36,$CA3) -> 6.035775 | ... CQ3: =_xlfn.QUARTILE.INC(U$12:U$36,$CA3) -> 6.1688
CA4: 2 | CB4: =_xlfn.QUARTILE.INC(F$12:F$36,$CA4) -> -1.2769 | CC4: =_xlfn.QUARTILE.INC(G$12:G$36,$CA4) -> 0.3021 | CD4: =_xlfn.QUARTILE.INC(H$12:H$36,$CA4) -> 3.9734 | CE4: =_xlfn.QUARTILE.INC(I$12:I$36,$CA4) -> 7.3478 | CF4: =_xlfn.QUARTILE.INC(J$12:J$36,$CA4) -> 6.2301 | CG4: =_xlfn.QUARTILE.INC(K$12:K$36,$CA4) -> 5.69075 | CH4: =_xlfn.QUARTILE.INC(L$12:L$36,$CA4) -> 5.5532 | CI4: =_xlfn.QUARTILE.INC(M$12:M$36,$CA4) -> 6.23005 | ... CQ4: =_xlfn.QUARTILE.INC(U$12:U$36,$CA4) -> 6.7414
CA5: 3 | CB5: =_xlfn.QUARTILE.INC(F$12:F$36,$CA5) -> -0.959 | CC5: =_xlfn.QUARTILE.INC(G$12:G$36,$CA5) -> 0.5658 | CD5: =_xlfn.QUARTILE.INC(H$12:H$36,$CA5) -> 4.1166 | CE5: =_xlfn.QUARTILE.INC(I$12:I$36,$CA5) -> 7.5029 | CF5: =_xlfn.QUARTILE.INC(J$12:J$36,$CA5) -> 6.3234 | CG5: =_xlfn.QUARTILE.INC(K$12:K$36,$CA5) -> 5.7699 | CH5: =_xlfn.QUARTILE.INC(L$12:L$36,$CA5) -> 5.682 | CI5: =_xlfn.QUARTILE.INC(M$12:M$36,$CA5) -> 6.297725 | ... CQ5: =_xlfn.QUARTILE.INC(U$12:U$36,$CA5) -> 7.0435
CB6: =_xlfn.QUARTILE.INC(F$12:F$36,$CA6) -> -1.9426 | CC6: =_xlfn.QUARTILE.INC(G$12:G$36,$CA6) -> -0.3119 | CD6: =_xlfn.QUARTILE.INC(H$12:H$36,$CA6) -> 2.7972 | CE6: =_xlfn.QUARTILE.INC(I$12:I$36,$CA6) -> 3.9817 | CF6: =_xlfn.QUARTILE.INC(J$12:J$36,$CA6) -> 4.7597 | CG6: =_xlfn.QUARTILE.INC(K$12:K$36,$CA6) -> 5.257 | CH6: =_xlfn.QUARTILE.INC(L$12:L$36,$CA6) -> 4.3557 | CI6: =_xlfn.QUARTILE.INC(M$12:M$36,$CA6) -> 5.7593 | ... CQ6: =_xlfn.QUARTILE.INC(U$12:U$36,$CA6) -> 4.7199
A7: Fund Barometer - Money Market Fund | CA7: 4 | CB7: =_xlfn.QUARTILE.INC(F$12:F$36,$CA7) -> 0.8689 | CC7: =_xlfn.QUARTILE.INC(G$12:G$36,$CA7) -> 1.9289 | CD7: =_xlfn.QUARTILE.INC(H$12:H$36,$CA7) -> 4.8624 | CE7: =_xlfn.QUARTILE.INC(I$12:I$36,$CA7) -> 7.8209 | CF7: =_xlfn.QUARTILE.INC(J$12:J$36,$CA7) -> 6.4843 | CG7: =_xlfn.QUARTILE.INC(K$12:K$36,$CA7) -> 5.844 | CH7: =_xlfn.QUARTILE.INC(L$12:L$36,$CA7) -> 5.8461 | CI7: =_xlfn.QUARTILE.INC(M$12:M$36,$CA7) -> 6.3445 | ... CQ7: =_xlfn.QUARTILE.INC(U$12:U$36,$CA7) -> 7.31
A8: ='Liquid Fund'!A8 -> (As on 30 Apr 2026) | B8: Value Information | F8: Simple Annualized (%) | M8: Compound Annualized (%) | U8: Since Inception | V8: Quartile | AL8: Credit Quality | AO8: Modified Duration (Years) | AP8: Average Maturity (Years) | AQ8: YTM | AR8: Expense Ratio(%)
A9: Scheme Name | B9: Launch Date | C9: Fund Size (Rs Crs) Feb26 | D9: Fund Size (Rs Crs) Mar26 | E9: Latest NAV | F9: 7 Days | G9: 14 Days | H9: 21 Days | I9: 1 Month | J9: 3 Months | K9: 6 Months | L9: YTD | M9: 1 Year | N9: 2 Years | O9: 3 Years | P9: 4 Years | Q9: 5 Years | R9: 7 Years | S9: 10 Years | T9: 15 Years | V9: 7 Days | W9: 14 Days | X9: 21 Days | Y9: 1 Month | Z9: 3 Months | AA9: 6 Months | AB9: YTD | AC9: 1 Year | AD9: 2 Years | AE9: 3 Years | AF9: 4 Years | AG9: 5 Years | AH9: 7 Years | AI9: 10 Years | AJ9: 15 Years | AK9: Since Inception | AL9: AA minus and Above | AM9: Below AA minus | AN9: Cash & Cash Equivalent
A10: To view Exit Loads of any Scheme in this group please click here
A11: Money Market Fund
A12: Aditya Birla SL Money Manager Fund(G) | B12: 38638 | C12: 30777.544 | D12: 28780.111 | E12: 389.1462 | F12: -1.4092 | G12: 0.0837 | H12: 3.9649 | I12: 7.5802 | J12: 6.4843 | K12: 5.6983 | L12: 5.5757 | M12: 6.2975 | N12: 7.1418 | O12: 7.2752 | P12: 6.9668 | Q12: 6.3495 | R12: 6.4322 | S12: 6.7277 | T12: 7.5249 | U12: 6.8318 | V12: =IF(F12="",0,IF(F12<=CB$3,4,IF(F12>=CB$5,1,IF(F12>=CB$4,2,3)))) -> 3 | W12: =IF(G12="",0,IF(G12<=CC$3,4,IF(G12>=CC$5,1,IF(G12>=CC$4,2,3)))) -> 3 | X12: =IF(H12="",0,IF(H12<=CD$3,4,IF(H12>=CD$5,1,IF(H12>=CD$4,2,3)))) -> 3 | Y12: =IF(I12="",0,IF(I12<=CE$3,4,IF(I12>=CE$5,1,IF(I12>=CE$4,2,3)))) -> 1 | Z12: =IF(J12="",0,IF(J12<=CF$3,4,IF(J12>=CF$5,1,IF(J12>=CF$4,2,3)))) -> 1 | AA12: =IF(K12="",0,IF(K12<=CG$3,4,IF(K12>=CG$5,1,IF(K12>=CG$4,2,3)))) -> 2 | AB12: =IF(L12="",0,IF(L12<=CH$3,4,IF(L12>=CH$5,1,IF(L12>=CH$4,2,3)))) -> 2 | AC12: =IF(M12="",0,IF(M12<=CI$3,4,IF(M12>=CI$5,1,IF(M12>=CI$4,2,3)))) -> 2 | ... AK12: =IF(U12="",0,IF(U12<=CQ$3,4,IF(U12>=CQ$5,1,IF(U12>=CQ$4,2,3)))) -> 2 | AL12: 101.6149 | AM12: 0.2759 | AN12: -1.8908 | AO12: 0.76 | AP12: 0.76 | AQ12: 7.38 | AR12: 0.37
A13: Axis Money Market Fund-Reg(G) | B13: 43683 | C13: 23789.675 | D13: 20349.468 | E13: 1505.8142 | F13: -1.0262 | G13: 0.4272 | H13: 4.1093 | I13: 7.4741 | J13: 6.3036 | K13: 5.8177 | L13: 5.7126 | M13: 6.3445 | N13: 7.1905 | O13: 7.2812 | P13: 6.9562 | Q13: 6.3235 | U13: 6.2643 | V13: =IF(F13="",0,IF(F13<=CB$3,4,IF(F13>=CB$5,1,IF(F13>=CB$4,2,3)))) -> 2 | W13: =IF(G13="",0,IF(G13<=CC$3,4,IF(G13>=CC$5,1,IF(G13>=CC$4,2,3)))) -> 2 | X13: =IF(H13="",0,IF(H13<=CD$3,4,IF(H13>=CD$5,1,IF(H13>=CD$4,2,3)))) -> 2 | Y13: =IF(I13="",0,IF(I13<=CE$3,4,IF(I13>=CE$5,1,IF(I13>=CE$4,2,3)))) -> 2 | Z13: =IF(J13="",0,IF(J13<=CF$3,4,IF(J13>=CF$5,1,IF(J13>=CF$4,2,3)))) -> 2 | AA13: =IF(K13="",0,IF(K13<=CG$3,4,IF(K13>=CG$5,1,IF(K13>=CG$4,2,3)))) -> 1 | AB13: =IF(L13="",0,IF(L13<=CH$3,4,IF(L13>=CH$5,1,IF(L13>=CH$4,2,3)))) -> 1 | AC13: =IF(M13="",0,IF(M13<=CI$3,4,IF(M13>=CI$5,1,IF(M13>=CI$4,2,3)))) -> 1 | ... AK13: =IF(U13="",0,IF(U13<=CQ$3,4,IF(U13>=CQ$5,1,IF(U13>=CQ$4,2,3)))) -> 3 | AL13: 103.0007 | AM13: 0.2935 | AN13: -3.2865 | AO13: 0.7425 | AP13: 0.7973 | AQ13: 7.19 | AR13: 0.34
A14: Bajaj Finserv Money Market Fund-Reg(G) | B14: 45131 | C14: 4991.4132 | D14: 4380.9921 | E14: 1202.508 | F14: -1.3794 | G14: -0.0798 | H14: 3.6104 | I14: 7.0764 | J14: 5.7108 | K14: 5.257 | L14: 5.1762 | M14: 5.802 | N14: 6.6593 | U14: 6.8843 | V14: =IF(F14="",0,IF(F14<=CB$3,4,IF(F14>=CB$5,1,IF(F14>=CB$4,2,3)))) -> 3 | W14: =IF(G14="",0,IF(G14<=CC$3,4,IF(G14>=CC$5,1,IF(G14>=CC$4,2,3)))) -> 4 | X14: =IF(H14="",0,IF(H14<=CD$3,4,IF(H14>=CD$5,1,IF(H14>=CD$4,2,3)))) -> 4 | Y14: =IF(I14="",0,IF(I14<=CE$3,4,IF(I14>=CE$5,1,IF(I14>=CE$4,2,3)))) -> 4 | Z14: =IF(J14="",0,IF(J14<=CF$3,4,IF(J14>=CF$5,1,IF(J14>=CF$4,2,3)))) -> 4 | AA14: =IF(K14="",0,IF(K14<=CG$3,4,IF(K14>=CG$5,1,IF(K14>=CG$4,2,3)))) -> 4 | AB14: =IF(L14="",0,IF(L14<=CH$3,4,IF(L14>=CH$5,1,IF(L14>=CH$4,2,3)))) -> 4 | AC14: =IF(M14="",0,IF(M14<=CI$3,4,IF(M14>=CI$5,1,IF(M14>=CI$4,2,3)))) -> 4 | ... AK14: =IF(U14="",0,IF(U14<=CQ$3,4,IF(U14>=CQ$5,1,IF(U14>=CQ$4,2,3)))) -> 2 | AL14: 96.3367 | AM14: 0.3472 | AN14: 3.3161 | AO14: 0.7096 | AP14: 0.7589 | AQ14: 7.12 | AR14: 0.76
A15: Bandhan Money Market Fund-Reg(G) | B15: 37670 | C15: 14805.349 | D15: 13437.112 | E15: 42.4021 | F15: -0.959 | G15: 0.5658 | H15: 4.4095 | I15: 7.3767 | J15: 6.2634 | K15: 5.844 | L15: 5.7626 | M15: 6.3053 | N15: 7.0002 | O15: 6.9102 | P15: 6.4891 | Q15: 5.7923 | R15: 5.6217 | S15: 5.9249 | T15: 6.7774 | U15: 6.4216 | V15: =IF(F15="",0,IF(F15<=CB$3,4,IF(F15>=CB$5,1,IF(F15>=CB$4,2,3)))) -> 1 | W15: =IF(G15="",0,IF(G15<=CC$3,4,IF(G15>=CC$5,1,IF(G15>=CC$4,2,3)))) -> 1 | X15: =IF(H15="",0,IF(H15<=CD$3,4,IF(H15>=CD$5,1,IF(H15>=CD$4,2,3)))) -> 1 | Y15: =IF(I15="",0,IF(I15<=CE$3,4,IF(I15>=CE$5,1,IF(I15>=CE$4,2,3)))) -> 2 | Z15: =IF(J15="",0,IF(J15<=CF$3,4,IF(J15>=CF$5,1,IF(J15>=CF$4,2,3)))) -> 2 | AA15: =IF(K15="",0,IF(K15<=CG$3,4,IF(K15>=CG$5,1,IF(K15>=CG$4,2,3)))) -> 1 | AB15: =IF(L15="",0,IF(L15<=CH$3,4,IF(L15>=CH$5,1,IF(L15>=CH$4,2,3)))) -> 1 | AC15: =IF(M15="",0,IF(M15<=CI$3,4,IF(M15>=CI$5,1,IF(M15>=CI$4,2,3)))) -> 1 | ... AK15: =IF(U15="",0,IF(U15<=CQ$3,4,IF(U15>=CQ$5,1,IF(U15>=CQ$4,2,3)))) -> 3 | AL15: 96.0476 | AM15: 0.2624 | AN15: 3.6901 | AO15: 0.7479 | AP15: 0.7479 | AQ15: 7.12 | AR15: 0.35
A16: Bank of India Money Market Fund-Reg(G) | B16: 45692 | C16: 400.6521 | D16: 427.0558 | E16: 10.8293 | F16: -1.4922 | G16: 0.0722 | H16: 3.9734 | I16: 7.2089 | J16: 6.4487 | K16: 5.6161 | L16: 5.5862 | M16: 6.0459 | U16: 6.6755 | V16: =IF(F16="",0,IF(F16<=CB$3,4,IF(F16>=CB$5,1,IF(F16>=CB$4,2,3)))) -> 3 | W16: =IF(G16="",0,IF(G16<=CC$3,4,IF(G16>=CC$5,1,IF(G16>=CC$4,2,3)))) -> 4 | X16: =IF(H16="",0,IF(H16<=CD$3,4,IF(H16>=CD$5,1,IF(H16>=CD$4,2,3)))) -> 2 | Y16: =IF(I16="",0,IF(I16<=CE$3,4,IF(I16>=CE$5,1,IF(I16>=CE$4,2,3)))) -> 3 | Z16: =IF(J16="",0,IF(J16<=CF$3,4,IF(J16>=CF$5,1,IF(J16>=CF$4,2,3)))) -> 1 | AA16: =IF(K16="",0,IF(K16<=CG$3,4,IF(K16>=CG$5,1,IF(K16>=CG$4,2,3)))) -> 3 | AB16: =IF(L16="",0,IF(L16<=CH$3,4,IF(L16>=CH$5,1,IF(L16>=CH$4,2,3)))) -> 2 | AC16: =IF(M16="",0,IF(M16<=CI$3,4,IF(M16>=CI$5,1,IF(M16>=CI$4,2,3)))) -> 3 | ... AK16: =IF(U16="",0,IF(U16<=CQ$3,4,IF(U16>=CQ$5,1,IF(U16>=CQ$4,2,3)))) -> 3 | AL16: 104.4994 | AM16: 0.2231 | AN16: -4.7224 | AO16: 1.01 | AP16: 0.83 | AQ16: 7.17 | AR16: 0.56
A17: Baroda BNP Paribas Money Market Fund-Reg(G) | B17: 43635 | C17: 4964.82 | D17: 4364.9692 | E17: 1449.2525 | F17: -1.2769 | G17: 0.3165 | H17: 3.9407 | I17: 7.587 | J17: 6.3258 | K17: 5.615 | L17: 5.4819 | M17: 6.2594 | N17: 6.9963 | O17: 6.9928 | P17: 6.5778 | Q17: 5.9128 | U17: 5.5508 | V17: =IF(F17="",0,IF(F17<=CB$3,4,IF(F17>=CB$5,1,IF(F17>=CB$4,2,3)))) -> 2 | W17: =IF(G17="",0,IF(G17<=CC$3,4,IF(G17>=CC$5,1,IF(G17>=CC$4,2,3)))) -> 2 | X17: =IF(H17="",0,IF(H17<=CD$3,4,IF(H17>=CD$5,1,IF(H17>=CD$4,2,3)))) -> 3 | Y17: =IF(I17="",0,IF(I17<=CE$3,4,IF(I17>=CE$5,1,IF(I17>=CE$4,2,3)))) -> 1 | Z17: =IF(J17="",0,IF(J17<=CF$3,4,IF(J17>=CF$5,1,IF(J17>=CF$4,2,3)))) -> 1 | AA17: =IF(K17="",0,IF(K17<=CG$3,4,IF(K17>=CG$5,1,IF(K17>=CG$4,2,3)))) -> 3 | AB17: =IF(L17="",0,IF(L17<=CH$3,4,IF(L17>=CH$5,1,IF(L17>=CH$4,2,3)))) -> 3 | AC17: =IF(M17="",0,IF(M17<=CI$3,4,IF(M17>=CI$5,1,IF(M17>=CI$4,2,3)))) -> 2 | ... AK17: =IF(U17="",0,IF(U17<=CQ$3,4,IF(U17>=CQ$5,1,IF(U17>=CQ$4,2,3)))) -> 4 | AL17: 99.6945 | AM17: 0.2968 | AN17: 0.0087 | AO17: 0.72 | AP17: 0.72 | AQ17: 7.26 | AR17: 0.37
A18: DSP Savings Fund-Reg(G) | B18: 36433 | C18: 8549.0684 | D18: 8947.396 | E18: 55.2965 | F18: -1.4235 | G18: 0.2358 | H18: 4.0042 | I18: 7.7157 | J18: 6.4722 | K18: 5.6873 | L18: 5.5774 | M18: 6.1755 | N18: 6.85 | O18: 6.9638 | P18: 6.5592 | Q18: 5.9356 | R18: 6.0028 | S18: 6.181 | T18: 6.8284 | U18: 6.6402 | V18: =IF(F18="",0,IF(F18<=CB$3,4,IF(F18>=CB$5,1,IF(F18>=CB$4,2,3)))) -> 3 | W18: =IF(G18="",0,IF(G18<=CC$3,4,IF(G18>=CC$5,1,IF(G18>=CC$4,2,3)))) -> 3 | X18: =IF(H18="",0,IF(H18<=CD$3,4,IF(H18>=CD$5,1,IF(H18>=CD$4,2,3)))) -> 2 | Y18: =IF(I18="",0,IF(I18<=CE$3,4,IF(I18>=CE$5,1,IF(I18>=CE$4,2,3)))) -> 1 | Z18: =IF(J18="",0,IF(J18<=CF$3,4,IF(J18>=CF$5,1,IF(J18>=CF$4,2,3)))) -> 1 | AA18: =IF(K18="",0,IF(K18<=CG$3,4,IF(K18>=CG$5,1,IF(K18>=CG$4,2,3)))) -> 3 | AB18: =IF(L18="",0,IF(L18<=CH$3,4,IF(L18>=CH$5,1,IF(L18>=CH$4,2,3)))) -> 2 | AC18: =IF(M18="",0,IF(M18<=CI$3,4,IF(M18>=CI$5,1,IF(M18>=CI$4,2,3)))) -> 3 | ... AK18: =IF(U18="",0,IF(U18<=CQ$3,4,IF(U18>=CQ$5,1,IF(U18>=CQ$4,2,3)))) -> 3 | AL18: 98.9086 | AM18: 0.2651 | AN18: 0.8263 | AO18: 0.72 | AP18: 0.77 | AQ18: 7.26 | AR18: 0.4
A19: Edelweiss Money Market Fund-Reg(G) | B19: 39626 | C19: 3026.9738 | D19: 2508.4503 | E19: 29.7833 | F19: -1.9426 | G19: -0.1751 | H19: 3.5613 | I19: 7.1352 | J19: 5.7939 | K19: 5.3388 | L19: 5.1048 | M19: 5.7593 | N19: 6.5538 | O19: 6.5764 | P19: 6.0918 | Q19: 5.4495 | R19: 6.1406 | S19: 6.2464 | T19: 6.711 | U19: 6.3041 | V19: =IF(F19="",0,IF(F19<=CB$3,4,IF(F19>=CB$5,1,IF(F19>=CB$4,2,3)))) -> 4 | W19: =IF(G19="",0,IF(G19<=CC$3,4,IF(G19>=CC$5,1,IF(G19>=CC$4,2,3)))) -> 4 | X19: =IF(H19="",0,IF(H19<=CD$3,4,IF(H19>=CD$5,1,IF(H19>=CD$4,2,3)))) -> 4 | Y19: =IF(I19="",0,IF(I19<=CE$3,4,IF(I19>=CE$5,1,IF(I19>=CE$4,2,3)))) -> 4 | Z19: =IF(J19="",0,IF(J19<=CF$3,4,IF(J19>=CF$5,1,IF(J19>=CF$4,2,3)))) -> 4 | AA19: =IF(K19="",0,IF(K19<=CG$3,4,IF(K19>=CG$5,1,IF(K19>=CG$4,2,3)))) -> 4 | AB19: =IF(L19="",0,IF(L19<=CH$3,4,IF(L19>=CH$5,1,IF(L19>=CH$4,2,3)))) -> 4 | AC19: =IF(M19="",0,IF(M19<=CI$3,4,IF(M19>=CI$5,1,IF(M19>=CI$4,2,3)))) -> 4 | ... AK19: =IF(U19="",0,IF(U19<=CQ$3,4,IF(U19>=CQ$5,1,IF(U19>=CQ$4,2,3)))) -> 3 | AL19: 106.5972 | AM19: 0.2763 | AN19: -6.8735 | AO19: 0.8 | AP19: 0.8 | AQ19: 7.23 | AR19: 0.77
A20: Franklin India Money Market Fund(G) | B20: 37298 | C20: 4351.8588 | D20: 3959.3795 | E20: 52.7761 | F20: -0.5038 | G20: 0.7462 | H20: 4.1198 | I20: 7.5079 | J20: 6.1297 | K20: 5.8112 | L20: 5.6915 | M20: 6.2984 | N20: 7.1731 | O20: 7.2402 | P20: 6.8532 | Q20: 6.1939 | R20: 6.2581 | S20: 6.6611 | T20: 7.4085 | U20: 7.1065 | V20: =IF(F20="",0,IF(F20<=CB$3,4,IF(F20>=CB$5,1,IF(F20>=CB$4,2,3)))) -> 1 | W20: =IF(G20="",0,IF(G20<=CC$3,4,IF(G20>=CC$5,1,IF(G20>=CC$4,2,3)))) -> 1 | X20: =IF(H20="",0,IF(H20<=CD$3,4,IF(H20>=CD$5,1,IF(H20>=CD$4,2,3)))) -> 1 | Y20: =IF(I20="",0,IF(I20<=CE$3,4,IF(I20>=CE$5,1,IF(I20>=CE$4,2,3)))) -> 1 | Z20: =IF(J20="",0,IF(J20<=CF$3,4,IF(J20>=CF$5,1,IF(J20>=CF$4,2,3)))) -> 3 | AA20: =IF(K20="",0,IF(K20<=CG$3,4,IF(K20>=CG$5,1,IF(K20>=CG$4,2,3)))) -> 1 | AB20: =IF(L20="",0,IF(L20<=CH$3,4,IF(L20>=CH$5,1,IF(L20>=CH$4,2,3)))) -> 1 | AC20: =IF(M20="",0,IF(M20<=CI$3,4,IF(M20>=CI$5,1,IF(M20>=CI$4,2,3)))) -> 1 | ... AK20: =IF(U20="",0,IF(U20<=CQ$3,4,IF(U20>=CQ$5,1,IF(U20>=CQ$4,2,3)))) -> 1 | AL20: 99.6112 | AM20: 0.2656 | AN20: 0.1233 | AO20: 0.73 | AP20: 0.78 | AQ20: 7.3 | AR20: 0.28
A21: Groww Money Market Fund-Reg(G) | B21: 45980 | C21: 21.6139 | D21: 73.2193 | E21: 10.2068 | F21: 0.5109 | G21: 1.3801 | H21: 2.7972 | I21: 3.9817 | J21: 4.7597 | L21: 4.3557 | U21: 4.7199 | V21: =IF(F21="",0,IF(F21<=CB$3,4,IF(F21>=CB$5,1,IF(F21>=CB$4,2,3)))) -> 1 | W21: =IF(G21="",0,IF(G21<=CC$3,4,IF(G21>=CC$5,1,IF(G21>=CC$4,2,3)))) -> 1 | X21: =IF(H21="",0,IF(H21<=CD$3,4,IF(H21>=CD$5,1,IF(H21>=CD$4,2,3)))) -> 4 | Y21: =IF(I21="",0,IF(I21<=CE$3,4,IF(I21>=CE$5,1,IF(I21>=CE$4,2,3)))) -> 4 | Z21: =IF(J21="",0,IF(J21<=CF$3,4,IF(J21>=CF$5,1,IF(J21>=CF$4,2,3)))) -> 4 | AA21: =IF(K21="",0,IF(K21<=CG$3,4,IF(K21>=CG$5,1,IF(K21>=CG$4,2,3)))) -> 0 | AB21: =IF(L21="",0,IF(L21<=CH$3,4,IF(L21>=CH$5,1,IF(L21>=CH$4,2,3)))) -> 4 | AC21: =IF(M21="",0,IF(M21<=CI$3,4,IF(M21>=CI$5,1,IF(M21>=CI$4,2,3)))) -> 0 | ... AK21: =IF(U21="",0,IF(U21<=CQ$3,4,IF(U21>=CQ$5,1,IF(U21>=CQ$4,2,3)))) -> 4 | AL21: 24.7423 | AM21: 0.0782 | AN21: 75.1794 | AO21: 0.17 | AP21: 0.17 | AQ21: 6.73 | AR21: 0.74
A22: HDFC Money Market Fund-Reg(G) | B22: 36528 | C22: 33094.052 | D22: 28187.696 | E22: 6011.5763 | F22: -1.7154 | G22: 0.0077 | H22: 3.7857 | I22: 7.299 | J22: 6.2675 | K22: 5.768 | L22: 5.6926 | M22: 6.2729 | N22: 7.116 | O22: 7.2164 | P22: 6.8894 | Q22: 6.2713 | R22: 6.3735 | S22: 6.5847 | T22: 7.3833 | U22: 7.0013 | V22: =IF(F22="",0,IF(F22<=CB$3,4,IF(F22>=CB$5,1,IF(F22>=CB$4,2,3)))) -> 4 | W22: =IF(G22="",0,IF(G22<=CC$3,4,IF(G22>=CC$5,1,IF(G22>=CC$4,2,3)))) -> 4 | X22: =IF(H22="",0,IF(H22<=CD$3,4,IF(H22>=CD$5,1,IF(H22>=CD$4,2,3)))) -> 4 | Y22: =IF(I22="",0,IF(I22<=CE$3,4,IF(I22>=CE$5,1,IF(I22>=CE$4,2,3)))) -> 3 | Z22: =IF(J22="",0,IF(J22<=CF$3,4,IF(J22>=CF$5,1,IF(J22>=CF$4,2,3)))) -> 2 | AA22: =IF(K22="",0,IF(K22<=CG$3,4,IF(K22>=CG$5,1,IF(K22>=CG$4,2,3)))) -> 2 | AB22: =IF(L22="",0,IF(L22<=CH$3,4,IF(L22>=CH$5,1,IF(L22>=CH$4,2,3)))) -> 1 | AC22: =IF(M22="",0,IF(M22<=CI$3,4,IF(M22>=CI$5,1,IF(M22>=CI$4,2,3)))) -> 2 | ... AK22: =IF(U22="",0,IF(U22<=CQ$3,4,IF(U22>=CQ$5,1,IF(U22>=CQ$4,2,3)))) -> 2 | AL22: 96.3434 | AM22: 0.324 | AN22: 3.3326 | AO22: 0.6667 | AP22: 0.719 | AQ22: 7.33 | AR22: 0.46
A23: HSBC Money Market Fund-Reg(G) | B23: 38574 | C23: 5379.2926 | D23: 5970.362 | E23: 27.7365 | F23: -1.2217 | G23: 0.3666 | H23: 4.1709 | I23: 7.4158 | J23: 6.0924 | K23: 5.6278 | L23: 5.4622 | M23: 6.1855 | N23: 7.0096 | O23: 7.0345 | P23: 6.6031 | Q23: 5.9015 | R23: 5.9064 | S23: 6.4923 | T23: 7.3599 | U23: 7.1174 | V23: =IF(F23="",0,IF(F23<=CB$3,4,IF(F23>=CB$5,1,IF(F23>=CB$4,2,3)))) -> 2 | W23: =IF(G23="",0,IF(G23<=CC$3,4,IF(G23>=CC$5,1,IF(G23>=CC$4,2,3)))) -> 2 | X23: =IF(H23="",0,IF(H23<=CD$3,4,IF(H23>=CD$5,1,IF(H23>=CD$4,2,3)))) -> 1 | Y23: =IF(I23="",0,IF(I23<=CE$3,4,IF(I23>=CE$5,1,IF(I23>=CE$4,2,3)))) -> 2 | Z23: =IF(J23="",0,IF(J23<=CF$3,4,IF(J23>=CF$5,1,IF(J23>=CF$4,2,3)))) -> 3 | AA23: =IF(K23="",0,IF(K23<=CG$3,4,IF(K23>=CG$5,1,IF(K23>=CG$4,2,3)))) -> 3 | AB23: =IF(L23="",0,IF(L23<=CH$3,4,IF(L23>=CH$5,1,IF(L23>=CH$4,2,3)))) -> 3 | AC23: =IF(M23="",0,IF(M23<=CI$3,4,IF(M23>=CI$5,1,IF(M23>=CI$4,2,3)))) -> 3 | ... AK23: =IF(U23="",0,IF(U23<=CQ$3,4,IF(U23>=CQ$5,1,IF(U23>=CQ$4,2,3)))) -> 1 | AL23: 97.551 | AM23: 0.2217 | AN23: 2.2273 | AO23: 0.7586 | AP23: 0.8062 | AQ23: 7.2 | AR23: 0.34
A24: ICICI Pru Money Market Fund(G) | B24: 38784 | C24: 35305.071 | D24: 31749.719 | E24: 399.1499 | F24: -1.6363 | G24: 0.0784 | H24: 3.8164 | I24: 7.143 | J24: 6.0473 | K24: 5.7401 | L24: 5.5801 | M24: 6.292 | N24: 7.1606 | O24: 7.2705 | P24: 6.942 | Q24: 6.2978 | R24: 6.3085 | S24: 6.6014 | T24: 7.4048 | U24: 7.1075 | V24: =IF(F24="",0,IF(F24<=CB$3,4,IF(F24>=CB$5,1,IF(F24>=CB$4,2,3)))) -> 4 | W24: =IF(G24="",0,IF(G24<=CC$3,4,IF(G24>=CC$5,1,IF(G24>=CC$4,2,3)))) -> 3 | X24: =IF(H24="",0,IF(H24<=CD$3,4,IF(H24>=CD$5,1,IF(H24>=CD$4,2,3)))) -> 3 | Y24: =IF(I24="",0,IF(I24<=CE$3,4,IF(I24>=CE$5,1,IF(I24>=CE$4,2,3)))) -> 4 | Z24: =IF(J24="",0,IF(J24<=CF$3,4,IF(J24>=CF$5,1,IF(J24>=CF$4,2,3)))) -> 3 | AA24: =IF(K24="",0,IF(K24<=CG$3,4,IF(K24>=CG$5,1,IF(K24>=CG$4,2,3)))) -> 2 | AB24: =IF(L24="",0,IF(L24<=CH$3,4,IF(L24>=CH$5,1,IF(L24>=CH$4,2,3)))) -> 2 | AC24: =IF(M24="",0,IF(M24<=CI$3,4,IF(M24>=CI$5,1,IF(M24>=CI$4,2,3)))) -> 2 | ... AK24: =IF(U24="",0,IF(U24<=CQ$3,4,IF(U24>=CQ$5,1,IF(U24>=CQ$4,2,3)))) -> 1 | AL24: 99.3332 | AM24: 0.2856 | AN24: 0.3812 | AO24: 0.7338 | AP24: 0.7898 | AQ24: 7.24 | AR24: 0.4
A25: Invesco India Money Market Fund(G) | B25: 40053 | C25: 6595.5639 | D25: 7153.8554 | E25: 3198.5217 | F25: -1.7692 | G25: 0.0976 | H25: 3.8084 | I25: 7.1531 | J25: 5.9233 | K25: 5.5623 | L25: 5.4058 | M25: 6.0809 | N25: 6.8889 | O25: 6.9799 | P25: 6.5458 | Q25: 5.9003 | R25: 5.8404 | S25: 6.2649 | T25: 7.3407 | U25: 7.2183 | V25: =IF(F25="",0,IF(F25<=CB$3,4,IF(F25>=CB$5,1,IF(F25>=CB$4,2,3)))) -> 4 | W25: =IF(G25="",0,IF(G25<=CC$3,4,IF(G25>=CC$5,1,IF(G25>=CC$4,2,3)))) -> 3 | X25: =IF(H25="",0,IF(H25<=CD$3,4,IF(H25>=CD$5,1,IF(H25>=CD$4,2,3)))) -> 4 | Y25: =IF(I25="",0,IF(I25<=CE$3,4,IF(I25>=CE$5,1,IF(I25>=CE$4,2,3)))) -> 3 | Z25: =IF(J25="",0,IF(J25<=CF$3,4,IF(J25>=CF$5,1,IF(J25>=CF$4,2,3)))) -> 4 | AA25: =IF(K25="",0,IF(K25<=CG$3,4,IF(K25>=CG$5,1,IF(K25>=CG$4,2,3)))) -> 3 | AB25: =IF(L25="",0,IF(L25<=CH$3,4,IF(L25>=CH$5,1,IF(L25>=CH$4,2,3)))) -> 4 | AC25: =IF(M25="",0,IF(M25<=CI$3,4,IF(M25>=CI$5,1,IF(M25>=CI$4,2,3)))) -> 3 | ... AK25: =IF(U25="",0,IF(U25<=CQ$3,4,IF(U25>=CQ$5,1,IF(U25>=CQ$4,2,3)))) -> 1 | AL25: 93.9254 | AM25: 0.2325 | AN25: 5.8421 | AO25: 0.6959 | AP25: 0.6959 | AQ25: 7.09 | AR25: 0.41
A26: Kotak Money Market Fund(G) | B26: 37816 | C26: 33661.366 | D26: 32331.253 | E26: 4723.8423 | F26: -1.2109 | G26: 0.455 | H26: 4.041 | I26: 7.2389 | J26: 6.3352 | K26: 5.7814 | L26: 5.682 | M26: 6.2943 | N26: 7.1363 | O26: 7.2444 | P26: 6.9291 | Q26: 6.3107 | R26: 6.2347 | S26: 6.571 | T26: 7.4081 | U26: 7.0435 | V26: =IF(F26="",0,IF(F26<=CB$3,4,IF(F26>=CB$5,1,IF(F26>=CB$4,2,3)))) -> 2 | W26: =IF(G26="",0,IF(G26<=CC$3,4,IF(G26>=CC$5,1,IF(G26>=CC$4,2,3)))) -> 2 | X26: =IF(H26="",0,IF(H26<=CD$3,4,IF(H26>=CD$5,1,IF(H26>=CD$4,2,3)))) -> 2 | Y26: =IF(I26="",0,IF(I26<=CE$3,4,IF(I26>=CE$5,1,IF(I26>=CE$4,2,3)))) -> 3 | Z26: =IF(J26="",0,IF(J26<=CF$3,4,IF(J26>=CF$5,1,IF(J26>=CF$4,2,3)))) -> 1 | AA26: =IF(K26="",0,IF(K26<=CG$3,4,IF(K26>=CG$5,1,IF(K26>=CG$4,2,3)))) -> 1 | AB26: =IF(L26="",0,IF(L26<=CH$3,4,IF(L26>=CH$5,1,IF(L26>=CH$4,2,3)))) -> 1 | AC26: =IF(M26="",0,IF(M26<=CI$3,4,IF(M26>=CI$5,1,IF(M26>=CI$4,2,3)))) -> 2 | ... AK26: =IF(U26="",0,IF(U26<=CQ$3,4,IF(U26>=CQ$5,1,IF(U26>=CQ$4,2,3)))) -> 1 | AL26: 102.6222 | AM26: 0.2863 | AN26: -2.9085 | AO26: 0.73 | AP26: 0.73 | AQ26: 7.24 | AR26: 0.35
A27: LIC MF Money Market Fund-Reg(G) | B27: 44774 | C27: 4900.2507 | D27: 4593.6322 | E27: 1249.6221 | F27: 0.3263 | G27: 1.7151 | H27: 4.8624 | I27: 7.4581 | J27: 6.2301 | K27: 5.6942 | L27: 5.5532 | M27: 6.232 | N27: 6.2492 | O27: 6.3142 | U27: 6.126 | V27: =IF(F27="",0,IF(F27<=CB$3,4,IF(F27>=CB$5,1,IF(F27>=CB$4,2,3)))) -> 1 | W27: =IF(G27="",0,IF(G27<=CC$3,4,IF(G27>=CC$5,1,IF(G27>=CC$4,2,3)))) -> 1 | X27: =IF(H27="",0,IF(H27<=CD$3,4,IF(H27>=CD$5,1,IF(H27>=CD$4,2,3)))) -> 1 | Y27: =IF(I27="",0,IF(I27<=CE$3,4,IF(I27>=CE$5,1,IF(I27>=CE$4,2,3)))) -> 2 | Z27: =IF(J27="",0,IF(J27<=CF$3,4,IF(J27>=CF$5,1,IF(J27>=CF$4,2,3)))) -> 2 | AA27: =IF(K27="",0,IF(K27<=CG$3,4,IF(K27>=CG$5,1,IF(K27>=CG$4,2,3)))) -> 2 | AB27: =IF(L27="",0,IF(L27<=CH$3,4,IF(L27>=CH$5,1,IF(L27>=CH$4,2,3)))) -> 2 | AC27: =IF(M27="",0,IF(M27<=CI$3,4,IF(M27>=CI$5,1,IF(M27>=CI$4,2,3)))) -> 2 | ... AK27: =IF(U27="",0,IF(U27<=CQ$3,4,IF(U27>=CQ$5,1,IF(U27>=CQ$4,2,3)))) -> 4 | AL27: 90.6875 | AM27: 0.2562 | AN27: 9.0562 | AO27: 0.5747 | AP27: 0.5747 | AQ27: 7.2 | AR27: 0.88
A28: Mirae Asset Money Market Fund-Reg(G) | B28: 44419 | C28: 3769.1611 | D28: 3351.3804 | E28: 1322.4448 | F28: -1.2819 | G28: 0.222 | H28: 3.9502 | I28: 7.2838 | J28: 5.9418 | K28: 5.4428 | L28: 5.2541 | M28: 6.0558 | N28: 6.9638 | O28: 7.0219 | P28: 6.6215 | U28: 6.0993 | V28: =IF(F28="",0,IF(F28<=CB$3,4,IF(F28>=CB$5,1,IF(F28>=CB$4,2,3)))) -> 3 | W28: =IF(G28="",0,IF(G28<=CC$3,4,IF(G28>=CC$5,1,IF(G28>=CC$4,2,3)))) -> 3 | X28: =IF(H28="",0,IF(H28<=CD$3,4,IF(H28>=CD$5,1,IF(H28>=CD$4,2,3)))) -> 3 | Y28: =IF(I28="",0,IF(I28<=CE$3,4,IF(I28>=CE$5,1,IF(I28>=CE$4,2,3)))) -> 3 | Z28: =IF(J28="",0,IF(J28<=CF$3,4,IF(J28>=CF$5,1,IF(J28>=CF$4,2,3)))) -> 4 | AA28: =IF(K28="",0,IF(K28<=CG$3,4,IF(K28>=CG$5,1,IF(K28>=CG$4,2,3)))) -> 4 | AB28: =IF(L28="",0,IF(L28<=CH$3,4,IF(L28>=CH$5,1,IF(L28>=CH$4,2,3)))) -> 4 | AC28: =IF(M28="",0,IF(M28<=CI$3,4,IF(M28>=CI$5,1,IF(M28>=CI$4,2,3)))) -> 3 | ... AK28: =IF(U28="",0,IF(U28<=CQ$3,4,IF(U28>=CQ$5,1,IF(U28>=CQ$4,2,3)))) -> 4 | AL28: 93.7929 | AM28: 0.257 | AN28: 5.9501 | AO28: 0.77 | AP28: 0.82 | AQ28: 7.05 | AR28: 0.41
A29: Nippon India Money Market Fund(G) | B29: 38518 | C29: 21876.273 | D29: 19419.682 | E29: 4365.1765 | F29: -1.2377 | G29: 0.3021 | H29: 4.0232 | I29: 7.4305 | J29: 6.2646 | K29: 5.6971 | L29: 5.5523 | M29: 6.2998 | N29: 7.148 | O29: 7.2706 | P29: 6.9817 | Q29: 6.3606 | R29: 6.3447 | S29: 6.6478 | T29: 7.437 | U29: 7.31 | V29: =IF(F29="",0,IF(F29<=CB$3,4,IF(F29>=CB$5,1,IF(F29>=CB$4,2,3)))) -> 2 | W29: =IF(G29="",0,IF(G29<=CC$3,4,IF(G29>=CC$5,1,IF(G29>=CC$4,2,3)))) -> 2 | X29: =IF(H29="",0,IF(H29<=CD$3,4,IF(H29>=CD$5,1,IF(H29>=CD$4,2,3)))) -> 2 | Y29: =IF(I29="",0,IF(I29<=CE$3,4,IF(I29>=CE$5,1,IF(I29>=CE$4,2,3)))) -> 2 | Z29: =IF(J29="",0,IF(J29<=CF$3,4,IF(J29>=CF$5,1,IF(J29>=CF$4,2,3)))) -> 2 | AA29: =IF(K29="",0,IF(K29<=CG$3,4,IF(K29>=CG$5,1,IF(K29>=CG$4,2,3)))) -> 2 | AB29: =IF(L29="",0,IF(L29<=CH$3,4,IF(L29>=CH$5,1,IF(L29>=CH$4,2,3)))) -> 3 | AC29: =IF(M29="",0,IF(M29<=CI$3,4,IF(M29>=CI$5,1,IF(M29>=CI$4,2,3)))) -> 1 | ... AK29: =IF(U29="",0,IF(U29<=CQ$3,4,IF(U29>=CQ$5,1,IF(U29>=CQ$4,2,3)))) -> 1 | AL29: 101.7339 | AM29: 0.3038 | AN29: -2.0377 | AO29: 0.7288 | AP29: 0.7836 | AQ29: 7.32 | AR29: 0.41
A30: PGIM India Money Market Fund-Reg(G) | B30: 43896 | C30: 225.7338 | D30: 152.4377 | E30: 1392.5621 | F30: -1.8139 | G30: 0.0418 | H30: 3.8119 | I30: 7.5029 | J30: 5.9717 | K30: 5.4286 | L30: 5.3463 | M30: 6.0054 | N30: 6.8285 | O30: 6.8837 | P30: 6.6055 | Q30: 5.895 | U30: 5.5289 | V30: =IF(F30="",0,IF(F30<=CB$3,4,IF(F30>=CB$5,1,IF(F30>=CB$4,2,3)))) -> 4 | W30: =IF(G30="",0,IF(G30<=CC$3,4,IF(G30>=CC$5,1,IF(G30>=CC$4,2,3)))) -> 4 | X30: =IF(H30="",0,IF(H30<=CD$3,4,IF(H30>=CD$5,1,IF(H30>=CD$4,2,3)))) -> 3 | Y30: =IF(I30="",0,IF(I30<=CE$3,4,IF(I30>=CE$5,1,IF(I30>=CE$4,2,3)))) -> 1 | Z30: =IF(J30="",0,IF(J30<=CF$3,4,IF(J30>=CF$5,1,IF(J30>=CF$4,2,3)))) -> 4 | AA30: =IF(K30="",0,IF(K30<=CG$3,4,IF(K30>=CG$5,1,IF(K30>=CG$4,2,3)))) -> 4 | AB30: =IF(L30="",0,IF(L30<=CH$3,4,IF(L30>=CH$5,1,IF(L30>=CH$4,2,3)))) -> 4 | AC30: =IF(M30="",0,IF(M30<=CI$3,4,IF(M30>=CI$5,1,IF(M30>=CI$4,2,3)))) -> 4 | ... AK30: =IF(U30="",0,IF(U30<=CQ$3,4,IF(U30>=CQ$5,1,IF(U30>=CQ$4,2,3)))) -> 4 | AL30: 99.5606 | AM30: 0.5688 | AN30: -0.1294 | AO30: 0.7475 | AP30: 0.8 | AQ30: 7.42 | AR30: 0.46
A31: SBI Savings Fund-Reg(G) | B31: 38182 | C31: 35417.753 | D31: 34892.055 | E31: 43.4667 | F31: -1.7269 | G31: -0.3119 | H31: 3.4658 | I31: 7.0194 | J31: 5.6899 | K31: 5.3747 | L31: 5.2028 | M31: 5.9528 | N31: 6.7605 | O31: 6.8378 | P31: 6.4994 | Q31: 5.8713 | R31: 5.91 | S31: 6.2617 | T31: 7.206 | U31: 6.9701 | V31: =IF(F31="",0,IF(F31<=CB$3,4,IF(F31>=CB$5,1,IF(F31>=CB$4,2,3)))) -> 4 | W31: =IF(G31="",0,IF(G31<=CC$3,4,IF(G31>=CC$5,1,IF(G31>=CC$4,2,3)))) -> 4 | X31: =IF(H31="",0,IF(H31<=CD$3,4,IF(H31>=CD$5,1,IF(H31>=CD$4,2,3)))) -> 4 | Y31: =IF(I31="",0,IF(I31<=CE$3,4,IF(I31>=CE$5,1,IF(I31>=CE$4,2,3)))) -> 4 | Z31: =IF(J31="",0,IF(J31<=CF$3,4,IF(J31>=CF$5,1,IF(J31>=CF$4,2,3)))) -> 4 | AA31: =IF(K31="",0,IF(K31<=CG$3,4,IF(K31>=CG$5,1,IF(K31>=CG$4,2,3)))) -> 4 | AB31: =IF(L31="",0,IF(L31<=CH$3,4,IF(L31>=CH$5,1,IF(L31>=CH$4,2,3)))) -> 4 | AC31: =IF(M31="",0,IF(M31<=CI$3,4,IF(M31>=CI$5,1,IF(M31>=CI$4,2,3)))) -> 4 | ... AK31: =IF(U31="",0,IF(U31<=CQ$3,4,IF(U31>=CQ$5,1,IF(U31>=CQ$4,2,3)))) -> 2 | AL31: 98.9602 | AM31: 0.2743 | AN31: 0.7654 | AO31: 0.78 | AP31: 0.84 | AQ31: 7.18 | AR31: 0.64
A32: Sundaram Money Market Fund-Reg(G) | B32: 43369 | C32: 2334.4781 | D32: 1943.3542 | E32: 15.7582 | F32: -1.5878 | G32: -0.182 | H32: 3.6364 | I32: 7.1261 | J32: 6.0308 | K32: 5.6246 | L32: 5.4324 | M32: 6.2281 | N32: 7.0631 | O32: 7.0949 | P32: 6.7859 | Q32: 6.1057 | R32: 6.0021 | U32: 6.1688 | V32: =IF(F32="",0,IF(F32<=CB$3,4,IF(F32>=CB$5,1,IF(F32>=CB$4,2,3)))) -> 4 | W32: =IF(G32="",0,IF(G32<=CC$3,4,IF(G32>=CC$5,1,IF(G32>=CC$4,2,3)))) -> 4 | X32: =IF(H32="",0,IF(H32<=CD$3,4,IF(H32>=CD$5,1,IF(H32>=CD$4,2,3)))) -> 4 | Y32: =IF(I32="",0,IF(I32<=CE$3,4,IF(I32>=CE$5,1,IF(I32>=CE$4,2,3)))) -> 4 | Z32: =IF(J32="",0,IF(J32<=CF$3,4,IF(J32>=CF$5,1,IF(J32>=CF$4,2,3)))) -> 3 | AA32: =IF(K32="",0,IF(K32<=CG$3,4,IF(K32>=CG$5,1,IF(K32>=CG$4,2,3)))) -> 3 | AB32: =IF(L32="",0,IF(L32<=CH$3,4,IF(L32>=CH$5,1,IF(L32>=CH$4,2,3)))) -> 3 | AC32: =IF(M32="",0,IF(M32<=CI$3,4,IF(M32>=CI$5,1,IF(M32>=CI$4,2,3)))) -> 3 | ... AK32: =IF(U32="",0,IF(U32<=CQ$3,4,IF(U32>=CQ$5,1,IF(U32>=CQ$4,2,3)))) -> 4 | AL32: 102.4768 | AM32: 0.2518 | AN32: -2.7286 | AO32: 0.84 | AP32: 0.84 | AQ32: 7.31 | AR32: 0.31
A33: Tata Money Market Fund-Reg(G) | B33: 37763 | C33: 36819.046 | D33: 32382.4 | E33: 4968.1519 | F33: -0.8765 | G33: 0.6665 | H33: 4.3905 | I33: 7.5771 | J33: 6.4632 | K33: 5.8152 | L33: 5.7693 | M33: 6.3312 | N33: 7.1615 | O33: 7.2732 | P33: 6.9506 | Q33: 6.3306 | R33: 6.3633 | S33: 5.8703 | T33: 6.9065 | U33: 6.7414 | V33: =IF(F33="",0,IF(F33<=CB$3,4,IF(F33>=CB$5,1,IF(F33>=CB$4,2,3)))) -> 1 | W33: =IF(G33="",0,IF(G33<=CC$3,4,IF(G33>=CC$5,1,IF(G33>=CC$4,2,3)))) -> 1 | X33: =IF(H33="",0,IF(H33<=CD$3,4,IF(H33>=CD$5,1,IF(H33>=CD$4,2,3)))) -> 1 | Y33: =IF(I33="",0,IF(I33<=CE$3,4,IF(I33>=CE$5,1,IF(I33>=CE$4,2,3)))) -> 1 | Z33: =IF(J33="",0,IF(J33<=CF$3,4,IF(J33>=CF$5,1,IF(J33>=CF$4,2,3)))) -> 1 | AA33: =IF(K33="",0,IF(K33<=CG$3,4,IF(K33>=CG$5,1,IF(K33>=CG$4,2,3)))) -> 1 | AB33: =IF(L33="",0,IF(L33<=CH$3,4,IF(L33>=CH$5,1,IF(L33>=CH$4,2,3)))) -> 1 | AC33: =IF(M33="",0,IF(M33<=CI$3,4,IF(M33>=CI$5,1,IF(M33>=CI$4,2,3)))) -> 1 | ... AK33: =IF(U33="",0,IF(U33<=CQ$3,4,IF(U33>=CQ$5,1,IF(U33>=CQ$4,2,3)))) -> 2 | AL33: 102.0391 | AM33: 0.3096 | AN33: -2.3487 | AO33: 0.7667 | AP33: 0.7667 | AQ33: 7.38 | AR33: 0.41
A34: TRUSTMF Money Market Fund-Reg(G) | B34: 44790 | C34: 132.0374 | D34: 110.4734 | E34: 1279.0961 | F34: 0.0489 | G34: 1.0975 | H34: 4.1166 | I34: 6.7162 | J34: 5.9783 | K34: 5.5399 | L34: 5.455 | M34: 6.0007 | N34: 6.8356 | O34: 6.8818 | U34: 6.8712 | V34: =IF(F34="",0,IF(F34<=CB$3,4,IF(F34>=CB$5,1,IF(F34>=CB$4,2,3)))) -> 1 | W34: =IF(G34="",0,IF(G34<=CC$3,4,IF(G34>=CC$5,1,IF(G34>=CC$4,2,3)))) -> 1 | X34: =IF(H34="",0,IF(H34<=CD$3,4,IF(H34>=CD$5,1,IF(H34>=CD$4,2,3)))) -> 1 | Y34: =IF(I34="",0,IF(I34<=CE$3,4,IF(I34>=CE$5,1,IF(I34>=CE$4,2,3)))) -> 4 | Z34: =IF(J34="",0,IF(J34<=CF$3,4,IF(J34>=CF$5,1,IF(J34>=CF$4,2,3)))) -> 3 | AA34: =IF(K34="",0,IF(K34<=CG$3,4,IF(K34>=CG$5,1,IF(K34>=CG$4,2,3)))) -> 4 | AB34: =IF(L34="",0,IF(L34<=CH$3,4,IF(L34>=CH$5,1,IF(L34>=CH$4,2,3)))) -> 3 | AC34: =IF(M34="",0,IF(M34<=CI$3,4,IF(M34>=CI$5,1,IF(M34>=CI$4,2,3)))) -> 4 | ... AK34: =IF(U34="",0,IF(U34<=CQ$3,4,IF(U34>=CQ$5,1,IF(U34>=CQ$4,2,3)))) -> 2 | AL34: 88.9743 | AM34: 0.4746 | AN34: 10.5511 | AO34: 0.6082 | AP34: 0.6082 | AQ34: 6.86 | AR34: 0.46
A35: Union Money Market Fund-Reg(G) | B35: 44434 | C35: 399.3019 | D35: 682.951 | E35: 1291.1004 | F35: 0.8689 | G35: 1.9289 | H35: 4.8188 | I35: 7.8209 | J35: 6.3234 | K35: 5.6948 | L35: 5.8461 | M35: 5.8154 | N35: 6.4337 | O35: 6.4009 | P35: 6.0922 | U35: 5.6117 | V35: =IF(F35="",0,IF(F35<=CB$3,4,IF(F35>=CB$5,1,IF(F35>=CB$4,2,3)))) -> 1 | W35: =IF(G35="",0,IF(G35<=CC$3,4,IF(G35>=CC$5,1,IF(G35>=CC$4,2,3)))) -> 1 | X35: =IF(H35="",0,IF(H35<=CD$3,4,IF(H35>=CD$5,1,IF(H35>=CD$4,2,3)))) -> 1 | Y35: =IF(I35="",0,IF(I35<=CE$3,4,IF(I35>=CE$5,1,IF(I35>=CE$4,2,3)))) -> 1 | Z35: =IF(J35="",0,IF(J35<=CF$3,4,IF(J35>=CF$5,1,IF(J35>=CF$4,2,3)))) -> 1 | AA35: =IF(K35="",0,IF(K35<=CG$3,4,IF(K35>=CG$5,1,IF(K35>=CG$4,2,3)))) -> 2 | AB35: =IF(L35="",0,IF(L35<=CH$3,4,IF(L35>=CH$5,1,IF(L35>=CH$4,2,3)))) -> 1 | AC35: =IF(M35="",0,IF(M35<=CI$3,4,IF(M35>=CI$5,1,IF(M35>=CI$4,2,3)))) -> 4 | ... AK35: =IF(U35="",0,IF(U35<=CQ$3,4,IF(U35>=CQ$5,1,IF(U35>=CQ$4,2,3)))) -> 4 | AL35: 94.32 | AM35: 0.0795 | AN35: 5.6005 | AO35: 0.3288 | AP35: 0.3507 | AQ35: 7.33 | AR35: 0.91
A36: UTI Money Market Fund-Reg(G) | B36: 40003 | C36: 20319.649 | D36: 18343.775 | E36: 3244.8265 | F36: -1.1105 | G36: 0.5302 | H36: 4.0543 | I36: 7.3478 | J36: 6.2431 | K36: 5.7756 | L36: 5.6009 | M36: 6.3427 | N36: 7.2028 | O36: 7.3075 | P36: 7.0024 | Q36: 6.3693 | R36: 6.3401 | S36: 6.6427 | T36: 7.435 | U36: 7.249 | V36: =IF(F36="",0,IF(F36<=CB$3,4,IF(F36>=CB$5,1,IF(F36>=CB$4,2,3)))) -> 2 | W36: =IF(G36="",0,IF(G36<=CC$3,4,IF(G36>=CC$5,1,IF(G36>=CC$4,2,3)))) -> 2 | X36: =IF(H36="",0,IF(H36<=CD$3,4,IF(H36>=CD$5,1,IF(H36>=CD$4,2,3)))) -> 2 | Y36: =IF(I36="",0,IF(I36<=CE$3,4,IF(I36>=CE$5,1,IF(I36>=CE$4,2,3)))) -> 2 | Z36: =IF(J36="",0,IF(J36<=CF$3,4,IF(J36>=CF$5,1,IF(J36>=CF$4,2,3)))) -> 2 | AA36: =IF(K36="",0,IF(K36<=CG$3,4,IF(K36>=CG$5,1,IF(K36>=CG$4,2,3)))) -> 1 | AB36: =IF(L36="",0,IF(L36<=CH$3,4,IF(L36>=CH$5,1,IF(L36>=CH$4,2,3)))) -> 2 | AC36: =IF(M36="",0,IF(M36<=CI$3,4,IF(M36>=CI$5,1,IF(M36>=CI$4,2,3)))) -> 1 | ... AK36: =IF(U36="",0,IF(U36<=CQ$3,4,IF(U36>=CQ$5,1,IF(U36>=CQ$4,2,3)))) -> 1 | AL36: 96.7891 | AM36: 0.3067 | AN36: 2.8798 | AO36: 0.7288 | AP36: 0.7288 | AQ36: 7.39 | AR36: 0.22
A37: Category Average (Weighted) | F37: =SUMPRODUCT($D12:$D36,F12:F36)/SUMIF(F12:F36,"<>"&"",$D12:$D36) -> -1.3101026 | G37: =SUMPRODUCT($D12:$D36,G12:G36)/SUMIF(G12:G36,"<>"&"",$D12:$D36) -> 0.26193142 | H37: =SUMPRODUCT($D12:$D36,H12:H36)/SUMIF(H12:H36,"<>"&"",$D12:$D36) -> 3.9748853 | I37: =SUMPRODUCT($D12:$D36,I12:I36)/SUMIF(I12:I36,"<>"&"",$D12:$D36) -> 7.3410383 | J37: =SUMPRODUCT($D12:$D36,J12:J36)/SUMIF(J12:J36,"<>"&"",$D12:$D36) -> 6.2039874 | K37: =SUMPRODUCT($D12:$D36,K12:K36)/SUMIF(K12:K36,"<>"&"",$D12:$D36) -> 5.6947229 | L37: =SUMPRODUCT($D12:$D36,L12:L36)/SUMIF(L12:L36,"<>"&"",$D12:$D36) -> 5.5733219 | M37: =SUMPRODUCT($D12:$D36,M12:M36)/SUMIF(M12:M36,"<>"&"",$D12:$D36) -> 6.2367853 | ... U37: =SUMPRODUCT($D12:$D36,U12:U36)/SUMIF(U12:U36,"<>"&"",$D12:$D36) -> 6.8677068
A38: Minimum | F38: =MIN(F12:F36) -> -1.9426 | G38: =MIN(G12:G36) -> -0.3119 | H38: =MIN(H12:H36) -> 2.7972 | I38: =MIN(I12:I36) -> 3.9817 | J38: =MIN(J12:J36) -> 4.7597 | K38: =MIN(K12:K36) -> 5.257 | L38: =MIN(L12:L36) -> 4.3557 | M38: =MIN(M12:M36) -> 5.7593 | ... U38: =MIN(U12:U36) -> 4.7199
A39: Maximum | F39: =MAX(F12:F36) -> 0.8689 | G39: =MAX(G12:G36) -> 1.9289 | H39: =MAX(H12:H36) -> 4.8624 | I39: =MAX(I12:I36) -> 7.8209 | J39: =MAX(J12:J36) -> 6.4843 | K39: =MAX(K12:K36) -> 5.844 | L39: =MAX(L12:L36) -> 5.8461 | M39: =MAX(M12:M36) -> 6.3445 | ... U39: =MAX(U12:U36) -> 7.31
A40: Median | F40: =MEDIAN(F12:F36) -> -1.2769 | G40: =MEDIAN(G12:G36) -> 0.3021 | H40: =MEDIAN(H12:H36) -> 3.9734 | I40: =MEDIAN(I12:I36) -> 7.3478 | J40: =MEDIAN(J12:J36) -> 6.2301 | K40: =MEDIAN(K12:K36) -> 5.69075 | L40: =MEDIAN(L12:L36) -> 5.5532 | M40: =MEDIAN(M12:M36) -> 6.23005 | ... U40: =MEDIAN(U12:U36) -> 6.7414
A41: Indices Performance
A42: CRISIL 1 Yr T-Bill Index* | B42: -- | E42: -- | F42: -- | G42: -- | H42: -- | I42: -- | J42: -- | K42: -- | L42: -- | M42: -- | N42: -- | O42: -- | P42: -- | Q42: -- | R42: -- | T42: -- | U42: --
A44: # : "In the Quartile System, the "performance range" of the entire category for a given time period, is divided into 4 parts. Schemes with returns in the top 25% of that range
A45: in the next 25% of the range have been ranked Quartile 2 and so on. Quartile 4 shows the schemes whose returns are in the bottom 25% of the range."

Sheet Liquid Fund
A1: Main Page | E1: Data Source: ACEMF | CA1: Quartile code | CB1: 7 Days | CC1: 14 Days | CD1: 21 Days | CE1: 1 Month | CF1: 3 Month | CG1: 6 Months | CH1: YTD | CI1: 1 Year | CJ1: 2 Year | CK1: 3 Year | CL1: 4 Years | CM1: 5 Years | CN1: 7 Years | CO1: 10 Years | CP1: 15 Years | CQ1: Inception
CA2: 0 | CB2: =_xlfn.QUARTILE.INC(F$12:F$50,$CA2) -> 3.3588 | CC2: =_xlfn.QUARTILE.INC(G$12:G$50,$CA2) -> 3.784 | CD2: =_xlfn.QUARTILE.INC(H$12:H$50,$CA2) -> 4.7917 | CE2: =_xlfn.QUARTILE.INC(I$12:I$50,$CA2) -> 6.0752 | CF2: =_xlfn.QUARTILE.INC(J$12:J$50,$CA2) -> 5.7646 | CG2: =_xlfn.QUARTILE.INC(K$12:K$50,$CA2) -> 5.6535 | CH2: =_xlfn.QUARTILE.INC(L$12:L$50,$CA2) -> 5.6642 | CI2: =_xlfn.QUARTILE.INC(M$12:M$50,$CA2) -> 5.7466 | ... CQ2: =_xlfn.QUARTILE.INC(U$12:U$50,$CA2) -> 4.6964
CA3: 1 | CB3: =_xlfn.QUARTILE.INC(F$12:F$50,$CA3) -> 3.873725 | CC3: =_xlfn.QUARTILE.INC(G$12:G$50,$CA3) -> 4.21035 | CD3: =_xlfn.QUARTILE.INC(H$12:H$50,$CA3) -> 5.319975 | CE3: =_xlfn.QUARTILE.INC(I$12:I$50,$CA3) -> 7.746 | CF3: =_xlfn.QUARTILE.INC(J$12:J$50,$CA3) -> 6.683775 | CG3: =_xlfn.QUARTILE.INC(K$12:K$50,$CA3) -> 6.1326 | CH3: =_xlfn.QUARTILE.INC(L$12:L$50,$CA3) -> 6.2866 | CI3: =_xlfn.QUARTILE.INC(M$12:M$50,$CA3) -> 6.0832 | ... CQ3: =_xlfn.QUARTILE.INC(U$12:U$50,$CA3) -> 6.200625
CA4: 2 | CB4: =_xlfn.QUARTILE.INC(F$12:F$50,$CA4) -> 4.0363 | CC4: =_xlfn.QUARTILE.INC(G$12:G$50,$CA4) -> 4.3201 | CD4: =_xlfn.QUARTILE.INC(H$12:H$50,$CA4) -> 5.40895 | CE4: =_xlfn.QUARTILE.INC(I$12:I$50,$CA4) -> 7.8754 | CF4: =_xlfn.QUARTILE.INC(J$12:J$50,$CA4) -> 6.7849 | CG4: =_xlfn.QUARTILE.INC(K$12:K$50,$CA4) -> 6.2412 | CH4: =_xlfn.QUARTILE.INC(L$12:L$50,$CA4) -> 6.3949 | CI4: =_xlfn.QUARTILE.INC(M$12:M$50,$CA4) -> 6.1741 | ... CQ4: =_xlfn.QUARTILE.INC(U$12:U$50,$CA4) -> 6.8062
CA5: 3 | CB5: =_xlfn.QUARTILE.INC(F$12:F$50,$CA5) -> 4.158875 | CC5: =_xlfn.QUARTILE.INC(G$12:G$50,$CA5) -> 4.392825 | CD5: =_xlfn.QUARTILE.INC(H$12:H$50,$CA5) -> 5.491575 | CE5: =_xlfn.QUARTILE.INC(I$12:I$50,$CA5) -> 8.01695 | CF5: =_xlfn.QUARTILE.INC(J$12:J$50,$CA5) -> 6.85505 | CG5: =_xlfn.QUARTILE.INC(K$12:K$50,$CA5) -> 6.2868 | CH5: =_xlfn.QUARTILE.INC(L$12:L$50,$CA5) -> 6.4575 | CI5: =_xlfn.QUARTILE.INC(M$12:M$50,$CA5) -> 6.2134 | ... CQ5: =_xlfn.QUARTILE.INC(U$12:U$50,$CA5) -> 6.941975
CB6: =_xlfn.QUARTILE.INC(F$12:F$50,$CA6) -> 3.3588 | CC6: =_xlfn.QUARTILE.INC(G$12:G$50,$CA6) -> 3.784 | CD6: =_xlfn.QUARTILE.INC(H$12:H$50,$CA6) -> 4.7917 | CE6: =_xlfn.QUARTILE.INC(I$12:I$50,$CA6) -> 6.0752 | CF6: =_xlfn.QUARTILE.INC(J$12:J$50,$CA6) -> 5.7646 | CG6: =_xlfn.QUARTILE.INC(K$12:K$50,$CA6) -> 5.6535 | CH6: =_xlfn.QUARTILE.INC(L$12:L$50,$CA6) -> 5.6642 | CI6: =_xlfn.QUARTILE.INC(M$12:M$50,$CA6) -> 5.7466 | ... CQ6: =_xlfn.QUARTILE.INC(U$12:U$50,$CA6) -> 4.6964
A7: Fund Barometer - Liquid Fund | CA7: 4 | CB7: =_xlfn.QUARTILE.INC(F$12:F$50,$CA7) -> 5.0205 | CC7: =_xlfn.QUARTILE.INC(G$12:G$50,$CA7) -> 5.0365 | CD7: =_xlfn.QUARTILE.INC(H$12:H$50,$CA7) -> 5.6588 | CE7: =_xlfn.QUARTILE.INC(I$12:I$50,$CA7) -> 8.2378 | CF7: =_xlfn.QUARTILE.INC(J$12:J$50,$CA7) -> 6.9432 | CG7: =_xlfn.QUARTILE.INC(K$12:K$50,$CA7) -> 6.3489 | CH7: =_xlfn.QUARTILE.INC(L$12:L$50,$CA7) -> 6.5242 | CI7: =_xlfn.QUARTILE.INC(M$12:M$50,$CA7) -> 6.2623 | ... CQ7: =_xlfn.QUARTILE.INC(U$12:U$50,$CA7) -> 7.3682
A8: ='Ultra Short Duration Fund'!A8 -> (As on 30 Apr 2026) | B8: Value Information | F8: Simple Annualized (%) | M8: Compound Annualized (%) | U8: Since Inception | V8: Quartile | AL8: Credit Quality | AO8: Modified Duration (Years) | AP8: Average Maturity (Years) | AQ8: YTM | AR8: Expense Ratio(%)
A9: Scheme Name | B9: Launch Date | C9: Fund Size (Rs Crs) Feb26 | D9: Fund Size (Rs Crs) Mar26 | E9: Latest NAV | F9: 7 Days | G9: 14 Days | H9: 21 Days | I9: 1 Month | J9: 3 Months | K9: 6 Months | L9: YTD | M9: 1 Year | N9: 2 Years | O9: 3 Years | P9: 4 Years | Q9: 5 Years | R9: 7 Years | S9: 10 Years | T9: 15 Years | V9: 7 Days | W9: 14 Days | X9: 21 Days | Y9: 1 Month | Z9: 3 Months | AA9: 6 Months | AB9: YTD | AC9: 1 Year | AD9: 2 Years | AE9: 3 Years | AF9: 4 Years | AG9: 5 Years | AH9: 7 Years | AI9: 10 Years | AJ9: 15 Years | AK9: Since Inception | AL9: AA minus and Above | AM9: Below AA minus | AN9: Cash & Cash Equivalent
A10: To view Exit Loads of any Scheme in this group please click here
A11: Liquid Fund
A12: 360 ONE Liquid Fund-Reg(G) | B12: 41591 | C12: 1282.794 | D12: 1177.2259 | E12: 2109.8793 | F12: 3.6023 | G12: 4.0357 | H12: 5.2595 | I12: 7.7232 | J12: 6.7085 | K12: 6.1213 | L12: 6.2855 | M12: 6.0263 | N12: 6.5676 | O12: 6.7421 | P12: 6.512 | Q12: 5.8465 | R12: 5.3231 | S12: 5.7074 | U12: 6.1691 | V12: =IF(F12="",0,IF(F12<=CB$3,4,IF(F12>=CB$5,1,IF(F12>=CB$4,2,3)))) -> 4 | W12: =IF(G12="",0,IF(G12<=CC$3,4,IF(G12>=CC$5,1,IF(G12>=CC$4,2,3)))) -> 4 | X12: =IF(H12="",0,IF(H12<=CD$3,4,IF(H12>=CD$5,1,IF(H12>=CD$4,2,3)))) -> 4 | Y12: =IF(I12="",0,IF(I12<=CE$3,4,IF(I12>=CE$5,1,IF(I12>=CE$4,2,3)))) -> 4 | Z12: =IF(J12="",0,IF(J12<=CF$3,4,IF(J12>=CF$5,1,IF(J12>=CF$4,2,3)))) -> 3 | AA12: =IF(K12="",0,IF(K12<=CG$3,4,IF(K12>=CG$5,1,IF(K12>=CG$4,2,3)))) -> 4 | AB12: =IF(L12="",0,IF(L12<=CH$3,4,IF(L12>=CH$5,1,IF(L12>=CH$4,2,3)))) -> 4 | AC12: =IF(M12="",0,IF(M12<=CI$3,4,IF(M12>=CI$5,1,IF(M12>=CI$4,2,3)))) -> 4 | ... AK12: =IF(U12="",0,IF(U12<=CQ$3,4,IF(U12>=CQ$5,1,IF(U12>=CQ$4,2,3)))) -> 4 | AL12: 99.5839 | AM12: 0.2572 | AN12: 0.1588 | AO12: 0.1458 | AP12: 0.1565 | AQ12: 7.18 | AR12: 0.32
A13: Aditya Birla SL Liquid Fund(G) | B13: 38076 | C13: 51838.157 | D13: 43022.178 | E13: 442.2387 | F13: 4.1418 | G13: 4.3841 | H13: 5.4644 | I13: 8.0831 | J13: 6.865 | K13: 6.3086 | L13: 6.485 | M13: 6.2187 | N13: 6.7538 | O13: 6.9112 | P13: 6.6776 | Q13: 6.0167 | R13: 5.6591 | S13: 6.1017 | T13: 7.0952 | U13: 6.9583 | V13: =IF(F13="",0,IF(F13<=CB$3,4,IF(F13>=CB$5,1,IF(F13>=CB$4,2,3)))) -> 2 | W13: =IF(G13="",0,IF(G13<=CC$3,4,IF(G13>=CC$5,1,IF(G13>=CC$4,2,3)))) -> 2 | X13: =IF(H13="",0,IF(H13<=CD$3,4,IF(H13>=CD$5,1,IF(H13>=CD$4,2,3)))) -> 2 | Y13: =IF(I13="",0,IF(I13<=CE$3,4,IF(I13>=CE$5,1,IF(I13>=CE$4,2,3)))) -> 1 | Z13: =IF(J13="",0,IF(J13<=CF$3,4,IF(J13>=CF$5,1,IF(J13>=CF$4,2,3)))) -> 1 | AA13: =IF(K13="",0,IF(K13<=CG$3,4,IF(K13>=CG$5,1,IF(K13>=CG$4,2,3)))) -> 1 | AB13: =IF(L13="",0,IF(L13<=CH$3,4,IF(L13>=CH$5,1,IF(L13>=CH$4,2,3)))) -> 1 | AC13: =IF(M13="",0,IF(M13<=CI$3,4,IF(M13>=CI$5,1,IF(M13>=CI$4,2,3)))) -> 1 | ... AK13: =IF(U13="",0,IF(U13<=CQ$3,4,IF(U13>=CQ$5,1,IF(U13>=CQ$4,2,3)))) -> 1 | AL13: 113.6365 | AM13: 0.3268 | AN13: -13.9632 | AO13: 0.18 | AP13: 0.18 | AQ13: 7.73 | AR13: 0.35
A14: Axis Liquid Fund-Reg(G) | B14: 40095 | C14: 43636.301 | D14: 30187.516 | E14: 3056.6964 | F14: 4.2032 | G14: 4.4376 | H14: 5.547 | I14: 8.1045 | J14: 6.9165 | K14: 6.3489 | L14: 6.5242 | M14: 6.255 | N14: 6.7842 | O14: 6.9488 | P14: 6.7117 | Q14: 6.0482 | R14: 5.6703 | S14: 6.1194 | T14: 7.0845 | U14: 6.9769 | V14: =IF(F14="",0,IF(F14<=CB$3,4,IF(F14>=CB$5,1,IF(F14>=CB$4,2,3)))) -> 1 | W14: =IF(G14="",0,IF(G14<=CC$3,4,IF(G14>=CC$5,1,IF(G14>=CC$4,2,3)))) -> 1 | X14: =IF(H14="",0,IF(H14<=CD$3,4,IF(H14>=CD$5,1,IF(H14>=CD$4,2,3)))) -> 1 | Y14: =IF(I14="",0,IF(I14<=CE$3,4,IF(I14>=CE$5,1,IF(I14>=CE$4,2,3)))) -> 1 | Z14: =IF(J14="",0,IF(J14<=CF$3,4,IF(J14>=CF$5,1,IF(J14>=CF$4,2,3)))) -> 1 | AA14: =IF(K14="",0,IF(K14<=CG$3,4,IF(K14>=CG$5,1,IF(K14>=CG$4,2,3)))) -> 1 | AB14: =IF(L14="",0,IF(L14<=CH$3,4,IF(L14>=CH$5,1,IF(L14>=CH$4,2,3)))) -> 1 | AC14: =IF(M14="",0,IF(M14<=CI$3,4,IF(M14>=CI$5,1,IF(M14>=CI$4,2,3)))) -> 1 | ... AK14: =IF(U14="",0,IF(U14<=CQ$3,4,IF(U14>=CQ$5,1,IF(U14>=CQ$4,2,3)))) -> 1 | AL14: 119.6601 | AM14: 0.3343 | AN14: -19.9944 | AO14: 0.1699 | AP14: 0.1808 | AQ14: 7.77 | AR14: 0.21
A15: Bajaj Finserv Liquid Fund-Reg(G) | B15: 45112 | C15: 5690.1977 | D15: 3178.503 | E15: 1204.2667 | F15: 3.8681 | G15: 4.2523 | H15: 5.3357 | I15: 7.6065 | J15: 6.6584 | K15: 6.1312 | L15: 6.2697 | M15: 6.0787 | N15: 6.6429 | U15: 6.802 | V15: =IF(F15="",0,IF(F15<=CB$3,4,IF(F15>=CB$5,1,IF(F15>=CB$4,2,3)))) -> 4 | W15: =IF(G15="",0,IF(G15<=CC$3,4,IF(G15>=CC$5,1,IF(G15>=CC$4,2,3)))) -> 3 | X15: =IF(H15="",0,IF(H15<=CD$3,4,IF(H15>=CD$5,1,IF(H15>=CD$4,2,3)))) -> 3 | Y15: =IF(I15="",0,IF(I15<=CE$3,4,IF(I15>=CE$5,1,IF(I15>=CE$4,2,3)))) -> 4 | Z15: =IF(J15="",0,IF(J15<=CF$3,4,IF(J15>=CF$5,1,IF(J15>=CF$4,2,3)))) -> 4 | AA15: =IF(K15="",0,IF(K15<=CG$3,4,IF(K15>=CG$5,1,IF(K15>=CG$4,2,3)))) -> 4 | AB15: =IF(L15="",0,IF(L15<=CH$3,4,IF(L15>=CH$5,1,IF(L15>=CH$4,2,3)))) -> 4 | AC15: =IF(M15="",0,IF(M15<=CI$3,4,IF(M15>=CI$5,1,IF(M15>=CI$4,2,3)))) -> 4 | ... AK15: =IF(U15="",0,IF(U15<=CQ$3,4,IF(U15>=CQ$5,1,IF(U15>=CQ$4,2,3)))) -> 3 | AL15: 110.739 | AM15: 0.4682 | AN15: -11.2072 | AO15: 0.1534 | AP15: 0.1644 | AQ15: 7.58 | AR15: 0.28
A16: Bandhan Liquid Fund-Reg(G) | B16: 38079 | C16: 17384.115 | D16: 12083.145 | E16: 3312.8745 | F16: 4.1748 | G16: 4.3902 | H16: 5.4961 | I16: 7.9583 | J16: 6.8017 | K16: 6.221 | L16: 6.367 | M16: 6.1297 | N16: 6.6691 | O16: 6.8445 | P16: 6.6101 | Q16: 5.9602 | R16: 5.5427 | S16: 5.992 | T16: 6.9932 | U16: 5.5714 | V16: =IF(F16="",0,IF(F16<=CB$3,4,IF(F16>=CB$5,1,IF(F16>=CB$4,2,3)))) -> 1 | W16: =IF(G16="",0,IF(G16<=CC$3,4,IF(G16>=CC$5,1,IF(G16>=CC$4,2,3)))) -> 2 | X16: =IF(H16="",0,IF(H16<=CD$3,4,IF(H16>=CD$5,1,IF(H16>=CD$4,2,3)))) -> 1 | Y16: =IF(I16="",0,IF(I16<=CE$3,4,IF(I16>=CE$5,1,IF(I16>=CE$4,2,3)))) -> 2 | Z16: =IF(J16="",0,IF(J16<=CF$3,4,IF(J16>=CF$5,1,IF(J16>=CF$4,2,3)))) -> 2 | AA16: =IF(K16="",0,IF(K16<=CG$3,4,IF(K16>=CG$5,1,IF(K16>=CG$4,2,3)))) -> 3 | AB16: =IF(L16="",0,IF(L16<=CH$3,4,IF(L16>=CH$5,1,IF(L16>=CH$4,2,3)))) -> 3 | AC16: =IF(M16="",0,IF(M16<=CI$3,4,IF(M16>=CI$5,1,IF(M16>=CI$4,2,3)))) -> 3 | ... AK16: =IF(U16="",0,IF(U16<=CQ$3,4,IF(U16>=CQ$5,1,IF(U16>=CQ$4,2,3)))) -> 4 | AL16: 122.0317 | AM16: 0.3447 | AN16: -22.3764 | AO16: 0.1808 | AP16: 0.1836 | AQ16: 7.32 | AR16: 0.23
A17: Bank of India Liquid Fund-Reg(G) | B17: 39645 | C17: 1914.9123 | D17: 1611.3715 | E17: 3161.3525 | F17: 4.0572 | G17: 4.3323 | H17: 5.478 | I17: 7.6779 | J17: 6.812 | K17: 6.3263 | L17: 6.4563 | M17: 6.2623 | N17: 6.8071 | O17: 6.9755 | P17: 6.731 | Q17: 6.0631 | R17: 5.6327 | S17: 6.0826 | T17: 6.9115 | U17: 6.6799 | V17: =IF(F17="",0,IF(F17<=CB$3,4,IF(F17>=CB$5,1,IF(F17>=CB$4,2,3)))) -> 2 | W17: =IF(G17="",0,IF(G17<=CC$3,4,IF(G17>=CC$5,1,IF(G17>=CC$4,2,3)))) -> 2 | X17: =IF(H17="",0,IF(H17<=CD$3,4,IF(H17>=CD$5,1,IF(H17>=CD$4,2,3)))) -> 2 | Y17: =IF(I17="",0,IF(I17<=CE$3,4,IF(I17>=CE$5,1,IF(I17>=CE$4,2,3)))) -> 4 | Z17: =IF(J17="",0,IF(J17<=CF$3,4,IF(J17>=CF$5,1,IF(J17>=CF$4,2,3)))) -> 2 | AA17: =IF(K17="",0,IF(K17<=CG$3,4,IF(K17>=CG$5,1,IF(K17>=CG$4,2,3)))) -> 1 | AB17: =IF(L17="",0,IF(L17<=CH$3,4,IF(L17>=CH$5,1,IF(L17>=CH$4,2,3)))) -> 2 | AC17: =IF(M17="",0,IF(M17<=CI$3,4,IF(M17>=CI$5,1,IF(M17>=CI$4,2,3)))) -> 1 | ... AK17: =IF(U17="",0,IF(U17<=CQ$3,4,IF(U17>=CQ$5,1,IF(U17>=CQ$4,2,3)))) -> 3 | AL17: 98.6469 | AM17: 0.3423 | AN17: 1.0107 | AO17: 0.13 | AP17: 0.14 | AQ17: 7.3 | AR17: 0.08
A18: Baroda BNP Paribas Liquid Fund(G) | B18: 39849 | C18: 12362.261 | D18: 8599.3814 | E18: 3153.6598 | F18: 4.1615 | G18: 4.3936 | H18: 5.5545 | I18: 7.8311 | J18: 6.7335 | K18: 6.2385 | L18: 6.3954 | M18: 6.1403 | N18: 6.6763 | O18: 6.8486 | P18: 6.6368 | Q18: 5.9936 | R18: 5.6119 | S18: 6.0801 | T18: 7.0718 | U18: 6.8887 | V18: =IF(F18="",0,IF(F18<=CB$3,4,IF(F18>=CB$5,1,IF(F18>=CB$4,2,3)))) -> 1 | W18: =IF(G18="",0,IF(G18<=CC$3,4,IF(G18>=CC$5,1,IF(G18>=CC$4,2,3)))) -> 1 | X18: =IF(H18="",0,IF(H18<=CD$3,4,IF(H18>=CD$5,1,IF(H18>=CD$4,2,3)))) -> 1 | Y18: =IF(I18="",0,IF(I18<=CE$3,4,IF(I18>=CE$5,1,IF(I18>=CE$4,2,3)))) -> 3 | Z18: =IF(J18="",0,IF(J18<=CF$3,4,IF(J18>=CF$5,1,IF(J18>=CF$4,2,3)))) -> 3 | AA18: =IF(K18="",0,IF(K18<=CG$3,4,IF(K18>=CG$5,1,IF(K18>=CG$4,2,3)))) -> 3 | AB18: =IF(L18="",0,IF(L18<=CH$3,4,IF(L18>=CH$5,1,IF(L18>=CH$4,2,3)))) -> 2 | AC18: =IF(M18="",0,IF(M18<=CI$3,4,IF(M18>=CI$5,1,IF(M18>=CI$4,2,3)))) -> 3 | ... AK18: =IF(U18="",0,IF(U18<=CQ$3,4,IF(U18>=CQ$5,1,IF(U18>=CQ$4,2,3)))) -> 2 | AL18: 106.1763 | AM18: 0.3063 | AN18: -6.4826 | AO18: 0.1562 | AP18: 0.1562 | AQ18: 7.6 | AR18: 0.26
A19: Canara Rob Liquid Fund-Reg(G) | B19: 39644 | C19: 7456.9017 | D19: 4858.3375 | E19: 3303.3632 | F19: 3.9857 | G19: 4.2777 | H19: 5.541 | I19: 8.1285 | J19: 6.9432 | K19: 6.2971 | L19: 6.4672 | M19: 6.2153 | N19: 6.7629 | O19: 6.9268 | P19: 6.6986 | Q19: 6.0215 | R19: 5.5305 | S19: 5.975 | T19: 6.9759 | U19: 6.9164 | V19: =IF(F19="",0,IF(F19<=CB$3,4,IF(F19>=CB$5,1,IF(F19>=CB$4,2,3)))) -> 3 | W19: =IF(G19="",0,IF(G19<=CC$3,4,IF(G19>=CC$5,1,IF(G19>=CC$4,2,3)))) -> 3 | X19: =IF(H19="",0,IF(H19<=CD$3,4,IF(H19>=CD$5,1,IF(H19>=CD$4,2,3)))) -> 1 | Y19: =IF(I19="",0,IF(I19<=CE$3,4,IF(I19>=CE$5,1,IF(I19>=CE$4,2,3)))) -> 1 | Z19: =IF(J19="",0,IF(J19<=CF$3,4,IF(J19>=CF$5,1,IF(J19>=CF$4,2,3)))) -> 1 | AA19: =IF(K19="",0,IF(K19<=CG$3,4,IF(K19>=CG$5,1,IF(K19>=CG$4,2,3)))) -> 1 | AB19: =IF(L19="",0,IF(L19<=CH$3,4,IF(L19>=CH$5,1,IF(L19>=CH$4,2,3)))) -> 1 | AC19: =IF(M19="",0,IF(M19<=CI$3,4,IF(M19>=CI$5,1,IF(M19>=CI$4,2,3)))) -> 1 | ... AK19: =IF(U19="",0,IF(U19<=CQ$3,4,IF(U19>=CQ$5,1,IF(U19>=CQ$4,2,3)))) -> 2 | AL19: 99.1811 | AM19: 0.2826 | AN19: 0.5363 | AO19: 0.17 | AP19: 0.18 | AQ19: 7.46 | AR19: 0.15
A20: Capitalmind Liquid Fund-Reg(G) | B20: 45989 | C20: 116.5343 | D20: 121.7248 | E20: 1027.8717 | F20: 4.2688 | G20: 4.511 | H20: 5.5871 | I20: 8.0114 | J20: 6.7682 | L20: 6.3785 | U20: 6.778 | V20: =IF(F20="",0,IF(F20<=CB$3,4,IF(F20>=CB$5,1,IF(F20>=CB$4,2,3)))) -> 1 | W20: =IF(G20="",0,IF(G20<=CC$3,4,IF(G20>=CC$5,1,IF(G20>=CC$4,2,3)))) -> 1 | X20: =IF(H20="",0,IF(H20<=CD$3,4,IF(H20>=CD$5,1,IF(H20>=CD$4,2,3)))) -> 1 | Y20: =IF(I20="",0,IF(I20<=CE$3,4,IF(I20>=CE$5,1,IF(I20>=CE$4,2,3)))) -> 2 | Z20: =IF(J20="",0,IF(J20<=CF$3,4,IF(J20>=CF$5,1,IF(J20>=CF$4,2,3)))) -> 3 | AA20: =IF(K20="",0,IF(K20<=CG$3,4,IF(K20>=CG$5,1,IF(K20>=CG$4,2,3)))) -> 0 | AB20: =IF(L20="",0,IF(L20<=CH$3,4,IF(L20>=CH$5,1,IF(L20>=CH$4,2,3)))) -> 3 | AC20: =IF(M20="",0,IF(M20<=CI$3,4,IF(M20>=CI$5,1,IF(M20>=CI$4,2,3)))) -> 0 | ... AK20: =IF(U20="",0,IF(U20<=CQ$3,4,IF(U20>=CQ$5,1,IF(U20>=CQ$4,2,3)))) -> 3 | AL20: 96.8518 | AM20: 0.1028 | AN20: 3.0454 | AO20: 0.1562 | AP20: 0.1589 | AQ20: 7.31 | AR20: 0.26
A21: DSP Liquidity Fund-Reg(G) | B21: 38678 | C21: 21057.947 | D21: 16866.074 | E21: 3918.7537 | F21: 4.005 | G21: 4.3468 | H21: 5.5477 | I21: 7.8987 | J21: 6.9023 | K21: 6.3377 | L21: 6.5003 | M21: 6.2412 | N21: 6.7718 | O21: 6.9187 | P21: 6.6652 | Q21: 6.0043 | R21: 5.6082 | S21: 6.0543 | T21: 7.0303 | U21: 6.9069 | V21: =IF(F21="",0,IF(F21<=CB$3,4,IF(F21>=CB$5,1,IF(F21>=CB$4,2,3)))) -> 3 | W21: =IF(G21="",0,IF(G21<=CC$3,4,IF(G21>=CC$5,1,IF(G21>=CC$4,2,3)))) -> 2 | X21: =IF(H21="",0,IF(H21<=CD$3,4,IF(H21>=CD$5,1,IF(H21>=CD$4,2,3)))) -> 1 | Y21: =IF(I21="",0,IF(I21<=CE$3,4,IF(I21>=CE$5,1,IF(I21>=CE$4,2,3)))) -> 2 | Z21: =IF(J21="",0,IF(J21<=CF$3,4,IF(J21>=CF$5,1,IF(J21>=CF$4,2,3)))) -> 1 | AA21: =IF(K21="",0,IF(K21<=CG$3,4,IF(K21>=CG$5,1,IF(K21>=CG$4,2,3)))) -> 1 | AB21: =IF(L21="",0,IF(L21<=CH$3,4,IF(L21>=CH$5,1,IF(L21>=CH$4,2,3)))) -> 1 | AC21: =IF(M21="",0,IF(M21<=CI$3,4,IF(M21>=CI$5,1,IF(M21>=CI$4,2,3)))) -> 1 | ... AK21: =IF(U21="",0,IF(U21<=CQ$3,4,IF(U21>=CQ$5,1,IF(U21>=CQ$4,2,3)))) -> 2 | AL21: 120.7612 | AM21: 0.2906 | AN21: -21.0518 | AO21: 0.16 | AP21: 0.17 | AQ21: 7.48 | AR21: 0.22
A22: Edelweiss Liquid Fund-Reg(G) | B22: 39707 | C22: 10631.352 | D22: 8877.2502 | E22: 3510.3605 | F22: 4.209 | G22: 4.5043 | H22: 5.5739 | I22: 8.1265 | J22: 6.8998 | K22: 6.3168 | L22: 6.4747 | M22: 6.2591 | N22: 6.7653 | O22: 6.8892 | P22: 6.609 | Q22: 5.9384 | R22: 5.5691 | S22: 5.9753 | T22: 6.9585 | U22: 6.8947 | V22: =IF(F22="",0,IF(F22<=CB$3,4,IF(F22>=CB$5,1,IF(F22>=CB$4,2,3)))) -> 1 | W22: =IF(G22="",0,IF(G22<=CC$3,4,IF(G22>=CC$5,1,IF(G22>=CC$4,2,3)))) -> 1 | X22: =IF(H22="",0,IF(H22<=CD$3,4,IF(H22>=CD$5,1,IF(H22>=CD$4,2,3)))) -> 1 | Y22: =IF(I22="",0,IF(I22<=CE$3,4,IF(I22>=CE$5,1,IF(I22>=CE$4,2,3)))) -> 1 | Z22: =IF(J22="",0,IF(J22<=CF$3,4,IF(J22>=CF$5,1,IF(J22>=CF$4,2,3)))) -> 1 | AA22: =IF(K22="",0,IF(K22<=CG$3,4,IF(K22>=CG$5,1,IF(K22>=CG$4,2,3)))) -> 1 | AB22: =IF(L22="",0,IF(L22<=CH$3,4,IF(L22>=CH$5,1,IF(L22>=CH$4,2,3)))) -> 1 | AC22: =IF(M22="",0,IF(M22<=CI$3,4,IF(M22>=CI$5,1,IF(M22>=CI$4,2,3)))) -> 1 | ... AK22: =IF(U22="",0,IF(U22<=CQ$3,4,IF(U22>=CQ$5,1,IF(U22>=CQ$4,2,3)))) -> 2 | AL22: 111.5619 | AM22: 0.3167 | AN22: -11.8785 | AO22: 0.1877 | AP22: 0.1877 | AQ22: 7.42 | AR22: 0.13
A23: Groww Liquid Fund-Reg(G) | B23: 40841 | C23: 163.9387 | D23: 161.5556 | E23: 2653.5774 | F23: 4.1296 | G23: 4.3059 | H23: 5.3826 | I23: 7.7502 | J23: 6.8127 | K23: 6.2491 | L23: 6.3896 | M23: 6.1963 | N23: 6.7565 | O23: 6.8876 | P23: 6.5746 | Q23: 5.872 | R23: 5.4909 | S23: 5.9907 | U23: 6.9505 | V23: =IF(F23="",0,IF(F23<=CB$3,4,IF(F23>=CB$5,1,IF(F23>=CB$4,2,3)))) -> 2 | W23: =IF(G23="",0,IF(G23<=CC$3,4,IF(G23>=CC$5,1,IF(G23>=CC$4,2,3)))) -> 3 | X23: =IF(H23="",0,IF(H23<=CD$3,4,IF(H23>=CD$5,1,IF(H23>=CD$4,2,3)))) -> 3 | Y23: =IF(I23="",0,IF(I23<=CE$3,4,IF(I23>=CE$5,1,IF(I23>=CE$4,2,3)))) -> 3 | Z23: =IF(J23="",0,IF(J23<=CF$3,4,IF(J23>=CF$5,1,IF(J23>=CF$4,2,3)))) -> 2 | AA23: =IF(K23="",0,IF(K23<=CG$3,4,IF(K23>=CG$5,1,IF(K23>=CG$4,2,3)))) -> 2 | AB23: =IF(L23="",0,IF(L23<=CH$3,4,IF(L23>=CH$5,1,IF(L23>=CH$4,2,3)))) -> 3 | AC23: =IF(M23="",0,IF(M23<=CI$3,4,IF(M23>=CI$5,1,IF(M23>=CI$4,2,3)))) -> 2 | ... AK23: =IF(U23="",0,IF(U23<=CQ$3,4,IF(U23>=CQ$5,1,IF(U23>=CQ$4,2,3)))) -> 1 | AL23: 87.8963 | AM23: 0.4356 | AN23: 11.6681 | AQ23: 7.48 | AR23: 0.2
A24: HDFC Liquid Fund(G) | B24: 36816 | C24: 67849.857 | D24: 53982.316 | E24: 5383.9205 | F24: 3.8369 | G24: 4.1854 | H24: 5.3027 | I24: 8.0388 | J24: 6.8498 | K24: 6.2986 | L24: 6.461 | M24: 6.1938 | N24: 6.7241 | O24: 6.882 | P24: 6.632 | Q24: 5.9732 | R24: 5.5765 | S24: 6.0028 | T24: 6.9961 | U24: 6.8104 | V24: =IF(F24="",0,IF(F24<=CB$3,4,IF(F24>=CB$5,1,IF(F24>=CB$4,2,3)))) -> 4 | W24: =IF(G24="",0,IF(G24<=CC$3,4,IF(G24>=CC$5,1,IF(G24>=CC$4,2,3)))) -> 4 | X24: =IF(H24="",0,IF(H24<=CD$3,4,IF(H24>=CD$5,1,IF(H24>=CD$4,2,3)))) -> 4 | Y24: =IF(I24="",0,IF(I24<=CE$3,4,IF(I24>=CE$5,1,IF(I24>=CE$4,2,3)))) -> 1 | Z24: =IF(J24="",0,IF(J24<=CF$3,4,IF(J24>=CF$5,1,IF(J24>=CF$4,2,3)))) -> 2 | AA24: =IF(K24="",0,IF(K24<=CG$3,4,IF(K24>=CG$5,1,IF(K24>=CG$4,2,3)))) -> 1 | AB24: =IF(L24="",0,IF(L24<=CH$3,4,IF(L24>=CH$5,1,IF(L24>=CH$4,2,3)))) -> 1 | AC24: =IF(M24="",0,IF(M24<=CI$3,4,IF(M24>=CI$5,1,IF(M24>=CI$4,2,3)))) -> 2 | ... AK24: =IF(U24="",0,IF(U24<=CQ$3,4,IF(U24>=CQ$5,1,IF(U24>=CQ$4,2,3)))) -> 2 | AL24: 115.9527 | AM24: 0.3589 | AN24: -16.3116 | AO24: 0.1698 | AP24: 0.1856 | AQ24: 7.38 | AR24: 0.31
A25: HSBC Liquid Fund(G) | B25: 38139 | C25: 17734.661 | D25: 13434.183 | E25: 2735.3981 | F25: 3.8578 | G25: 4.1639 | H25: 5.3154 | I25: 7.882 | J25: 6.7811 | K25: 6.2367 | L25: 6.4156 | M25: 6.1902 | N25: 6.73 | O25: 6.897 | P25: 6.6616 | Q25: 6.001 | R25: 5.6023 | S25: 6.0613 | T25: 4.0328 | U25: 4.6964 | V25: =IF(F25="",0,IF(F25<=CB$3,4,IF(F25>=CB$5,1,IF(F25>=CB$4,2,3)))) -> 4 | W25: =IF(G25="",0,IF(G25<=CC$3,4,IF(G25>=CC$5,1,IF(G25>=CC$4,2,3)))) -> 4 | X25: =IF(H25="",0,IF(H25<=CD$3,4,IF(H25>=CD$5,1,IF(H25>=CD$4,2,3)))) -> 4 | Y25: =IF(I25="",0,IF(I25<=CE$3,4,IF(I25>=CE$5,1,IF(I25>=CE$4,2,3)))) -> 2 | Z25: =IF(J25="",0,IF(J25<=CF$3,4,IF(J25>=CF$5,1,IF(J25>=CF$4,2,3)))) -> 3 | AA25: =IF(K25="",0,IF(K25<=CG$3,4,IF(K25>=CG$5,1,IF(K25>=CG$4,2,3)))) -> 3 | AB25: =IF(L25="",0,IF(L25<=CH$3,4,IF(L25>=CH$5,1,IF(L25>=CH$4,2,3)))) -> 2 | AC25: =IF(M25="",0,IF(M25<=CI$3,4,IF(M25>=CI$5,1,IF(M25>=CI$4,2,3)))) -> 2 | ... AK25: =IF(U25="",0,IF(U25<=CQ$3,4,IF(U25>=CQ$5,1,IF(U25>=CQ$4,2,3)))) -> 4 | AL25: 118.4183 | AM25: 0.3922 | AN25: -18.8104 | AO25: 0.1828 | AP25: 0.185 | AQ25: 7.57 | AR25: 0.2
A26: ICICI Pru Liquid Fund(G) | B26: 38673 | C26: 53738.395 | D26: 42887.992 | E26: 406.0737 | F26: 4.1123 | G26: 4.377 | H26: 5.3875 | I26: 7.8682 | J26: 6.7023 | K26: 6.2233 | L26: 6.3717 | M26: 6.1585 | N26: 6.7142 | O26: 6.8816 | P26: 6.6318 | Q26: 5.971 | R26: 5.6115 | S26: 6.062 | T26: 7.0515 | U26: 7.0882 | V26: =IF(F26="",0,IF(F26<=CB$3,4,IF(F26>=CB$5,1,IF(F26>=CB$4,2,3)))) -> 2 | W26: =IF(G26="",0,IF(G26<=CC$3,4,IF(G26>=CC$5,1,IF(G26>=CC$4,2,3)))) -> 2 | X26: =IF(H26="",0,IF(H26<=CD$3,4,IF(H26>=CD$5,1,IF(H26>=CD$4,2,3)))) -> 3 | Y26: =IF(I26="",0,IF(I26<=CE$3,4,IF(I26>=CE$5,1,IF(I26>=CE$4,2,3)))) -> 3 | Z26: =IF(J26="",0,IF(J26<=CF$3,4,IF(J26>=CF$5,1,IF(J26>=CF$4,2,3)))) -> 3 | AA26: =IF(K26="",0,IF(K26<=CG$3,4,IF(K26>=CG$5,1,IF(K26>=CG$4,2,3)))) -> 3 | AB26: =IF(L26="",0,IF(L26<=CH$3,4,IF(L26>=CH$5,1,IF(L26>=CH$4,2,3)))) -> 3 | AC26: =IF(M26="",0,IF(M26<=CI$3,4,IF(M26>=CI$5,1,IF(M26>=CI$4,2,3)))) -> 3 | ... AK26: =IF(U26="",0,IF(U26<=CQ$3,4,IF(U26>=CQ$5,1,IF(U26>=CQ$4,2,3)))) -> 1 | AL26: 109.8813 | AM26: 0.332 | AN26: -10.2133 | AO26: 0.1538 | AP26: 0.1682 | AQ26: 7.72 | AR26: 0.32
A27: Invesco India Liquid Fund(G) | B27: 39038 | C27: 15423.272 | D27: 11723.175 | E27: 3771.83 | F27: 4.151 | G27: 4.4094 | H27: 5.5033 | I27: 8.0188 | J27: 6.811 | K27: 6.2818 | L27: 6.4579 | M27: 6.2152 | N27: 6.7546 | O27: 6.9155 | P27: 6.665 | Q27: 6.0053 | R27: 5.592 | S27: 6.0547 | T27: 7.0517 | U27: 7.0589 | V27: =IF(F27="",0,IF(F27<=CB$3,4,IF(F27>=CB$5,1,IF(F27>=CB$4,2,3)))) -> 2 | W27: =IF(G27="",0,IF(G27<=CC$3,4,IF(G27>=CC$5,1,IF(G27>=CC$4,2,3)))) -> 1 | X27: =IF(H27="",0,IF(H27<=CD$3,4,IF(H27>=CD$5,1,IF(H27>=CD$4,2,3)))) -> 1 | Y27: =IF(I27="",0,IF(I27<=CE$3,4,IF(I27>=CE$5,1,IF(I27>=CE$4,2,3)))) -> 1 | Z27: =IF(J27="",0,IF(J27<=CF$3,4,IF(J27>=CF$5,1,IF(J27>=CF$4,2,3)))) -> 2 | AA27: =IF(K27="",0,IF(K27<=CG$3,4,IF(K27>=CG$5,1,IF(K27>=CG$4,2,3)))) -> 2 | AB27: =IF(L27="",0,IF(L27<=CH$3,4,IF(L27>=CH$5,1,IF(L27>=CH$4,2,3)))) -> 1 | AC27: =IF(M27="",0,IF(M27<=CI$3,4,IF(M27>=CI$5,1,IF(M27>=CI$4,2,3)))) -> 1 | ... AK27: =IF(U27="",0,IF(U27<=CQ$3,4,IF(U27>=CQ$5,1,IF(U27>=CQ$4,2,3)))) -> 1 | AL27: 115.7912 | AM27: 0.3814 | AN27: -16.1727 | AO27: 0.1836 | AP27: 0.1836 | AQ27: 7.46 | AR27: 0.22
A28: ITI Liquid Fund-Reg(G) | B28: 43579 | C28: 55.7922 | D28: 57.9674 | E28: 1427.3739 | F28: 3.795 | G28: 4.0803 | H28: 5.3337 | I28: 7.6705 | J28: 6.4753 | K28: 5.986 | L28: 6.0901 | M28: 6.0503 | N28: 6.5113 | O28: 6.6148 | P28: 6.3736 | Q28: 5.728 | R28: 5.1937 | U28: 5.1968 | V28: =IF(F28="",0,IF(F28<=CB$3,4,IF(F28>=CB$5,1,IF(F28>=CB$4,2,3)))) -> 4 | W28: =IF(G28="",0,IF(G28<=CC$3,4,IF(G28>=CC$5,1,IF(G28>=CC$4,2,3)))) -> 4 | X28: =IF(H28="",0,IF(H28<=CD$3,4,IF(H28>=CD$5,1,IF(H28>=CD$4,2,3)))) -> 3 | Y28: =IF(I28="",0,IF(I28<=CE$3,4,IF(I28>=CE$5,1,IF(I28>=CE$4,2,3)))) -> 4 | Z28: =IF(J28="",0,IF(J28<=CF$3,4,IF(J28>=CF$5,1,IF(J28>=CF$4,2,3)))) -> 4 | AA28: =IF(K28="",0,IF(K28<=CG$3,4,IF(K28>=CG$5,1,IF(K28>=CG$4,2,3)))) -> 4 | AB28: =IF(L28="",0,IF(L28<=CH$3,4,IF(L28>=CH$5,1,IF(L28>=CH$4,2,3)))) -> 4 | AC28: =IF(M28="",0,IF(M28<=CI$3,4,IF(M28>=CI$5,1,IF(M28>=CI$4,2,3)))) -> 4 | ... AK28: =IF(U28="",0,IF(U28<=CQ$3,4,IF(U28>=CQ$5,1,IF(U28>=CQ$4,2,3)))) -> 4 | AL28: 88.5539 | AM28: 0.3164 | AN28: 11.1297 | AO28: 0.1616 | AP28: 0.1616 | AQ28: 6.93 | AR28: 0.25
A29: JM Liquid Fund(G) | B29: 35795 | C29: 2576.8493 | D29: 2566.8441 | E29: 74.7993 | F29: 3.9556 | G29: 4.2488 | H29: 5.4241 | I29: 7.6794 | J29: 6.6426 | K29: 6.1246 | L29: 6.2639 | M29: 6.0989 | N29: 6.6345 | O29: 6.8168 | P29: 6.5834 | Q29: 5.9473 | R29: 5.5477 | S29: 6.0378 | T29: 7.0393 | U29: 7.3563 | V29: =IF(F29="",0,IF(F29<=CB$3,4,IF(F29>=CB$5,1,IF(F29>=CB$4,2,3)))) -> 3 | W29: =IF(G29="",0,IF(G29<=CC$3,4,IF(G29>=CC$5,1,IF(G29>=CC$4,2,3)))) -> 3 | X29: =IF(H29="",0,IF(H29<=CD$3,4,IF(H29>=CD$5,1,IF(H29>=CD$4,2,3)))) -> 2 | Y29: =IF(I29="",0,IF(I29<=CE$3,4,IF(I29>=CE$5,1,IF(I29>=CE$4,2,3)))) -> 4 | Z29: =IF(J29="",0,IF(J29<=CF$3,4,IF(J29>=CF$5,1,IF(J29>=CF$4,2,3)))) -> 4 | AA29: =IF(K29="",0,IF(K29<=CG$3,4,IF(K29>=CG$5,1,IF(K29>=CG$4,2,3)))) -> 4 | AB29: =IF(L29="",0,IF(L29<=CH$3,4,IF(L29>=CH$5,1,IF(L29>=CH$4,2,3)))) -> 4 | AC29: =IF(M29="",0,IF(M29<=CI$3,4,IF(M29>=CI$5,1,IF(M29>=CI$4,2,3)))) -> 3 | ... AK29: =IF(U29="",0,IF(U29<=CQ$3,4,IF(U29>=CQ$5,1,IF(U29>=CQ$4,2,3)))) -> 1 | AL29: 94.0731 | AM29: 0.3212 | AN29: 5.6058 | AO29: 0.1479 | AP29: 0.1589 | AQ29: 7.11 | AR29: 0.26
A30: Kotak Liquid Fund-Reg(G) | B30: 37929 | C30: 42746.413 | D30: 33309.004 | E30: 5544.7385 | F30: 3.9787 | G30: 4.3092 | H30: 5.3938 | I30: 7.9625 | J30: 6.7887 | K30: 6.221 | L30: 6.3772 | M30: 6.1741 | N30: 6.7073 | O30: 6.8647 | P30: 6.6113 | Q30: 5.9558 | R30: 5.5651 | S30: 6.0212 | T30: 7.0192 | U30: 6.8527 | V30: =IF(F30="",0,IF(F30<=CB$3,4,IF(F30>=CB$5,1,IF(F30>=CB$4,2,3)))) -> 3 | W30: =IF(G30="",0,IF(G30<=CC$3,4,IF(G30>=CC$5,1,IF(G30>=CC$4,2,3)))) -> 3 | X30: =IF(H30="",0,IF(H30<=CD$3,4,IF(H30>=CD$5,1,IF(H30>=CD$4,2,3)))) -> 3 | Y30: =IF(I30="",0,IF(I30<=CE$3,4,IF(I30>=CE$5,1,IF(I30>=CE$4,2,3)))) -> 2 | Z30: =IF(J30="",0,IF(J30<=CF$3,4,IF(J30>=CF$5,1,IF(J30>=CF$4,2,3)))) -> 2 | AA30: =IF(K30="",0,IF(K30<=CG$3,4,IF(K30>=CG$5,1,IF(K30>=CG$4,2,3)))) -> 3 | AB30: =IF(L30="",0,IF(L30<=CH$3,4,IF(L30>=CH$5,1,IF(L30>=CH$4,2,3)))) -> 3 | AC30: =IF(M30="",0,IF(M30<=CI$3,4,IF(M30>=CI$5,1,IF(M30>=CI$4,2,3)))) -> 2 | ... AK30: =IF(U30="",0,IF(U30<=CQ$3,4,IF(U30>=CQ$5,1,IF(U30>=CQ$4,2,3)))) -> 2 | AL30: 122.2792 | AM30: 0.2975 | AN30: -22.5767 | AO30: 0.19 | AP30: 0.19 | AQ30: 7.64 | AR30: 0.31
A31: LIC MF Liquid Fund-Reg(G) | B31: 37328 | C31: 14186.719 | D31: 11106.165 | E31: 4959.9481 | F31: 4.315 | G31: 4.5411 | H31: 5.4347 | I31: 8.0961 | J31: 6.8979 | K31: 6.2912 | L31: 6.4956 | M31: 6.1788 | N31: 6.7096 | O31: 6.8799 | P31: 6.6226 | Q31: 5.9624 | R31: 5.5996 | S31: 6.0376 | T31: 6.9638 | U31: 6.8564 | V31: =IF(F31="",0,IF(F31<=CB$3,4,IF(F31>=CB$5,1,IF(F31>=CB$4,2,3)))) -> 1 | W31: =IF(G31="",0,IF(G31<=CC$3,4,IF(G31>=CC$5,1,IF(G31>=CC$4,2,3)))) -> 1 | X31: =IF(H31="",0,IF(H31<=CD$3,4,IF(H31>=CD$5,1,IF(H31>=CD$4,2,3)))) -> 2 | Y31: =IF(I31="",0,IF(I31<=CE$3,4,IF(I31>=CE$5,1,IF(I31>=CE$4,2,3)))) -> 1 | Z31: =IF(J31="",0,IF(J31<=CF$3,4,IF(J31>=CF$5,1,IF(J31>=CF$4,2,3)))) -> 1 | AA31: =IF(K31="",0,IF(K31<=CG$3,4,IF(K31>=CG$5,1,IF(K31>=CG$4,2,3)))) -> 1 | AB31: =IF(L31="",0,IF(L31<=CH$3,4,IF(L31>=CH$5,1,IF(L31>=CH$4,2,3)))) -> 1 | AC31: =IF(M31="",0,IF(M31<=CI$3,4,IF(M31>=CI$5,1,IF(M31>=CI$4,2,3)))) -> 2 | ... AK31: =IF(U31="",0,IF(U31<=CQ$3,4,IF(U31>=CQ$5,1,IF(U31>=CQ$4,2,3)))) -> 2 | AL31: 111.9282 | AM31: 0.299 | AN31: -12.2272 | AO31: 0.1698 | AP31: 0.1698 | AQ31: 7.65 | AR31: 0.2
A32: Mahindra Manulife Liquid Fund-Reg(G) | B32: 42555 | C32: 1144.7093 | D32: 1012.3222 | E32: 1785.6494 | F32: 3.9247 | G32: 4.2407 | H32: 5.3644 | I32: 7.8301 | J32: 6.8252 | K32: 6.2679 | L32: 6.3944 | M32: 6.2125 | N32: 6.7429 | O32: 6.9139 | P32: 6.6794 | Q32: 6.0219 | R32: 5.6636 | U32: 6.0754 | V32: =IF(F32="",0,IF(F32<=CB$3,4,IF(F32>=CB$5,1,IF(F32>=CB$4,2,3)))) -> 3 | W32: =IF(G32="",0,IF(G32<=CC$3,4,IF(G32>=CC$5,1,IF(G32>=CC$4,2,3)))) -> 3 | X32: =IF(H32="",0,IF(H32<=CD$3,4,IF(H32>=CD$5,1,IF(H32>=CD$4,2,3)))) -> 3 | Y32: =IF(I32="",0,IF(I32<=CE$3,4,IF(I32>=CE$5,1,IF(I32>=CE$4,2,3)))) -> 3 | Z32: =IF(J32="",0,IF(J32<=CF$3,4,IF(J32>=CF$5,1,IF(J32>=CF$4,2,3)))) -> 2 | AA32: =IF(K32="",0,IF(K32<=CG$3,4,IF(K32>=CG$5,1,IF(K32>=CG$4,2,3)))) -> 2 | AB32: =IF(L32="",0,IF(L32<=CH$3,4,IF(L32>=CH$5,1,IF(L32>=CH$4,2,3)))) -> 3 | AC32: =IF(M32="",0,IF(M32<=CI$3,4,IF(M32>=CI$5,1,IF(M32>=CI$4,2,3)))) -> 2 | ... AK32: =IF(U32="",0,IF(U32<=CQ$3,4,IF(U32>=CQ$5,1,IF(U32>=CQ$4,2,3)))) -> 4 | AL32: 98.1887 | AM32: 0.325 | AN32: 1.4863 | AO32: 0.1461 | AP32: 0.1562 | AQ32: 7.58 | AR32: 0.26
A33: Mirae Asset Liquid Fund-Reg(G) | B33: 39825 | C33: 12394.755 | D33: 10561.68 | E33: 2876.5202 | F33: 3.741 | G33: 4.1651 | H33: 5.3792 | I33: 7.6172 | J33: 6.7562 | K33: 6.214 | L33: 6.3378 | M33: 6.1735 | N33: 6.7218 | O33: 6.8916 | P33: 6.6521 | Q33: 5.9969 | R33: 5.6165 | S33: 6.0375 | T33: 6.6959 | U33: 6.2952 | V33: =IF(F33="",0,IF(F33<=CB$3,4,IF(F33>=CB$5,1,IF(F33>=CB$4,2,3)))) -> 4 | W33: =IF(G33="",0,IF(G33<=CC$3,4,IF(G33>=CC$5,1,IF(G33>=CC$4,2,3)))) -> 4 | X33: =IF(H33="",0,IF(H33<=CD$3,4,IF(H33>=CD$5,1,IF(H33>=CD$4,2,3)))) -> 3 | Y33: =IF(I33="",0,IF(I33<=CE$3,4,IF(I33>=CE$5,1,IF(I33>=CE$4,2,3)))) -> 4 | Z33: =IF(J33="",0,IF(J33<=CF$3,4,IF(J33>=CF$5,1,IF(J33>=CF$4,2,3)))) -> 3 | AA33: =IF(K33="",0,IF(K33<=CG$3,4,IF(K33>=CG$5,1,IF(K33>=CG$4,2,3)))) -> 3 | AB33: =IF(L33="",0,IF(L33<=CH$3,4,IF(L33>=CH$5,1,IF(L33>=CH$4,2,3)))) -> 3 | AC33: =IF(M33="",0,IF(M33<=CI$3,4,IF(M33>=CI$5,1,IF(M33>=CI$4,2,3)))) -> 3 | ... AK33: =IF(U33="",0,IF(U33<=CQ$3,4,IF(U33>=CQ$5,1,IF(U33>=CQ$4,2,3)))) -> 3 | AL33: 125.1841 | AM33: 0.409 | AN33: -25.5931 | AO33: 0.19 | AP33: 0.1995 | AQ33: 7.58 | AR33: 0.18
A34: Motilal Oswal Liquid Fund-Reg(G) | B34: 43453 | C34: 1114.0563 | D34: 1016.6546 | E34: 14.4539 | F34: 4.0436 | G34: 4.3905 | H34: 5.029 | I34: 6.8332 | J34: 6.2278 | K34: 5.8402 | L34: 5.9277 | M34: 5.7654 | N34: 6.2681 | O34: 6.4422 | P34: 6.1883 | Q34: 5.5641 | R34: 5.078 | U34: 5.1274 | V34: =IF(F34="",0,IF(F34<=CB$3,4,IF(F34>=CB$5,1,IF(F34>=CB$4,2,3)))) -> 2 | W34: =IF(G34="",0,IF(G34<=CC$3,4,IF(G34>=CC$5,1,IF(G34>=CC$4,2,3)))) -> 2 | X34: =IF(H34="",0,IF(H34<=CD$3,4,IF(H34>=CD$5,1,IF(H34>=CD$4,2,3)))) -> 4 | Y34: =IF(I34="",0,IF(I34<=CE$3,4,IF(I34>=CE$5,1,IF(I34>=CE$4,2,3)))) -> 4 | Z34: =IF(J34="",0,IF(J34<=CF$3,4,IF(J34>=CF$5,1,IF(J34>=CF$4,2,3)))) -> 4 | AA34: =IF(K34="",0,IF(K34<=CG$3,4,IF(K34>=CG$5,1,IF(K34>=CG$4,2,3)))) -> 4 | AB34: =IF(L34="",0,IF(L34<=CH$3,4,IF(L34>=CH$5,1,IF(L34>=CH$4,2,3)))) -> 4 | AC34: =IF(M34="",0,IF(M34<=CI$3,4,IF(M34>=CI$5,1,IF(M34>=CI$4,2,3)))) -> 4 | ... AK34: =IF(U34="",0,IF(U34<=CQ$3,4,IF(U34>=CQ$5,1,IF(U34>=CQ$4,2,3)))) -> 4 | AL34: 95.2327 | AM34: 0.3242 | AN34: 4.4431 | AO34: 0.09 | AP34: 0.09 | AQ34: 7.21 | AR34: 0.35
A35: Navi Liquid Fund-Reg(G) | B35: 40228 | C35: 83.8145 | D35: 62.247 | E35: 29.7184 | F35: 4.3374 | G35: 4.5347 | H35: 4.9267 | I35: 6.4174 | J35: 5.7646 | K35: 5.6535 | L35: 5.6642 | M35: 5.7466 | N35: 6.3056 | O35: 6.4891 | P35: 6.3391 | Q35: 5.8241 | R35: 5.36 | S35: 5.9183 | T35: 6.9968 | U35: 6.9533 | V35: =IF(F35="",0,IF(F35<=CB$3,4,IF(F35>=CB$5,1,IF(F35>=CB$4,2,3)))) -> 1 | W35: =IF(G35="",0,IF(G35<=CC$3,4,IF(G35>=CC$5,1,IF(G35>=CC$4,2,3)))) -> 1 | X35: =IF(H35="",0,IF(H35<=CD$3,4,IF(H35>=CD$5,1,IF(H35>=CD$4,2,3)))) -> 4 | Y35: =IF(I35="",0,IF(I35<=CE$3,4,IF(I35>=CE$5,1,IF(I35>=CE$4,2,3)))) -> 4 | Z35: =IF(J35="",0,IF(J35<=CF$3,4,IF(J35>=CF$5,1,IF(J35>=CF$4,2,3)))) -> 4 | AA35: =IF(K35="",0,IF(K35<=CG$3,4,IF(K35>=CG$5,1,IF(K35>=CG$4,2,3)))) -> 4 | AB35: =IF(L35="",0,IF(L35<=CH$3,4,IF(L35>=CH$5,1,IF(L35>=CH$4,2,3)))) -> 4 | AC35: =IF(M35="",0,IF(M35<=CI$3,4,IF(M35>=CI$5,1,IF(M35>=CI$4,2,3)))) -> 4 | ... AK35: =IF(U35="",0,IF(U35<=CQ$3,4,IF(U35>=CQ$5,1,IF(U35>=CQ$4,2,3)))) -> 1 | AL35: 83.2204 | AM35: 0.7528 | AN35: 16.0268 | AO35: 0.07 | AP35: 0.07 | AQ35: 6.33 | AR35: 0.2
A36: Nippon India Liquid Fund(G) | B36: 37964 | C36: 32735.755 | D36: 25755.634 | E36: 6696.2579 | F36: 4.0757 | G36: 4.3567 | H36: 5.4631 | I36: 8.0077 | J36: 6.8568 | K36: 6.274 | L36: 6.4422 | M36: 6.196 | N36: 6.7199 | O36: 6.8802 | P36: 6.6291 | Q36: 5.97 | R36: 5.6187 | S36: 6.0792 | T36: 7.0604 | U36: 6.8408 | V36: =IF(F36="",0,IF(F36<=CB$3,4,IF(F36>=CB$5,1,IF(F36>=CB$4,2,3)))) -> 2 | W36: =IF(G36="",0,IF(G36<=CC$3,4,IF(G36>=CC$5,1,IF(G36>=CC$4,2,3)))) -> 2 | X36: =IF(H36="",0,IF(H36<=CD$3,4,IF(H36>=CD$5,1,IF(H36>=CD$4,2,3)))) -> 2 | Y36: =IF(I36="",0,IF(I36<=CE$3,4,IF(I36>=CE$5,1,IF(I36>=CE$4,2,3)))) -> 2 | Z36: =IF(J36="",0,IF(J36<=CF$3,4,IF(J36>=CF$5,1,IF(J36>=CF$4,2,3)))) -> 1 | AA36: =IF(K36="",0,IF(K36<=CG$3,4,IF(K36>=CG$5,1,IF(K36>=CG$4,2,3)))) -> 2 | AB36: =IF(L36="",0,IF(L36<=CH$3,4,IF(L36>=CH$5,1,IF(L36>=CH$4,2,3)))) -> 2 | AC36: =IF(M36="",0,IF(M36<=CI$3,4,IF(M36>=CI$5,1,IF(M36>=CI$4,2,3)))) -> 2 | ... AK36: =IF(U36="",0,IF(U36<=CQ$3,4,IF(U36>=CQ$5,1,IF(U36>=CQ$4,2,3)))) -> 2 | AL36: 120.4097 | AM36: 0.3727 | AN36: -20.7823 | AO36: 0.1699 | AP36: 0.1836 | AQ36: 7.72 | AR36: 0.38
A37: Parag Parikh Liquid Fund-Reg(G) | B37: 43231 | C37: 5097.779 | D37: 5170.9341 | E37: 1521.615 | F37: 3.7447 | G37: 4.0965 | H37: 5.4719 | I37: 8.0089 | J37: 6.8795 | K37: 6.2412 | L37: 6.4406 | M37: 6.1073 | N37: 6.5029 | O37: 6.6076 | P37: 6.3291 | Q37: 5.7088 | R37: 5.2683 | U37: 5.4023 | V37: =IF(F37="",0,IF(F37<=CB$3,4,IF(F37>=CB$5,1,IF(F37>=CB$4,2,3)))) -> 4 | W37: =IF(G37="",0,IF(G37<=CC$3,4,IF(G37>=CC$5,1,IF(G37>=CC$4,2,3)))) -> 4 | X37: =IF(H37="",0,IF(H37<=CD$3,4,IF(H37>=CD$5,1,IF(H37>=CD$4,2,3)))) -> 2 | Y37: =IF(I37="",0,IF(I37<=CE$3,4,IF(I37>=CE$5,1,IF(I37>=CE$4,2,3)))) -> 2 | Z37: =IF(J37="",0,IF(J37<=CF$3,4,IF(J37>=CF$5,1,IF(J37>=CF$4,2,3)))) -> 1 | AA37: =IF(K37="",0,IF(K37<=CG$3,4,IF(K37>=CG$5,1,IF(K37>=CG$4,2,3)))) -> 2 | AB37: =IF(L37="",0,IF(L37<=CH$3,4,IF(L37>=CH$5,1,IF(L37>=CH$4,2,3)))) -> 2 | AC37: =IF(M37="",0,IF(M37<=CI$3,4,IF(M37>=CI$5,1,IF(M37>=CI$4,2,3)))) -> 3 | ... AK37: =IF(U37="",0,IF(U37<=CQ$3,4,IF(U37>=CQ$5,1,IF(U37>=CQ$4,2,3)))) -> 4 | AL37: 98.849 | AM37: 0.2584 | AN37: 0.8927 | AO37: 0.1617 | AP37: 0.1759 | AQ37: 7.06 | AR37: 0.21
A38: PGIM India Liquid Fund(G) | B38: 39329 | C38: 677.3513 | D38: 478.4765 | E38: 357.247 | F38: 4.2508 | G38: 4.4696 | H38: 5.4501 | I38: 8.1095 | J38: 6.8271 | K38: 6.2753 | L38: 6.4539 | M38: 6.2037 | N38: 6.7472 | O38: 6.8956 | P38: 6.6539 | Q38: 5.9961 | R38: 5.629 | S38: 6.0916 | T38: 7.0643 | U38: 7.0594 | V38: =IF(F38="",0,IF(F38<=CB$3,4,IF(F38>=CB$5,1,IF(F38>=CB$4,2,3)))) -> 1 | W38: =IF(G38="",0,IF(G38<=CC$3,4,IF(G38>=CC$5,1,IF(G38>=CC$4,2,3)))) -> 1 | X38: =IF(H38="",0,IF(H38<=CD$3,4,IF(H38>=CD$5,1,IF(H38>=CD$4,2,3)))) -> 2 | Y38: =IF(I38="",0,IF(I38<=CE$3,4,IF(I38>=CE$5,1,IF(I38>=CE$4,2,3)))) -> 1 | Z38: =IF(J38="",0,IF(J38<=CF$3,4,IF(J38>=CF$5,1,IF(J38>=CF$4,2,3)))) -> 2 | AA38: =IF(K38="",0,IF(K38<=CG$3,4,IF(K38>=CG$5,1,IF(K38>=CG$4,2,3)))) -> 2 | AB38: =IF(L38="",0,IF(L38<=CH$3,4,IF(L38>=CH$5,1,IF(L38>=CH$4,2,3)))) -> 2 | AC38: =IF(M38="",0,IF(M38<=CI$3,4,IF(M38>=CI$5,1,IF(M38>=CI$4,2,3)))) -> 2 | ... AK38: =IF(U38="",0,IF(U38<=CQ$3,4,IF(U38>=CQ$5,1,IF(U38>=CQ$4,2,3)))) -> 1 | AL38: 111.3536 | AM38: 0.4839 | AN38: -11.8375 | AO38: 0.1592 | AP38: 0.17 | AQ38: 7.71 | AR38: 0.22
A39: Quant Liquid Plan(G) | B39: 38624 | C39: 1261.4469 | D39: 1417.7622 | E39: 43.2472 | F39: 4.32 | G39: 4.4385 | H39: 4.7917 | I39: 6.0752 | J39: 6.0107 | K39: 5.7226 | L39: 5.7582 | M39: 5.8147 | N39: 6.4222 | O39: 6.5816 | P39: 6.3458 | Q39: 5.8373 | R39: 5.7316 | S39: 6.1622 | T39: 7.311 | U39: 7.3682 | V39: =IF(F39="",0,IF(F39<=CB$3,4,IF(F39>=CB$5,1,IF(F39>=CB$4,2,3)))) -> 1 | W39: =IF(G39="",0,IF(G39<=CC$3,4,IF(G39>=CC$5,1,IF(G39>=CC$4,2,3)))) -> 1 | X39: =IF(H39="",0,IF(H39<=CD$3,4,IF(H39>=CD$5,1,IF(H39>=CD$4,2,3)))) -> 4 | Y39: =IF(I39="",0,IF(I39<=CE$3,4,IF(I39>=CE$5,1,IF(I39>=CE$4,2,3)))) -> 4 | Z39: =IF(J39="",0,IF(J39<=CF$3,4,IF(J39>=CF$5,1,IF(J39>=CF$4,2,3)))) -> 4 | AA39: =IF(K39="",0,IF(K39<=CG$3,4,IF(K39>=CG$5,1,IF(K39>=CG$4,2,3)))) -> 4 | AB39: =IF(L39="",0,IF(L39<=CH$3,4,IF(L39>=CH$5,1,IF(L39>=CH$4,2,3)))) -> 4 | AC39: =IF(M39="",0,IF(M39<=CI$3,4,IF(M39>=CI$5,1,IF(M39>=CI$4,2,3)))) -> 4 | ... AK39: =IF(U39="",0,IF(U39<=CQ$3,4,IF(U39>=CQ$5,1,IF(U39>=CQ$4,2,3)))) -> 1 | AL39: 71.7894 | AM39: 0.5327 | AN39: 27.678 | AO39: 0.0685 | AP39: 0.074 | AQ39: 6.77 | AR39: 0.54
A40: SBI Liquid Fund-Reg(G) | B40: 39152 | C40: 66119.335 | D40: 57891.291 | E40: 4287.4945 | F40: 3.9062 | G40: 4.2381 | H40: 5.3453 | I40: 8.0269 | J40: 6.803 | K40: 6.2448 | L40: 6.4204 | M40: 6.1554 | N40: 6.6666 | O40: 6.8338 | P40: 6.5964 | Q40: 5.9477 | R40: 5.5709 | S40: 6.0084 | T40: 7.0013 | U40: 6.6889 | V40: =IF(F40="",0,IF(F40<=CB$3,4,IF(F40>=CB$5,1,IF(F40>=CB$4,2,3)))) -> 3 | W40: =IF(G40="",0,IF(G40<=CC$3,4,IF(G40>=CC$5,1,IF(G40>=CC$4,2,3)))) -> 3 | X40: =IF(H40="",0,IF(H40<=CD$3,4,IF(H40>=CD$5,1,IF(H40>=CD$4,2,3)))) -> 3 | Y40: =IF(I40="",0,IF(I40<=CE$3,4,IF(I40>=CE$5,1,IF(I40>=CE$4,2,3)))) -> 1 | Z40: =IF(J40="",0,IF(J40<=CF$3,4,IF(J40>=CF$5,1,IF(J40>=CF$4,2,3)))) -> 2 | AA40: =IF(K40="",0,IF(K40<=CG$3,4,IF(K40>=CG$5,1,IF(K40>=CG$4,2,3)))) -> 2 | AB40: =IF(L40="",0,IF(L40<=CH$3,4,IF(L40>=CH$5,1,IF(L40>=CH$4,2,3)))) -> 2 | AC40: =IF(M40="",0,IF(M40<=CI$3,4,IF(M40>=CI$5,1,IF(M40>=CI$4,2,3)))) -> 3 | ... AK40: =IF(U40="",0,IF(U40<=CQ$3,4,IF(U40>=CQ$5,1,IF(U40>=CQ$4,2,3)))) -> 3 | AL40: 116.2199 | AM40: 0.3204 | AN40: -16.5403 | AO40: 0.17 | AP40: 0.18 | AQ40: 7.58 | AR40: 0.28
A41: Shriram Liquid Fund-Reg(G) | B41: 45610 | C41: 222.6764 | D41: 138.0267 | E41: 1093.1538 | F41: 3.8488 | G41: 4.2768 | H41: 5.2408 | I41: 7.89 | J41: 6.5637 | K41: 6.0612 | L41: 6.2215 | M41: 5.9448 | U41: 6.3014 | V41: =IF(F41="",0,IF(F41<=CB$3,4,IF(F41>=CB$5,1,IF(F41>=CB$4,2,3)))) -> 4 | W41: =IF(G41="",0,IF(G41<=CC$3,4,IF(G41>=CC$5,1,IF(G41>=CC$4,2,3)))) -> 3 | X41: =IF(H41="",0,IF(H41<=CD$3,4,IF(H41>=CD$5,1,IF(H41>=CD$4,2,3)))) -> 4 | Y41: =IF(I41="",0,IF(I41<=CE$3,4,IF(I41>=CE$5,1,IF(I41>=CE$4,2,3)))) -> 2 | Z41: =IF(J41="",0,IF(J41<=CF$3,4,IF(J41>=CF$5,1,IF(J41>=CF$4,2,3)))) -> 4 | AA41: =IF(K41="",0,IF(K41<=CG$3,4,IF(K41>=CG$5,1,IF(K41>=CG$4,2,3)))) -> 4 | AB41: =IF(L41="",0,IF(L41<=CH$3,4,IF(L41>=CH$5,1,IF(L41>=CH$4,2,3)))) -> 4 | AC41: =IF(M41="",0,IF(M41<=CI$3,4,IF(M41>=CI$5,1,IF(M41>=CI$4,2,3)))) -> 4 | ... AK41: =IF(U41="",0,IF(U41<=CQ$3,4,IF(U41>=CQ$5,1,IF(U41>=CQ$4,2,3)))) -> 3 | AL41: 118.1235 | AM41: 0.2995 | AN41: -18.423 | AO41: 0.186 | AP41: 0.1995 | AQ41: 7.36 | AR41: 0.27
A42: Sundaram Liquid Fund(G) | B42: 38229 | C42: 6220.8825 | D42: 5174.93 | E42: 2417.9435 | F42: 3.9194 | G42: 4.2011 | H42: 5.3653 | I42: 7.8239 | J42: 6.6776 | K42: 6.1359 | L42: 6.2899 | M42: 6.0777 | N42: 6.6523 | O42: 6.8309 | P42: 6.6088 | Q42: 5.9468 | R42: 5.478 | S42: 5.0242 | T42: 6.3478 | U42: 6.4394 | V42: =IF(F42="",0,IF(F42<=CB$3,4,IF(F42>=CB$5,1,IF(F42>=CB$4,2,3)))) -> 3 | W42: =IF(G42="",0,IF(G42<=CC$3,4,IF(G42>=CC$5,1,IF(G42>=CC$4,2,3)))) -> 4 | X42: =IF(H42="",0,IF(H42<=CD$3,4,IF(H42>=CD$5,1,IF(H42>=CD$4,2,3)))) -> 3 | Y42: =IF(I42="",0,IF(I42<=CE$3,4,IF(I42>=CE$5,1,IF(I42>=CE$4,2,3)))) -> 3 | Z42: =IF(J42="",0,IF(J42<=CF$3,4,IF(J42>=CF$5,1,IF(J42>=CF$4,2,3)))) -> 4 | AA42: =IF(K42="",0,IF(K42<=CG$3,4,IF(K42>=CG$5,1,IF(K42>=CG$4,2,3)))) -> 3 | AB42: =IF(L42="",0,IF(L42<=CH$3,4,IF(L42>=CH$5,1,IF(L42>=CH$4,2,3)))) -> 3 | AC42: =IF(M42="",0,IF(M42<=CI$3,4,IF(M42>=CI$5,1,IF(M42>=CI$4,2,3)))) -> 4 | ... AK42: =IF(U42="",0,IF(U42<=CQ$3,4,IF(U42>=CQ$5,1,IF(U42>=CQ$4,2,3)))) -> 3 | AL42: 117.4966 | AM42: 0.3472 | AN42: -17.8439 | AO42: 0.2 | AP42: 0.2 | AQ42: 7.5 | AR42: 0.35
A43: Tata Liquid Fund-Reg(G) | B43: 38231 | C43: 33551.105 | D43: 22315.559 | E43: 4321.5892 | F43: 3.6885 | G43: 4.122 | H43: 5.4278 | I43: 7.7446 | J43: 6.7718 | K43: 6.2599 | L43: 6.3958 | M43: 6.1986 | N43: 6.7346 | O43: 6.8907 | P43: 6.6275 | Q43: 5.9718 | R43: 5.6138 | S43: 6.0707 | T43: 7.068 | U43: 6.9861 | V43: =IF(F43="",0,IF(F43<=CB$3,4,IF(F43>=CB$5,1,IF(F43>=CB$4,2,3)))) -> 4 | W43: =IF(G43="",0,IF(G43<=CC$3,4,IF(G43>=CC$5,1,IF(G43>=CC$4,2,3)))) -> 4 | X43: =IF(H43="",0,IF(H43<=CD$3,4,IF(H43>=CD$5,1,IF(H43>=CD$4,2,3)))) -> 2 | Y43: =IF(I43="",0,IF(I43<=CE$3,4,IF(I43>=CE$5,1,IF(I43>=CE$4,2,3)))) -> 4 | Z43: =IF(J43="",0,IF(J43<=CF$3,4,IF(J43>=CF$5,1,IF(J43>=CF$4,2,3)))) -> 3 | AA43: =IF(K43="",0,IF(K43<=CG$3,4,IF(K43>=CG$5,1,IF(K43>=CG$4,2,3)))) -> 2 | AB43: =IF(L43="",0,IF(L43<=CH$3,4,IF(L43>=CH$5,1,IF(L43>=CH$4,2,3)))) -> 2 | AC43: =IF(M43="",0,IF(M43<=CI$3,4,IF(M43>=CI$5,1,IF(M43>=CI$4,2,3)))) -> 2 | ... AK43: =IF(U43="",0,IF(U43<=CQ$3,4,IF(U43>=CQ$5,1,IF(U43>=CQ$4,2,3)))) -> 1 | AL43: 102.4061 | AM43: 0.304 | AN43: -2.7101 | AO43: 0.1644 | AP43: 0.1644 | AQ43: 7.58 | AR43: 0.31
A44: The Wealth Company Liquid Fund-Reg(G) | B44: 45944 | C44: 713.6016 | D44: 484.0456 | E44: 1034.5168 | F44: 4.0495 | G44: 4.289 | H44: 5.1907 | I44: 7.8191 | J44: 6.907 | K44: 6.2736 | L44: 6.4582 | U44: 6.4554 | V44: =IF(F44="",0,IF(F44<=CB$3,4,IF(F44>=CB$5,1,IF(F44>=CB$4,2,3)))) -> 2 | W44: =IF(G44="",0,IF(G44<=CC$3,4,IF(G44>=CC$5,1,IF(G44>=CC$4,2,3)))) -> 3 | X44: =IF(H44="",0,IF(H44<=CD$3,4,IF(H44>=CD$5,1,IF(H44>=CD$4,2,3)))) -> 4 | Y44: =IF(I44="",0,IF(I44<=CE$3,4,IF(I44>=CE$5,1,IF(I44>=CE$4,2,3)))) -> 3 | Z44: =IF(J44="",0,IF(J44<=CF$3,4,IF(J44>=CF$5,1,IF(J44>=CF$4,2,3)))) -> 1 | AA44: =IF(K44="",0,IF(K44<=CG$3,4,IF(K44>=CG$5,1,IF(K44>=CG$4,2,3)))) -> 2 | AB44: =IF(L44="",0,IF(L44<=CH$3,4,IF(L44>=CH$5,1,IF(L44>=CH$4,2,3)))) -> 1 | AC44: =IF(M44="",0,IF(M44<=CI$3,4,IF(M44>=CI$5,1,IF(M44>=CI$4,2,3)))) -> 0 | ... AK44: =IF(U44="",0,IF(U44<=CQ$3,4,IF(U44>=CQ$5,1,IF(U44>=CQ$4,2,3)))) -> 3 | AL44: 96.3423 | AM44: 0.5071 | AN44: 3.1505 | AO44: 0.1312 | AP44: 0.1413 | AQ44: 7.72 | AR44: 0.23
A45: TRUSTMF Liquid Fund-Reg(G) | B45: 44309 | C45: 942.6049 | D45: 706.0644 | E45: 1332.2256 | F45: 3.3588 | G45: 3.784 | H45: 5.2406 | I45: 7.778 | J45: 6.6425 | K45: 6.1326 | L45: 6.2682 | M45: 6.0811 | N45: 6.6099 | O45: 6.7806 | P45: 6.548 | Q45: 5.8872 | U45: 5.8783 | V45: =IF(F45="",0,IF(F45<=CB$3,4,IF(F45>=CB$5,1,IF(F45>=CB$4,2,3)))) -> 4 | W45: =IF(G45="",0,IF(G45<=CC$3,4,IF(G45>=CC$5,1,IF(G45>=CC$4,2,3)))) -> 4 | X45: =IF(H45="",0,IF(H45<=CD$3,4,IF(H45>=CD$5,1,IF(H45>=CD$4,2,3)))) -> 4 | Y45: =IF(I45="",0,IF(I45<=CE$3,4,IF(I45>=CE$5,1,IF(I45>=CE$4,2,3)))) -> 3 | Z45: =IF(J45="",0,IF(J45<=CF$3,4,IF(J45>=CF$5,1,IF(J45>=CF$4,2,3)))) -> 4 | AA45: =IF(K45="",0,IF(K45<=CG$3,4,IF(K45>=CG$5,1,IF(K45>=CG$4,2,3)))) -> 4 | AB45: =IF(L45="",0,IF(L45<=CH$3,4,IF(L45>=CH$5,1,IF(L45>=CH$4,2,3)))) -> 4 | AC45: =IF(M45="",0,IF(M45<=CI$3,4,IF(M45>=CI$5,1,IF(M45>=CI$4,2,3)))) -> 4 | ... AK45: =IF(U45="",0,IF(U45<=CQ$3,4,IF(U45>=CQ$5,1,IF(U45>=CQ$4,2,3)))) -> 4 | AL45: 98.2696 | AM45: 0.2231 | AN45: 1.5074 | AO45: 0.1863 | AP45: 0.1863 | AQ45: 7.14 | AR45: 0.25
A46: Unifi Liquid Fund-Reg(G) | B46: 45819 | C46: 162.8614 | D46: 46.6928 | E46: 1054.0592 | F46: 5.0205 | G46: 5.0365 | H46: 5.6588 | I46: 8.2378 | J46: 6.4886 | K46: 6.0591 | L46: 6.2845 | U46: 6.13 | V46: =IF(F46="",0,IF(F46<=CB$3,4,IF(F46>=CB$5,1,IF(F46>=CB$4,2,3)))) -> 1 | W46: =IF(G46="",0,IF(G46<=CC$3,4,IF(G46>=CC$5,1,IF(G46>=CC$4,2,3)))) -> 1 | X46: =IF(H46="",0,IF(H46<=CD$3,4,IF(H46>=CD$5,1,IF(H46>=CD$4,2,3)))) -> 1 | Y46: =IF(I46="",0,IF(I46<=CE$3,4,IF(I46>=CE$5,1,IF(I46>=CE$4,2,3)))) -> 1 | Z46: =IF(J46="",0,IF(J46<=CF$3,4,IF(J46>=CF$5,1,IF(J46>=CF$4,2,3)))) -> 4 | AA46: =IF(K46="",0,IF(K46<=CG$3,4,IF(K46>=CG$5,1,IF(K46>=CG$4,2,3)))) -> 4 | AB46: =IF(L46="",0,IF(L46<=CH$3,4,IF(L46>=CH$5,1,IF(L46>=CH$4,2,3)))) -> 4 | AC46: =IF(M46="",0,IF(M46<=CI$3,4,IF(M46>=CI$5,1,IF(M46>=CI$4,2,3)))) -> 0 | ... AK46: =IF(U46="",0,IF(U46<=CQ$3,4,IF(U46>=CQ$5,1,IF(U46>=CQ$4,2,3)))) -> 4 | AL46: 63.952 | AM46: 12.0255 | AN46: 24.0224 | AP46: 0.07 | AQ46: 7.49 | AR46: 0.2
A47: Union Liquid Fund(G) | B47: 40709 | C47: 7923.4336 | D47: 5755.5955 | E47: 2640.6515 | F47: 4.0778 | G47: 4.3704 | H47: 5.5825 | I47: 7.8423 | J47: 6.7794 | K47: 6.2868 | L47: 6.4321 | M47: 6.2143 | N47: 6.7522 | O47: 6.9173 | P47: 6.6788 | Q47: 6.0177 | R47: 5.6385 | S47: 5.6614 | U47: 6.7397 | V47: =IF(F47="",0,IF(F47<=CB$3,4,IF(F47>=CB$5,1,IF(F47>=CB$4,2,3)))) -> 2 | W47: =IF(G47="",0,IF(G47<=CC$3,4,IF(G47>=CC$5,1,IF(G47>=CC$4,2,3)))) -> 2 | X47: =IF(H47="",0,IF(H47<=CD$3,4,IF(H47>=CD$5,1,IF(H47>=CD$4,2,3)))) -> 1 | Y47: =IF(I47="",0,IF(I47<=CE$3,4,IF(I47>=CE$5,1,IF(I47>=CE$4,2,3)))) -> 3 | Z47: =IF(J47="",0,IF(J47<=CF$3,4,IF(J47>=CF$5,1,IF(J47>=CF$4,2,3)))) -> 3 | AA47: =IF(K47="",0,IF(K47<=CG$3,4,IF(K47>=CG$5,1,IF(K47>=CG$4,2,3)))) -> 1 | AB47: =IF(L47="",0,IF(L47<=CH$3,4,IF(L47>=CH$5,1,IF(L47>=CH$4,2,3)))) -> 2 | AC47: =IF(M47="",0,IF(M47<=CI$3,4,IF(M47>=CI$5,1,IF(M47>=CI$4,2,3)))) -> 1 | ... AK47: =IF(U47="",0,IF(U47<=CQ$3,4,IF(U47>=CQ$5,1,IF(U47>=CQ$4,2,3)))) -> 3 | AL47: 108.2832 | AM47: 0.2656 | AN47: -8.5488 | AO47: 0.1616 | AP47: 0.1753 | AQ47: 7.5 | AR47: 0.17
A48: UTI Liquid Fund-Reg(G) | B48: 37965 | C48: 27263.409 | D48: 19763.193 | E48: 4502.7207 | F48: 4.029 | G48: 4.331 | H48: 5.4323 | I48: 7.9555 | J48: 6.8778 | K48: 6.3133 | L48: 6.4842 | M48: 6.228 | N48: 6.757 | O48: 6.9093 | P48: 6.673 | Q48: 6.0148 | R48: 5.631 | S48: 6.0859 | T48: 7.043 | U48: 6.8415 | V48: =IF(F48="",0,IF(F48<=CB$3,4,IF(F48>=CB$5,1,IF(F48>=CB$4,2,3)))) -> 3 | W48: =IF(G48="",0,IF(G48<=CC$3,4,IF(G48>=CC$5,1,IF(G48>=CC$4,2,3)))) -> 2 | X48: =IF(H48="",0,IF(H48<=CD$3,4,IF(H48>=CD$5,1,IF(H48>=CD$4,2,3)))) -> 2 | Y48: =IF(I48="",0,IF(I48<=CE$3,4,IF(I48>=CE$5,1,IF(I48>=CE$4,2,3)))) -> 2 | Z48: =IF(J48="",0,IF(J48<=CF$3,4,IF(J48>=CF$5,1,IF(J48>=CF$4,2,3)))) -> 1 | AA48: =IF(K48="",0,IF(K48<=CG$3,4,IF(K48>=CG$5,1,IF(K48>=CG$4,2,3)))) -> 1 | AB48: =IF(L48="",0,IF(L48<=CH$3,4,IF(L48>=CH$5,1,IF(L48>=CH$4,2,3)))) -> 1 | AC48: =IF(M48="",0,IF(M48<=CI$3,4,IF(M48>=CI$5,1,IF(M48>=CI$4,2,3)))) -> 1 | ... AK48: =IF(U48="",0,IF(U48<=CQ$3,4,IF(U48>=CQ$5,1,IF(U48>=CQ$4,2,3)))) -> 2 | AL48: 120.2723 | AM48: 0.3433 | AN48: -20.6912 | AO48: 0.1836 | AP48: 0.1836 | AQ48: 7.55 | AR48: 0.26
A49: WOC Liquid Fund-Reg(G) | B49: 43481 | C49: 599.917 | D49: 591.9424 | E49: 1474.6805 | F49: 3.8906 | G49: 4.1091 | H49: 5.2745 | I49: 7.8688 | J49: 6.7753 | K49: 6.1809 | L49: 6.364 | M49: 6.0853 | N49: 6.6348 | O49: 6.7883 | P49: 6.5006 | Q49: 5.7899 | R49: 5.3892 | U49: 5.4726 | V49: =IF(F49="",0,IF(F49<=CB$3,4,IF(F49>=CB$5,1,IF(F49>=CB$4,2,3)))) -> 3 | W49: =IF(G49="",0,IF(G49<=CC$3,4,IF(G49>=CC$5,1,IF(G49>=CC$4,2,3)))) -> 4 | X49: =IF(H49="",0,IF(H49<=CD$3,4,IF(H49>=CD$5,1,IF(H49>=CD$4,2,3)))) -> 4 | Y49: =IF(I49="",0,IF(I49<=CE$3,4,IF(I49>=CE$5,1,IF(I49>=CE$4,2,3)))) -> 3 | Z49: =IF(J49="",0,IF(J49<=CF$3,4,IF(J49>=CF$5,1,IF(J49>=CF$4,2,3)))) -> 3 | AA49: =IF(K49="",0,IF(K49<=CG$3,4,IF(K49>=CG$5,1,IF(K49>=CG$4,2,3)))) -> 3 | AB49: =IF(L49="",0,IF(L49<=CH$3,4,IF(L49>=CH$5,1,IF(L49>=CH$4,2,3)))) -> 3 | AC49: =IF(M49="",0,IF(M49<=CI$3,4,IF(M49>=CI$5,1,IF(M49>=CI$4,2,3)))) -> 3 | ... AK49: =IF(U49="",0,IF(U49<=CQ$3,4,IF(U49>=CQ$5,1,IF(U49>=CQ$4,2,3)))) -> 4 | AL49: 95.5095 | AM49: 0.2589 | AN49: 4.2316 | AO49: 0.15 | AP49: 0.16 | AQ49: 7.29 | AR49: 0.31
V50: =IF(F50="",0,IF(F50<=CB$3,4,IF(F50>=CB$5,1,IF(F50>=CB$4,2,3)))) -> 0 | W50: =IF(G50="",0,IF(G50<=CC$3,4,IF(G50>=CC$5,1,IF(G50>=CC$4,2,3)))) -> 0 | X50: =IF(H50="",0,IF(H50<=CD$3,4,IF(H50>=CD$5,1,IF(H50>=CD$4,2,3)))) -> 0 | Y50: =IF(I50="",0,IF(I50<=CE$3,4,IF(I50>=CE$5,1,IF(I50>=CE$4,2,3)))) -> 0 | Z50: =IF(J50="",0,IF(J50<=CF$3,4,IF(J50>=CF$5,1,IF(J50>=CF$4,2,3)))) -> 0 | AA50: =IF(K50="",0,IF(K50<=CG$3,4,IF(K50>=CG$5,1,IF(K50>=CG$4,2,3)))) -> 0 | AB50: =IF(L50="",0,IF(L50<=CH$3,4,IF(L50>=CH$5,1,IF(L50>=CH$4,2,3)))) -> 0 | AC50: =IF(M50="",0,IF(M50<=CI$3,4,IF(M50>=CI$5,1,IF(M50>=CI$4,2,3)))) -> 0 | ... AK50: =IF(U50="",0,IF(U50<=CQ$3,4,IF(U50>=CQ$5,1,IF(U50>=CQ$4,2,3)))) -> 0
A51: Category Average (Weighted) | F51: =SUMPRODUCT($D12:$D50,F12:F50)/SUMIF(F12:F50,"<>"&"",$D12:$D50) -> 4.0035172 | G51: =SUMPRODUCT($D12:$D50,G12:G50)/SUMIF(G12:G50,"<>"&"",$D12:$D50) -> 4.3065344 | H51: =SUMPRODUCT($D12:$D50,H12:H50)/SUMIF(H12:H50,"<>"&"",$D12:$D50) -> 5.4171941 | I51: =SUMPRODUCT($D12:$D50,I12:I50)/SUMIF(I12:I50,"<>"&"",$D12:$D50) -> 7.9599094 | J51: =SUMPRODUCT($D12:$D50,J12:J50)/SUMIF(J12:J50,"<>"&"",$D12:$D50) -> 6.8154609 | K51: =SUMPRODUCT($D12:$D50,K12:K50)/SUMIF(K12:K50,"<>"&"",$D12:$D50) -> 6.2662544 | L51: =SUMPRODUCT($D12:$D50,L12:L50)/SUMIF(L12:L50,"<>"&"",$D12:$D50) -> 6.4296043 | M51: =SUMPRODUCT($D12:$D50,M12:M50)/SUMIF(M12:M50,"<>"&"",$D12:$D50) -> 6.1864692 | ... U51: =SUMPRODUCT($D12:$D50,U12:U50)/SUMIF(U12:U50,"<>"&"",$D12:$D50) -> 6.7419505
A52: Minimum | F52: =MIN(F12:F50) -> 3.3588 | G52: =MIN(G12:G50) -> 3.784 | H52: =MIN(H12:H50) -> 4.7917 | I52: =MIN(I12:I50) -> 6.0752 | J52: =MIN(J12:J50) -> 5.7646 | K52: =MIN(K12:K50) -> 5.6535 | L52: =MIN(L12:L50) -> 5.6642 | M52: =MIN(M12:M50) -> 5.7466 | ... U52: =MIN(U12:U50) -> 4.6964
A53: Maximum | F53: =MAX(F12:F50) -> 5.0205 | G53: =MAX(G12:G50) -> 5.0365 | H53: =MAX(H12:H50) -> 5.6588 | I53: =MAX(I12:I50) -> 8.2378 | J53: =MAX(J12:J50) -> 6.9432 | K53: =MAX(K12:K50) -> 6.3489 | L53: =MAX(L12:L50) -> 6.5242 | M53: =MAX(M12:M50) -> 6.2623 | ... U53: =MAX(U12:U50) -> 7.3682
A54: Median | F54: =MEDIAN(F12:F50) -> 4.0363 | G54: =MEDIAN(G12:G50) -> 4.3201 | H54: =MEDIAN(H12:H50) -> 5.40895 | I54: =MEDIAN(I12:I50) -> 7.8754 | J54: =MEDIAN(J12:J50) -> 6.7849 | K54: =MEDIAN(K12:K50) -> 6.2412 | L54: =MEDIAN(L12:L50) -> 6.3949 | M54: =MEDIAN(M12:M50) -> 6.1741 | ... U54: =MEDIAN(U12:U50) -> 6.8062
A55: Indices Performance
A56: CRISIL Liquid Debt Index* | B56: -- | E56: -- | F56: -- | G56: -- | H56: -- | I56: -- | J56: -- | K56: -- | L56: -- | M56: -- | N56: -- | O56: -- | P56: -- | Q56: -- | R56: -- | T56: -- | U56: --
A58: # : "In the Quartile System, the "performance range" of the entire category for a given time period, is divided into 4 parts. Schemes with returns in the top 25% of that range
A59: in the next 25% of the range have been ranked Quartile 2 and so on. Quartile 4 shows the schemes whose returns are in the bottom 25% of the range."

Sheet Ultra Short Duration Fund
A1: Main Page | E1: Data Source: ACEMF | CA1: Quartile code | CB1: 7 Days | CC1: 14 Days | CD1: 21 Days | CE1: 1 Month | CF1: 3 Month | CG1: 6 Months | CH1: YTD | CI1: 1 Year | CJ1: 2 Year | CK1: 3 Year | CL1: 4 Years | CM1: 5 Years | CN1: 7 Years | CO1: 10 Years | CP1: 15 Years | CQ1: Inception
CA2: 0 | CB2: =_xlfn.QUARTILE.INC(F$12:F$36,$CA2) -> -0.2086 | CC2: =_xlfn.QUARTILE.INC(G$12:G$36,$CA2) -> 0.9338 | CD2: =_xlfn.QUARTILE.INC(H$12:H$36,$CA2) -> 4.0494 | CE2: =_xlfn.QUARTILE.INC(I$12:I$36,$CA2) -> 6.1109 | CF2: =_xlfn.QUARTILE.INC(J$12:J$36,$CA2) -> 5.5056 | CG2: =_xlfn.QUARTILE.INC(K$12:K$36,$CA2) -> 4.7618 | CH2: =_xlfn.QUARTILE.INC(L$12:L$36,$CA2) -> 4.7596 | CI2: =_xlfn.QUARTILE.INC(M$12:M$36,$CA2) -> 5.1566 | ... CQ2: =_xlfn.QUARTILE.INC(U$12:U$36,$CA2) -> 4.366
CA3: 1 | CB3: =_xlfn.QUARTILE.INC(F$12:F$36,$CA3) -> 0.7619 | CC3: =_xlfn.QUARTILE.INC(G$12:G$36,$CA3) -> 1.7527 | CD3: =_xlfn.QUARTILE.INC(H$12:H$36,$CA3) -> 4.5985 | CE3: =_xlfn.QUARTILE.INC(I$12:I$36,$CA3) -> 6.8229 | CF3: =_xlfn.QUARTILE.INC(J$12:J$36,$CA3) -> 6.2555 | CG3: =_xlfn.QUARTILE.INC(K$12:K$36,$CA3) -> 5.4144 | CH3: =_xlfn.QUARTILE.INC(L$12:L$36,$CA3) -> 5.4638 | CI3: =_xlfn.QUARTILE.INC(M$12:M$36,$CA3) -> 5.7782 | ... CQ3: =_xlfn.QUARTILE.INC(U$12:U$36,$CA3) -> 5.7816
CA4: 2 | CB4: =_xlfn.QUARTILE.INC(F$12:F$36,$CA4) -> 1.3593 | CC4: =_xlfn.QUARTILE.INC(G$12:G$36,$CA4) -> 2.1436 | CD4: =_xlfn.QUARTILE.INC(H$12:H$36,$CA4) -> 5.0431 | CE4: =_xlfn.QUARTILE.INC(I$12:I$36,$CA4) -> 7.3106 | CF4: =_xlfn.QUARTILE.INC(J$12:J$36,$CA4) -> 6.4824 | CG4: =_xlfn.QUARTILE.INC(K$12:K$36,$CA4) -> 5.6395 | CH4: =_xlfn.QUARTILE.INC(L$12:L$36,$CA4) -> 5.6927 | CI4: =_xlfn.QUARTILE.INC(M$12:M$36,$CA4) -> 6.057 | ... CQ4: =_xlfn.QUARTILE.INC(U$12:U$36,$CA4) -> 6.2858
CA5: 3 | CB5: =_xlfn.QUARTILE.INC(F$12:F$36,$CA5) -> 1.7204 | CC5: =_xlfn.QUARTILE.INC(G$12:G$36,$CA5) -> 2.5455 | CD5: =_xlfn.QUARTILE.INC(H$12:H$36,$CA5) -> 5.2025 | CE5: =_xlfn.QUARTILE.INC(I$12:I$36,$CA5) -> 7.8864 | CF5: =_xlfn.QUARTILE.INC(J$12:J$36,$CA5) -> 6.6382 | CG5: =_xlfn.QUARTILE.INC(K$12:K$36,$CA5) -> 5.7666 | CH5: =_xlfn.QUARTILE.INC(L$12:L$36,$CA5) -> 5.7764 | CI5: =_xlfn.QUARTILE.INC(M$12:M$36,$CA5) -> 6.2249 | ... CQ5: =_xlfn.QUARTILE.INC(U$12:U$36,$CA5) -> 6.9595
CB6: =_xlfn.QUARTILE.INC(F$12:F$36,$CA6) -> -0.2086 | CC6: =_xlfn.QUARTILE.INC(G$12:G$36,$CA6) -> 0.9338 | CD6: =_xlfn.QUARTILE.INC(H$12:H$36,$CA6) -> 4.0494 | CE6: =_xlfn.QUARTILE.INC(I$12:I$36,$CA6) -> 6.1109 | CF6: =_xlfn.QUARTILE.INC(J$12:J$36,$CA6) -> 5.5056 | CG6: =_xlfn.QUARTILE.INC(K$12:K$36,$CA6) -> 4.7618 | CH6: =_xlfn.QUARTILE.INC(L$12:L$36,$CA6) -> 4.7596 | CI6: =_xlfn.QUARTILE.INC(M$12:M$36,$CA6) -> 5.1566 | ... CQ6: =_xlfn.QUARTILE.INC(U$12:U$36,$CA6) -> 4.366
A7: Fund Barometer - Ultra Short Duration Fund | CA7: 4 | CB7: =_xlfn.QUARTILE.INC(F$12:F$36,$CA7) -> 3.8506 | CC7: =_xlfn.QUARTILE.INC(G$12:G$36,$CA7) -> 3.4237 | CD7: =_xlfn.QUARTILE.INC(H$12:H$36,$CA7) -> 6.1256 | CE7: =_xlfn.QUARTILE.INC(I$12:I$36,$CA7) -> 8.2187 | CF7: =_xlfn.QUARTILE.INC(J$12:J$36,$CA7) -> 6.8894 | CG7: =_xlfn.QUARTILE.INC(K$12:K$36,$CA7) -> 5.951 | CH7: =_xlfn.QUARTILE.INC(L$12:L$36,$CA7) -> 6.0206 | CI7: =_xlfn.QUARTILE.INC(M$12:M$36,$CA7) -> 6.4532 | ... CQ7: =_xlfn.QUARTILE.INC(U$12:U$36,$CA7) -> 7.3877
A8: ='Low Duration Fund'!A8 -> (As on 30 Apr 2026) | B8: Value Information | F8: Simple Annualized (%) | M8: Compound Annualized (%) | U8: Since Inception | V8: Quartile | AL8: Credit Quality | AO8: Modified Duration (Years) | AP8: Average Maturity (Years) | AQ8: YTM | AR8: Expense Ratio(%)
A9: Scheme Name | B9: Launch Date | C9: Fund Size (Rs Crs) Feb26 | D9: Fund Size (Rs Crs) Mar26 | E9: Latest NAV | F9: 7 Days | G9: 14 Days | H9: 21 Days | I9: 1 Month | J9: 3 Months | K9: 6 Months | L9: YTD | M9: 1 Year | N9: 2 Years | O9: 3 Years | P9: 4 Years | Q9: 5 Years | R9: 7 Years | S9: 10 Years | T9: 15 Years | V9: 7 Days | W9: 14 Days | X9: 21 Days | Y9: 1 Month | Z9: 3 Months | AA9: 6 Months | AB9: YTD | AC9: 1 Year | AD9: 2 Years | AE9: 3 Years | AF9: 4 Years | AG9: 5 Years | AH9: 7 Years | AI9: 10 Years | AJ9: 15 Years | AK9: Since Inception | AL9: AA minus and Above | AM9: Below AA minus | AN9: Cash & Cash Equivalent
A10: To view Exit Loads of any Scheme in this group please click here
A11: Ultra Short Duration Fund
A12: Aditya Birla SL Savings Fund-Reg(G) | B12: 37727 | C12: 21466.7 | D12: 19347.833 | E12: 576.8383 | F12: 3.0155 | G12: 3.4237 | H12: 5.6835 | I12: 6.8229 | J12: 6.5167 | K12: 5.7633 | L12: 5.6767 | M12: 6.4532 | N12: 7.2044 | O12: 7.2852 | P12: 6.8934 | Q12: 6.3236 | R12: 6.5 | S12: 6.918 | T12: 7.7589 | U12: 7.3877 | V12: =IF(F12="",0,IF(F12<=CB$3,4,IF(F12>=CB$5,1,IF(F12>=CB$4,2,3)))) -> 1 | W12: =IF(G12="",0,IF(G12<=CC$3,4,IF(G12>=CC$5,1,IF(G12>=CC$4,2,3)))) -> 1 | X12: =IF(H12="",0,IF(H12<=CD$3,4,IF(H12>=CD$5,1,IF(H12>=CD$4,2,3)))) -> 1 | Y12: =IF(I12="",0,IF(I12<=CE$3,4,IF(I12>=CE$5,1,IF(I12>=CE$4,2,3)))) -> 4 | Z12: =IF(J12="",0,IF(J12<=CF$3,4,IF(J12>=CF$5,1,IF(J12>=CF$4,2,3)))) -> 2 | AA12: =IF(K12="",0,IF(K12<=CG$3,4,IF(K12>=CG$5,1,IF(K12>=CG$4,2,3)))) -> 2 | AB12: =IF(L12="",0,IF(L12<=CH$3,4,IF(L12>=CH$5,1,IF(L12>=CH$4,2,3)))) -> 3 | AC12: =IF(M12="",0,IF(M12<=CI$3,4,IF(M12>=CI$5,1,IF(M12>=CI$4,2,3)))) -> 1 | ... AK12: =IF(U12="",0,IF(U12<=CQ$3,4,IF(U12>=CQ$5,1,IF(U12>=CQ$4,2,3)))) -> 1 | AL12: 97.6146 | AM12: 0.3436 | AN12: 2.0418 | AO12: 0.49 | AP12: 0.59 | AQ12: 7.45 | AR12: 0.59
A13: Axis Ultra Short Duration Fund-Reg(G) | B13: 43353 | C13: 5823.8456 | D13: 3958.3034 | E13: 15.4257 | F13: 0.1352 | G13: 1.4543 | H13: 4.5867 | I13: 6.9948 | J13: 6.1547 | K13: 5.4101 | L13: 5.4249 | M13: 5.8483 | N13: 6.4922 | O13: 6.5601 | P13: 6.2305 | Q13: 5.6237 | R13: 5.6399 | U13: 5.8366 | V13: =IF(F13="",0,IF(F13<=CB$3,4,IF(F13>=CB$5,1,IF(F13>=CB$4,2,3)))) -> 4 | W13: =IF(G13="",0,IF(G13<=CC$3,4,IF(G13>=CC$5,1,IF(G13>=CC$4,2,3)))) -> 4 | X13: =IF(H13="",0,IF(H13<=CD$3,4,IF(H13>=CD$5,1,IF(H13>=CD$4,2,3)))) -> 4 | Y13: =IF(I13="",0,IF(I13<=CE$3,4,IF(I13>=CE$5,1,IF(I13>=CE$4,2,3)))) -> 3 | Z13: =IF(J13="",0,IF(J13<=CF$3,4,IF(J13>=CF$5,1,IF(J13>=CF$4,2,3)))) -> 4 | AA13: =IF(K13="",0,IF(K13<=CG$3,4,IF(K13>=CG$5,1,IF(K13>=CG$4,2,3)))) -> 4 | AB13: =IF(L13="",0,IF(L13<=CH$3,4,IF(L13>=CH$5,1,IF(L13>=CH$4,2,3)))) -> 4 | AC13: =IF(M13="",0,IF(M13<=CI$3,4,IF(M13>=CI$5,1,IF(M13>=CI$4,2,3)))) -> 3 | ... AK13: =IF(U13="",0,IF(U13<=CQ$3,4,IF(U13>=CQ$5,1,IF(U13>=CQ$4,2,3)))) -> 3 | AL13: 101.8145 | AM13: 0.4457 | AN13: -2.3303 | AO13: 0.4767 | AP13: 0.5315 | AQ13: 8.29 | AR13: 1.2
A14: Bandhan Ultra Short Duration Fund-Reg(G) | B14: 43299 | C14: 3732.3631 | D14: 3527.7692 | E14: 15.9886 | F14: 0.8154 | G14: 2.0235 | H14: 5.5181 | I14: 7.776 | J14: 6.6988 | K14: 5.8385 | L14: 5.8815 | M14: 6.2274 | N14: 6.8771 | O14: 6.967 | P14: 6.626 | Q14: 5.9819 | R14: 5.9817 | U14: 6.2102 | V14: =IF(F14="",0,IF(F14<=CB$3,4,IF(F14>=CB$5,1,IF(F14>=CB$4,2,3)))) -> 3 | W14: =IF(G14="",0,IF(G14<=CC$3,4,IF(G14>=CC$5,1,IF(G14>=CC$4,2,3)))) -> 3 | X14: =IF(H14="",0,IF(H14<=CD$3,4,IF(H14>=CD$5,1,IF(H14>=CD$4,2,3)))) -> 1 | Y14: =IF(I14="",0,IF(I14<=CE$3,4,IF(I14>=CE$5,1,IF(I14>=CE$4,2,3)))) -> 2 | Z14: =IF(J14="",0,IF(J14<=CF$3,4,IF(J14>=CF$5,1,IF(J14>=CF$4,2,3)))) -> 1 | AA14: =IF(K14="",0,IF(K14<=CG$3,4,IF(K14>=CG$5,1,IF(K14>=CG$4,2,3)))) -> 1 | AB14: =IF(L14="",0,IF(L14<=CH$3,4,IF(L14>=CH$5,1,IF(L14>=CH$4,2,3)))) -> 1 | AC14: =IF(M14="",0,IF(M14<=CI$3,4,IF(M14>=CI$5,1,IF(M14>=CI$4,2,3)))) -> 1 | ... AK14: =IF(U14="",0,IF(U14<=CQ$3,4,IF(U14>=CQ$5,1,IF(U14>=CQ$4,2,3)))) -> 3 | AL14: 97.7459 | AM14: 0.3727 | AN14: 1.8519 | AO14: 0.4301 | AP14: 0.5616 | AQ14: 7.59 | AR14: 0.47
A15: Bank of India Ultra Short Duration Fund-Reg(G) | B15: 39645 | C15: 165.1771 | D15: 116.6009 | E15: 3312.1267 | F15: -0.0701 | G15: 1.396 | H15: 4.0669 | I15: 6.9241 | J15: 6.6581 | K15: 5.6284 | L15: 5.7458 | M15: 5.8546 | N15: 6.3919 | O15: 6.3575 | P15: 6.103 | Q15: 5.542 | R15: 5.5194 | S15: 6.2759 | T15: 7.1316 | U15: 6.9595 | V15: =IF(F15="",0,IF(F15<=CB$3,4,IF(F15>=CB$5,1,IF(F15>=CB$4,2,3)))) -> 4 | W15: =IF(G15="",0,IF(G15<=CC$3,4,IF(G15>=CC$5,1,IF(G15>=CC$4,2,3)))) -> 4 | X15: =IF(H15="",0,IF(H15<=CD$3,4,IF(H15>=CD$5,1,IF(H15>=CD$4,2,3)))) -> 4 | Y15: =IF(I15="",0,IF(I15<=CE$3,4,IF(I15>=CE$5,1,IF(I15>=CE$4,2,3)))) -> 3 | Z15: =IF(J15="",0,IF(J15<=CF$3,4,IF(J15>=CF$5,1,IF(J15>=CF$4,2,3)))) -> 1 | AA15: =IF(K15="",0,IF(K15<=CG$3,4,IF(K15>=CG$5,1,IF(K15>=CG$4,2,3)))) -> 3 | AB15: =IF(L15="",0,IF(L15<=CH$3,4,IF(L15>=CH$5,1,IF(L15>=CH$4,2,3)))) -> 2 | AC15: =IF(M15="",0,IF(M15<=CI$3,4,IF(M15>=CI$5,1,IF(M15>=CI$4,2,3)))) -> 3 | ... AK15: =IF(U15="",0,IF(U15<=CQ$3,4,IF(U15>=CQ$5,1,IF(U15>=CQ$4,2,3)))) -> 1 | AL15: 112.5716 | AM15: 0.4183 | AN15: -12.9899 | AO15: 0.57 | AP15: 0.51 | AQ15: 7.2 | AR15: 0.85
A16: Baroda BNP Paribas Ultra Short Duration Fund-Reg(G) | B16: 43252 | C16: 669.6414 | D16: 705.1557 | E16: 1620.7527 | F16: 0.9737 | G16: 2.0887 | H16: 5.0431 | I16: 8.2187 | J16: 6.8894 | K16: 5.8897 | L16: 5.9426 | M16: 6.2955 | N16: 6.955 | O16: 7.0595 | P16: 6.7965 | Q16: 6.1911 | R16: 6.043 | U16: 6.2886 | V16: =IF(F16="",0,IF(F16<=CB$3,4,IF(F16>=CB$5,1,IF(F16>=CB$4,2,3)))) -> 3 | W16: =IF(G16="",0,IF(G16<=CC$3,4,IF(G16>=CC$5,1,IF(G16>=CC$4,2,3)))) -> 3 | X16: =IF(H16="",0,IF(H16<=CD$3,4,IF(H16>=CD$5,1,IF(H16>=CD$4,2,3)))) -> 2 | Y16: =IF(I16="",0,IF(I16<=CE$3,4,IF(I16>=CE$5,1,IF(I16>=CE$4,2,3)))) -> 1 | Z16: =IF(J16="",0,IF(J16<=CF$3,4,IF(J16>=CF$5,1,IF(J16>=CF$4,2,3)))) -> 1 | AA16: =IF(K16="",0,IF(K16<=CG$3,4,IF(K16>=CG$5,1,IF(K16>=CG$4,2,3)))) -> 1 | AB16: =IF(L16="",0,IF(L16<=CH$3,4,IF(L16>=CH$5,1,IF(L16>=CH$4,2,3)))) -> 1 | AC16: =IF(M16="",0,IF(M16<=CI$3,4,IF(M16>=CI$5,1,IF(M16>=CI$4,2,3)))) -> 1 | ... AK16: =IF(U16="",0,IF(U16<=CQ$3,4,IF(U16>=CQ$5,1,IF(U16>=CQ$4,2,3)))) -> 2 | AL16: 90.8673 | AM16: 0.4772 | AN16: 8.6555 | AO16: 0.47 | AP16: 0.52 | AQ16: 7.58 | AR16: 0.47
A17: Canara Rob Ultra Short Term Fund-Reg(G) | B17: 39640 | C17: 563.1334 | D17: 483.2529 | E17: 3976.8285 | F17: 0.7694 | G17: 1.7404 | H17: 5.0359 | I17: 7.9785 | J17: 6.6545 | K17: 5.4644 | L17: 5.6078 | M17: 5.7782 | N17: 6.4058 | O17: 6.438 | P17: 6.0873 | Q17: 5.4207 | R17: 5.2671 | S17: 5.5444 | T17: 6.732 | U17: 6.7573 | V17: =IF(F17="",0,IF(F17<=CB$3,4,IF(F17>=CB$5,1,IF(F17>=CB$4,2,3)))) -> 3 | W17: =IF(G17="",0,IF(G17<=CC$3,4,IF(G17>=CC$5,1,IF(G17>=CC$4,2,3)))) -> 4 | X17: =IF(H17="",0,IF(H17<=CD$3,4,IF(H17>=CD$5,1,IF(H17>=CD$4,2,3)))) -> 3 | Y17: =IF(I17="",0,IF(I17<=CE$3,4,IF(I17>=CE$5,1,IF(I17>=CE$4,2,3)))) -> 1 | Z17: =IF(J17="",0,IF(J17<=CF$3,4,IF(J17>=CF$5,1,IF(J17>=CF$4,2,3)))) -> 1 | AA17: =IF(K17="",0,IF(K17<=CG$3,4,IF(K17>=CG$5,1,IF(K17>=CG$4,2,3)))) -> 3 | AB17: =IF(L17="",0,IF(L17<=CH$3,4,IF(L17>=CH$5,1,IF(L17>=CH$4,2,3)))) -> 3 | AC17: =IF(M17="",0,IF(M17<=CI$3,4,IF(M17>=CI$5,1,IF(M17>=CI$4,2,3)))) -> 4 | ... AK17: =IF(U17="",0,IF(U17<=CQ$3,4,IF(U17>=CQ$5,1,IF(U17>=CQ$4,2,3)))) -> 2 | AL17: 87.4808 | AM17: 0.37 | AN17: 12.1493 | AO17: 0.4 | AP17: 0.5 | AQ17: 7.43 | AR17: 0.97
A18: DSP Ultra Short Fund-Reg(G) | B18: 38929 | C18: 3714.4634 | D18: 3559.8134 | E18: 3567.4437 | F18: 0.082 | G18: 1.2967 | H18: 6.1256 | I18: 8.1498 | J18: 6.5452 | K18: 5.5018 | L18: 5.609 | M18: 5.8396 | N18: 6.5631 | O18: 6.6468 | P18: 6.2785 | Q18: 5.6221 | R18: 5.5172 | S18: 5.7089 | T18: 6.665 | U18: 6.6476 | V18: =IF(F18="",0,IF(F18<=CB$3,4,IF(F18>=CB$5,1,IF(F18>=CB$4,2,3)))) -> 4 | W18: =IF(G18="",0,IF(G18<=CC$3,4,IF(G18>=CC$5,1,IF(G18>=CC$4,2,3)))) -> 4 | X18: =IF(H18="",0,IF(H18<=CD$3,4,IF(H18>=CD$5,1,IF(H18>=CD$4,2,3)))) -> 1 | Y18: =IF(I18="",0,IF(I18<=CE$3,4,IF(I18>=CE$5,1,IF(I18>=CE$4,2,3)))) -> 1 | Z18: =IF(J18="",0,IF(J18<=CF$3,4,IF(J18>=CF$5,1,IF(J18>=CF$4,2,3)))) -> 2 | AA18: =IF(K18="",0,IF(K18<=CG$3,4,IF(K18>=CG$5,1,IF(K18>=CG$4,2,3)))) -> 3 | AB18: =IF(L18="",0,IF(L18<=CH$3,4,IF(L18>=CH$5,1,IF(L18>=CH$4,2,3)))) -> 3 | AC18: =IF(M18="",0,IF(M18<=CI$3,4,IF(M18>=CI$5,1,IF(M18>=CI$4,2,3)))) -> 3 | ... AK18: =IF(U18="",0,IF(U18<=CQ$3,4,IF(U18>=CQ$5,1,IF(U18>=CQ$4,2,3)))) -> 2 | AL18: 96.7242 | AM18: 0.3151 | AN18: 2.8373 | AO18: 0.46 | AP18: 0.69 | AQ18: 7.71 | AR18: 1.02
A19: Franklin India Ultra Short Duration Fund-Reg(G) | B19: 45533 | C19: 282.9518 | D19: 260.0093 | E19: 11.1585 | F19: 2.5714 | G19: 2.7131 | H19: 5.2025 | I19: 6.4293 | J19: 6.2555 | K19: 5.6395 | L19: 5.7266 | M19: 6.2249 | U19: 6.7904 | V19: =IF(F19="",0,IF(F19<=CB$3,4,IF(F19>=CB$5,1,IF(F19>=CB$4,2,3)))) -> 1 | W19: =IF(G19="",0,IF(G19<=CC$3,4,IF(G19>=CC$5,1,IF(G19>=CC$4,2,3)))) -> 1 | X19: =IF(H19="",0,IF(H19<=CD$3,4,IF(H19>=CD$5,1,IF(H19>=CD$4,2,3)))) -> 1 | Y19: =IF(I19="",0,IF(I19<=CE$3,4,IF(I19>=CE$5,1,IF(I19>=CE$4,2,3)))) -> 4 | Z19: =IF(J19="",0,IF(J19<=CF$3,4,IF(J19>=CF$5,1,IF(J19>=CF$4,2,3)))) -> 4 | AA19: =IF(K19="",0,IF(K19<=CG$3,4,IF(K19>=CG$5,1,IF(K19>=CG$4,2,3)))) -> 2 | AB19: =IF(L19="",0,IF(L19<=CH$3,4,IF(L19>=CH$5,1,IF(L19>=CH$4,2,3)))) -> 2 | AC19: =IF(M19="",0,IF(M19<=CI$3,4,IF(M19>=CI$5,1,IF(M19>=CI$4,2,3)))) -> 1 | ... AK19: =IF(U19="",0,IF(U19<=CQ$3,4,IF(U19>=CQ$5,1,IF(U19>=CQ$4,2,3)))) -> 2 | AL19: 91.2402 | AM19: 0.2881 | AN19: 8.4717 | AO19: 0.45 | AP19: 0.89 | AQ19: 7.46 | AR19: 0.71
A20: HDFC Ultra Short Term Fund-Reg(G) | B20: 43367 | C20: 17170.584 | D20: 16037.1 | E20: 15.8959 | F20: 1.6735 | G20: 2.2489 | H20: 4.8464 | I20: 6.6519 | J20: 6.3486 | K20: 5.5293 | L20: 5.4638 | M20: 6.0901 | N20: 6.8097 | O20: 6.92 | P20: 6.5891 | Q20: 5.9794 | R20: 6.0786 | U20: 6.2858 | V20: =IF(F20="",0,IF(F20<=CB$3,4,IF(F20>=CB$5,1,IF(F20>=CB$4,2,3)))) -> 2 | W20: =IF(G20="",0,IF(G20<=CC$3,4,IF(G20>=CC$5,1,IF(G20>=CC$4,2,3)))) -> 2 | X20: =IF(H20="",0,IF(H20<=CD$3,4,IF(H20>=CD$5,1,IF(H20>=CD$4,2,3)))) -> 3 | Y20: =IF(I20="",0,IF(I20<=CE$3,4,IF(I20>=CE$5,1,IF(I20>=CE$4,2,3)))) -> 4 | Z20: =IF(J20="",0,IF(J20<=CF$3,4,IF(J20>=CF$5,1,IF(J20>=CF$4,2,3)))) -> 3 | AA20: =IF(K20="",0,IF(K20<=CG$3,4,IF(K20>=CG$5,1,IF(K20>=CG$4,2,3)))) -> 3 | AB20: =IF(L20="",0,IF(L20<=CH$3,4,IF(L20>=CH$5,1,IF(L20>=CH$4,2,3)))) -> 4 | AC20: =IF(M20="",0,IF(M20<=CI$3,4,IF(M20>=CI$5,1,IF(M20>=CI$4,2,3)))) -> 2 | ... AK20: =IF(U20="",0,IF(U20<=CQ$3,4,IF(U20>=CQ$5,1,IF(U20>=CQ$4,2,3)))) -> 2 | AL20: 99.1041 | AM20: 0.3134 | AN20: 0.5825 | AO20: 0.4637 | AP20: 0.8866 | AQ20: 7.8 | AR20: 0.73
A21: HSBC Ultra Short Duration Fund-Reg(G) | B21: 43859 | C21: 2873.6287 | D21: 2470.0058 | E21: 1422.726 | F21: 1.0748 | G21: 2.0353 | H21: 4.6872 | I21: 7.5081 | J21: 6.8693 | K21: 5.951 | L21: 6.0206 | M21: 6.2758 | N21: 6.9215 | O21: 6.9927 | P21: 6.6685 | Q21: 6.0362 | U21: 5.7988 | V21: =IF(F21="",0,IF(F21<=CB$3,4,IF(F21>=CB$5,1,IF(F21>=CB$4,2,3)))) -> 3 | W21: =IF(G21="",0,IF(G21<=CC$3,4,IF(G21>=CC$5,1,IF(G21>=CC$4,2,3)))) -> 3 | X21: =IF(H21="",0,IF(H21<=CD$3,4,IF(H21>=CD$5,1,IF(H21>=CD$4,2,3)))) -> 3 | Y21: =IF(I21="",0,IF(I21<=CE$3,4,IF(I21>=CE$5,1,IF(I21>=CE$4,2,3)))) -> 2 | Z21: =IF(J21="",0,IF(J21<=CF$3,4,IF(J21>=CF$5,1,IF(J21>=CF$4,2,3)))) -> 1 | AA21: =IF(K21="",0,IF(K21<=CG$3,4,IF(K21>=CG$5,1,IF(K21>=CG$4,2,3)))) -> 1 | AB21: =IF(L21="",0,IF(L21<=CH$3,4,IF(L21>=CH$5,1,IF(L21>=CH$4,2,3)))) -> 1 | AC21: =IF(M21="",0,IF(M21<=CI$3,4,IF(M21>=CI$5,1,IF(M21>=CI$4,2,3)))) -> 1 | ... AK21: =IF(U21="",0,IF(U21<=CQ$3,4,IF(U21>=CQ$5,1,IF(U21>=CQ$4,2,3)))) -> 3 | AL21: 111.0932 | AM21: 0.3591 | AN21: -11.4889 | AO21: 0.4683 | AP21: 0.5 | AQ21: 7.4 | AR21: 0.33
A22: ICICI Pru Ultra Short Term Fund Fund(G) | B22: 40666 | C22: 16815.773 | D22: 13619.405 | E22: 29.1117 | F22: 1.5229 | G22: 2.5459 | H22: 4.9156 | I22: 6.6215 | J22: 6.4824 | K22: 5.7609 | L22: 5.7552 | M22: 6.3309 | N22: 6.9134 | O22: 6.9999 | P22: 6.6691 | Q22: 6.0992 | R22: 6.3003 | S22: 6.7746 | U22: 7.3822 | V22: =IF(F22="",0,IF(F22<=CB$3,4,IF(F22>=CB$5,1,IF(F22>=CB$4,2,3)))) -> 2 | W22: =IF(G22="",0,IF(G22<=CC$3,4,IF(G22>=CC$5,1,IF(G22>=CC$4,2,3)))) -> 1 | X22: =IF(H22="",0,IF(H22<=CD$3,4,IF(H22>=CD$5,1,IF(H22>=CD$4,2,3)))) -> 3 | Y22: =IF(I22="",0,IF(I22<=CE$3,4,IF(I22>=CE$5,1,IF(I22>=CE$4,2,3)))) -> 4 | Z22: =IF(J22="",0,IF(J22<=CF$3,4,IF(J22>=CF$5,1,IF(J22>=CF$4,2,3)))) -> 2 | AA22: =IF(K22="",0,IF(K22<=CG$3,4,IF(K22>=CG$5,1,IF(K22>=CG$4,2,3)))) -> 2 | AB22: =IF(L22="",0,IF(L22<=CH$3,4,IF(L22>=CH$5,1,IF(L22>=CH$4,2,3)))) -> 2 | AC22: =IF(M22="",0,IF(M22<=CI$3,4,IF(M22>=CI$5,1,IF(M22>=CI$4,2,3)))) -> 1 | ... AK22: =IF(U22="",0,IF(U22<=CQ$3,4,IF(U22>=CQ$5,1,IF(U22>=CQ$4,2,3)))) -> 1 | AL22: 95.5532 | AM22: 0.3552 | AN22: 4.0916 | AO22: 0.46 | AP22: 0.58 | AQ22: 7.73 | AR22: 0.77
A23: Invesco India Ultra Short Duration Fund-Reg(G) | B23: 40542 | C23: 1292.1235 | D23: 963.4744 | E23: 2829.4948 | F23: 1.0106 | G23: 2.1436 | H23: 5.1647 | I23: 7.8864 | J23: 6.5455 | K23: 5.6932 | L23: 5.7936 | M23: 6.057 | N23: 6.737 | O23: 6.8533 | P23: 6.4444 | Q23: 5.7774 | R23: 5.7074 | S23: 6.2907 | T23: 6.9983 | U23: 7.0143 | V23: =IF(F23="",0,IF(F23<=CB$3,4,IF(F23>=CB$5,1,IF(F23>=CB$4,2,3)))) -> 3 | W23: =IF(G23="",0,IF(G23<=CC$3,4,IF(G23>=CC$5,1,IF(G23>=CC$4,2,3)))) -> 2 | X23: =IF(H23="",0,IF(H23<=CD$3,4,IF(H23>=CD$5,1,IF(H23>=CD$4,2,3)))) -> 2 | Y23: =IF(I23="",0,IF(I23<=CE$3,4,IF(I23>=CE$5,1,IF(I23>=CE$4,2,3)))) -> 1 | Z23: =IF(J23="",0,IF(J23<=CF$3,4,IF(J23>=CF$5,1,IF(J23>=CF$4,2,3)))) -> 2 | AA23: =IF(K23="",0,IF(K23<=CG$3,4,IF(K23>=CG$5,1,IF(K23>=CG$4,2,3)))) -> 2 | AB23: =IF(L23="",0,IF(L23<=CH$3,4,IF(L23>=CH$5,1,IF(L23>=CH$4,2,3)))) -> 1 | AC23: =IF(M23="",0,IF(M23<=CI$3,4,IF(M23>=CI$5,1,IF(M23>=CI$4,2,3)))) -> 2 | ... AK23: =IF(U23="",0,IF(U23<=CQ$3,4,IF(U23>=CQ$5,1,IF(U23>=CQ$4,2,3)))) -> 1 | AL23: 98.407 | AM23: 0.4183 | AN23: 1.1746 | AO23: 0.4822 | AP23: 0.5041 | AQ23: 7.66 | AR23: 0.79
A24: ITI Ultra Short Duration Fund-Reg(G) | B24: 44321 | C24: 195.1743 | D24: 221.899 | E24: 1293.1231 | F24: 1.9201 | G24: 2.5455 | H24: 5.1692 | I24: 7.706 | J24: 6.2113 | K24: 5.4144 | L24: 5.5285 | M24: 5.653 | N24: 6.1938 | O24: 6.2668 | P24: 5.9348 | U24: 5.2875 | V24: =IF(F24="",0,IF(F24<=CB$3,4,IF(F24>=CB$5,1,IF(F24>=CB$4,2,3)))) -> 1 | W24: =IF(G24="",0,IF(G24<=CC$3,4,IF(G24>=CC$5,1,IF(G24>=CC$4,2,3)))) -> 1 | X24: =IF(H24="",0,IF(H24<=CD$3,4,IF(H24>=CD$5,1,IF(H24>=CD$4,2,3)))) -> 2 | Y24: =IF(I24="",0,IF(I24<=CE$3,4,IF(I24>=CE$5,1,IF(I24>=CE$4,2,3)))) -> 2 | Z24: =IF(J24="",0,IF(J24<=CF$3,4,IF(J24>=CF$5,1,IF(J24>=CF$4,2,3)))) -> 4 | AA24: =IF(K24="",0,IF(K24<=CG$3,4,IF(K24>=CG$5,1,IF(K24>=CG$4,2,3)))) -> 4 | AB24: =IF(L24="",0,IF(L24<=CH$3,4,IF(L24>=CH$5,1,IF(L24>=CH$4,2,3)))) -> 3 | AC24: =IF(M24="",0,IF(M24<=CI$3,4,IF(M24>=CI$5,1,IF(M24>=CI$4,2,3)))) -> 4 | ... AK24: =IF(U24="",0,IF(U24<=CQ$3,4,IF(U24>=CQ$5,1,IF(U24>=CQ$4,2,3)))) -> 4 | AL24: 96.0656 | AM24: 0.2955 | AN24: 3.6389 | AO24: 0.3726 | AP24: 0.3808 | AQ24: 7.27 | AR24: 0.92
A25: Kotak Savings Fund(G) | B25: 38212 | C25: 16105.32 | D25: 14989.419 | E25: 44.9906 | F25: 3.8506 | G25: 3.3189 | H25: 5.4954 | I25: 6.1109 | J25: 6.3762 | K25: 5.6897 | L25: 5.7196 | M25: 6.0919 | N25: 6.7211 | O25: 6.7939 | P25: 6.4764 | Q25: 5.8651 | R25: 5.9037 | S25: 6.3519 | T25: 7.2642 | U25: 7.1672 | V25: =IF(F25="",0,IF(F25<=CB$3,4,IF(F25>=CB$5,1,IF(F25>=CB$4,2,3)))) -> 1 | W25: =IF(G25="",0,IF(G25<=CC$3,4,IF(G25>=CC$5,1,IF(G25>=CC$4,2,3)))) -> 1 | X25: =IF(H25="",0,IF(H25<=CD$3,4,IF(H25>=CD$5,1,IF(H25>=CD$4,2,3)))) -> 1 | Y25: =IF(I25="",0,IF(I25<=CE$3,4,IF(I25>=CE$5,1,IF(I25>=CE$4,2,3)))) -> 4 | Z25: =IF(J25="",0,IF(J25<=CF$3,4,IF(J25>=CF$5,1,IF(J25>=CF$4,2,3)))) -> 3 | AA25: =IF(K25="",0,IF(K25<=CG$3,4,IF(K25>=CG$5,1,IF(K25>=CG$4,2,3)))) -> 2 | AB25: =IF(L25="",0,IF(L25<=CH$3,4,IF(L25>=CH$5,1,IF(L25>=CH$4,2,3)))) -> 2 | AC25: =IF(M25="",0,IF(M25<=CI$3,4,IF(M25>=CI$5,1,IF(M25>=CI$4,2,3)))) -> 2 | ... AK25: =IF(U25="",0,IF(U25<=CQ$3,4,IF(U25>=CQ$5,1,IF(U25>=CQ$4,2,3)))) -> 1 | AL25: 99.6463 | AM25: 0.3073 | AN25: 0.0464 | AO25: 0.48 | AP25: 0.55 | AQ25: 7.53 | AR25: 0.82
A26: LIC MF Ultra Short Duration Fund-Reg(G) | B26: 43796 | C26: 230.3436 | D26: 186.5843 | E26: 1382.8268 | F26: 1.3593 | G26: 2.3502 | H26: 4.5985 | I26: 7.3379 | J26: 6.3214 | K26: 5.3865 | L26: 5.5187 | M26: 5.7356 | N26: 6.3812 | O26: 6.3461 | P26: 6.0448 | Q26: 5.48 | U26: 5.1723 | V26: =IF(F26="",0,IF(F26<=CB$3,4,IF(F26>=CB$5,1,IF(F26>=CB$4,2,3)))) -> 2 | W26: =IF(G26="",0,IF(G26<=CC$3,4,IF(G26>=CC$5,1,IF(G26>=CC$4,2,3)))) -> 2 | X26: =IF(H26="",0,IF(H26<=CD$3,4,IF(H26>=CD$5,1,IF(H26>=CD$4,2,3)))) -> 4 | Y26: =IF(I26="",0,IF(I26<=CE$3,4,IF(I26>=CE$5,1,IF(I26>=CE$4,2,3)))) -> 2 | Z26: =IF(J26="",0,IF(J26<=CF$3,4,IF(J26>=CF$5,1,IF(J26>=CF$4,2,3)))) -> 3 | AA26: =IF(K26="",0,IF(K26<=CG$3,4,IF(K26>=CG$5,1,IF(K26>=CG$4,2,3)))) -> 4 | AB26: =IF(L26="",0,IF(L26<=CH$3,4,IF(L26>=CH$5,1,IF(L26>=CH$4,2,3)))) -> 3 | AC26: =IF(M26="",0,IF(M26<=CI$3,4,IF(M26>=CI$5,1,IF(M26>=CI$4,2,3)))) -> 4 | ... AK26: =IF(U26="",0,IF(U26<=CQ$3,4,IF(U26>=CQ$5,1,IF(U26>=CQ$4,2,3)))) -> 4 | AL26: 110.4238 | AM26: 0.4407 | AN26: -10.8645 | AO26: 0.4634 | AP26: 0.4634 | AQ26: 7.49 | AR26: 1.22
A27: Mahindra Manulife Ultra Short Duration Fund-Reg(G) | B27: 43755 | C27: 217.0128 | D27: 193.7116 | E27: 1444.224 | F27: 1.4988 | G27: 2.6864 | H27: 5.5042 | I27: 8.1234 | J27: 6.8832 | K27: 5.8212 | L27: 5.9033 | M27: 6.1374 | N27: 6.7929 | O27: 6.8733 | P27: 6.5326 | Q27: 5.8993 | U27: 5.7816 | V27: =IF(F27="",0,IF(F27<=CB$3,4,IF(F27>=CB$5,1,IF(F27>=CB$4,2,3)))) -> 2 | W27: =IF(G27="",0,IF(G27<=CC$3,4,IF(G27>=CC$5,1,IF(G27>=CC$4,2,3)))) -> 1 | X27: =IF(H27="",0,IF(H27<=CD$3,4,IF(H27>=CD$5,1,IF(H27>=CD$4,2,3)))) -> 1 | Y27: =IF(I27="",0,IF(I27<=CE$3,4,IF(I27>=CE$5,1,IF(I27>=CE$4,2,3)))) -> 1 | Z27: =IF(J27="",0,IF(J27<=CF$3,4,IF(J27>=CF$5,1,IF(J27>=CF$4,2,3)))) -> 1 | AA27: =IF(K27="",0,IF(K27<=CG$3,4,IF(K27>=CG$5,1,IF(K27>=CG$4,2,3)))) -> 1 | AB27: =IF(L27="",0,IF(L27<=CH$3,4,IF(L27>=CH$5,1,IF(L27>=CH$4,2,3)))) -> 1 | AC27: =IF(M27="",0,IF(M27<=CI$3,4,IF(M27>=CI$5,1,IF(M27>=CI$4,2,3)))) -> 2 | ... AK27: =IF(U27="",0,IF(U27<=CQ$3,4,IF(U27>=CQ$5,1,IF(U27>=CQ$4,2,3)))) -> 4 | AL27: 94.1198 | AM27: 0.3484 | AN27: 5.5318 | AO27: 0.36 | AP27: 0.3907 | AQ27: 7.6 | AR27: 0.7
A28: Mirae Asset Ultra Short Duration Fund-Reg(G) | B28: 44111 | C28: 1809.3093 | D28: 1640.3889 | E28: 1375.3422 | F28: 1.3629 | G28: 2.4224 | H28: 5.1402 | I28: 8.0968 | J28: 6.6382 | K28: 5.8373 | L28: 5.7764 | M28: 6.3631 | N28: 7.0713 | O28: 7.1555 | P28: 6.8021 | Q28: 6.1677 | U28: 5.8947 | V28: =IF(F28="",0,IF(F28<=CB$3,4,IF(F28>=CB$5,1,IF(F28>=CB$4,2,3)))) -> 2 | W28: =IF(G28="",0,IF(G28<=CC$3,4,IF(G28>=CC$5,1,IF(G28>=CC$4,2,3)))) -> 2 | X28: =IF(H28="",0,IF(H28<=CD$3,4,IF(H28>=CD$5,1,IF(H28>=CD$4,2,3)))) -> 2 | Y28: =IF(I28="",0,IF(I28<=CE$3,4,IF(I28>=CE$5,1,IF(I28>=CE$4,2,3)))) -> 1 | Z28: =IF(J28="",0,IF(J28<=CF$3,4,IF(J28>=CF$5,1,IF(J28>=CF$4,2,3)))) -> 1 | AA28: =IF(K28="",0,IF(K28<=CG$3,4,IF(K28>=CG$5,1,IF(K28>=CG$4,2,3)))) -> 1 | AB28: =IF(L28="",0,IF(L28<=CH$3,4,IF(L28>=CH$5,1,IF(L28>=CH$4,2,3)))) -> 1 | AC28: =IF(M28="",0,IF(M28<=CI$3,4,IF(M28>=CI$5,1,IF(M28>=CI$4,2,3)))) -> 1 | ... AK28: =IF(U28="",0,IF(U28<=CQ$3,4,IF(U28>=CQ$5,1,IF(U28>=CQ$4,2,3)))) -> 3 | AL28: 91.7769 | AM28: 0.351 | AN28: 7.8721 | AO28: 0.47 | AP28: 0.5144 | AQ28: 7.44 | AR28: 0.44
A29: Motilal Oswal Ultra Short Term Fund-Reg(G) | B29: 41523 | C29: 440.9888 | D29: 411.0435 | E29: 17.1735 | F29: 1.9439 | G29: 2.5529 | H29: 4.4951 | I29: 6.8546 | J29: 5.9813 | K29: 5.0485 | L29: 5.1421 | M29: 5.1589 | N29: 5.5605 | O29: 5.7027 | P29: 5.4034 | Q29: 4.8314 | R29: 4.7518 | S29: 3.6297 | U29: 4.366 | V29: =IF(F29="",0,IF(F29<=CB$3,4,IF(F29>=CB$5,1,IF(F29>=CB$4,2,3)))) -> 1 | W29: =IF(G29="",0,IF(G29<=CC$3,4,IF(G29>=CC$5,1,IF(G29>=CC$4,2,3)))) -> 1 | X29: =IF(H29="",0,IF(H29<=CD$3,4,IF(H29>=CD$5,1,IF(H29>=CD$4,2,3)))) -> 4 | Y29: =IF(I29="",0,IF(I29<=CE$3,4,IF(I29>=CE$5,1,IF(I29>=CE$4,2,3)))) -> 3 | Z29: =IF(J29="",0,IF(J29<=CF$3,4,IF(J29>=CF$5,1,IF(J29>=CF$4,2,3)))) -> 4 | AA29: =IF(K29="",0,IF(K29<=CG$3,4,IF(K29>=CG$5,1,IF(K29>=CG$4,2,3)))) -> 4 | AB29: =IF(L29="",0,IF(L29<=CH$3,4,IF(L29>=CH$5,1,IF(L29>=CH$4,2,3)))) -> 4 | AC29: =IF(M29="",0,IF(M29<=CI$3,4,IF(M29>=CI$5,1,IF(M29>=CI$4,2,3)))) -> 4 | ... AK29: =IF(U29="",0,IF(U29<=CQ$3,4,IF(U29>=CQ$5,1,IF(U29>=CQ$4,2,3)))) -> 4 | AL29: 95.5086 | AM29: 0.3864 | AN29: 4.105 | AO29: 0.25 | AP29: 0.27 | AQ29: 6.92 | AR29: 1
A30: Nippon India Ultra Short Duration Fund(G) | B30: 37231 | C30: 10671.709 | D30: 9511.5089 | E30: 4229.6246 | F30: 1.9498 | G30: 2.4438 | H30: 5.0968 | I30: 7.3106 | J30: 6.5449 | K30: 5.8185 | L30: 5.8851 | M30: 6.1466 | N30: 6.7437 | O30: 6.7922 | P30: 6.4728 | Q30: 6.6993 | R30: 5.5985 | S30: 5.8016 | T30: 6.6875 | U30: 6.0849 | V30: =IF(F30="",0,IF(F30<=CB$3,4,IF(F30>=CB$5,1,IF(F30>=CB$4,2,3)))) -> 1 | W30: =IF(G30="",0,IF(G30<=CC$3,4,IF(G30>=CC$5,1,IF(G30>=CC$4,2,3)))) -> 2 | X30: =IF(H30="",0,IF(H30<=CD$3,4,IF(H30>=CD$5,1,IF(H30>=CD$4,2,3)))) -> 2 | Y30: =IF(I30="",0,IF(I30<=CE$3,4,IF(I30>=CE$5,1,IF(I30>=CE$4,2,3)))) -> 2 | Z30: =IF(J30="",0,IF(J30<=CF$3,4,IF(J30>=CF$5,1,IF(J30>=CF$4,2,3)))) -> 2 | AA30: =IF(K30="",0,IF(K30<=CG$3,4,IF(K30>=CG$5,1,IF(K30>=CG$4,2,3)))) -> 1 | AB30: =IF(L30="",0,IF(L30<=CH$3,4,IF(L30>=CH$5,1,IF(L30>=CH$4,2,3)))) -> 1 | AC30: =IF(M30="",0,IF(M30<=CI$3,4,IF(M30>=CI$5,1,IF(M30>=CI$4,2,3)))) -> 2 | ... AK30: =IF(U30="",0,IF(U30<=CQ$3,4,IF(U30>=CQ$5,1,IF(U30>=CQ$4,2,3)))) -> 3 | AL30: 101.4602 | AM30: 0.3244 | AN30: -1.8581 | AO30: 0.4877 | AP30: 0.7068 | AQ30: 7.97 | AR30: 1.12
A31: PGIM India Ultra Short Duration Fund(G) | B31: 39633 | C31: 165.2894 | D31: 161.0088 | E31: 35.5946 | F31: 0.7619 | G31: 1.7957 | H31: 4.3126 | I31: 7.0815 | J31: 5.9211 | K31: 5.0761 | L31: 5.1453 | M31: 5.5715 | N31: 6.2739 | O31: 6.4033 | P31: 6.1276 | Q31: 5.5717 | R31: 6.6891 | S31: 6.8294 | T31: 7.7274 | U31: 7.379 | V31: =IF(F31="",0,IF(F31<=CB$3,4,IF(F31>=CB$5,1,IF(F31>=CB$4,2,3)))) -> 4 | W31: =IF(G31="",0,IF(G31<=CC$3,4,IF(G31>=CC$5,1,IF(G31>=CC$4,2,3)))) -> 3 | X31: =IF(H31="",0,IF(H31<=CD$3,4,IF(H31>=CD$5,1,IF(H31>=CD$4,2,3)))) -> 4 | Y31: =IF(I31="",0,IF(I31<=CE$3,4,IF(I31>=CE$5,1,IF(I31>=CE$4,2,3)))) -> 3 | Z31: =IF(J31="",0,IF(J31<=CF$3,4,IF(J31>=CF$5,1,IF(J31>=CF$4,2,3)))) -> 4 | AA31: =IF(K31="",0,IF(K31<=CG$3,4,IF(K31>=CG$5,1,IF(K31>=CG$4,2,3)))) -> 4 | AB31: =IF(L31="",0,IF(L31<=CH$3,4,IF(L31>=CH$5,1,IF(L31>=CH$4,2,3)))) -> 4 | AC31: =IF(M31="",0,IF(M31<=CI$3,4,IF(M31>=CI$5,1,IF(M31>=CI$4,2,3)))) -> 4 | ... AK31: =IF(U31="",0,IF(U31<=CQ$3,4,IF(U31>=CQ$5,1,IF(U31>=CQ$4,2,3)))) -> 1 | AL31: 92.333 | AM31: 0.8703 | AN31: 6.7967 | AO31: 0.4408 | AP31: 0.47 | AQ31: 7.3 | AR31: 0.94
A32: SBI Ultra Short Duration Fund-Reg(G) | B32: 36299 | C32: 13685.392 | D32: 11847.06 | E32: 6274.6573 | F32: -0.2086 | G32: 0.9338 | H32: 4.0494 | I32: 6.3878 | J32: 6.3418 | K32: 5.7666 | L32: 5.6927 | M32: 6.1873 | N32: 6.8705 | O32: 6.9588 | P32: 6.6033 | Q32: 5.9813 | R32: 6.0191 | S32: 6.4218 | T32: 7.257 | U32: 7.0475 | V32: =IF(F32="",0,IF(F32<=CB$3,4,IF(F32>=CB$5,1,IF(F32>=CB$4,2,3)))) -> 4 | W32: =IF(G32="",0,IF(G32<=CC$3,4,IF(G32>=CC$5,1,IF(G32>=CC$4,2,3)))) -> 4 | X32: =IF(H32="",0,IF(H32<=CD$3,4,IF(H32>=CD$5,1,IF(H32>=CD$4,2,3)))) -> 4 | Y32: =IF(I32="",0,IF(I32<=CE$3,4,IF(I32>=CE$5,1,IF(I32>=CE$4,2,3)))) -> 4 | Z32: =IF(J32="",0,IF(J32<=CF$3,4,IF(J32>=CF$5,1,IF(J32>=CF$4,2,3)))) -> 3 | AA32: =IF(K32="",0,IF(K32<=CG$3,4,IF(K32>=CG$5,1,IF(K32>=CG$4,2,3)))) -> 1 | AB32: =IF(L32="",0,IF(L32<=CH$3,4,IF(L32>=CH$5,1,IF(L32>=CH$4,2,3)))) -> 2 | AC32: =IF(M32="",0,IF(M32<=CI$3,4,IF(M32>=CI$5,1,IF(M32>=CI$4,2,3)))) -> 2 | ... AK32: =IF(U32="",0,IF(U32<=CQ$3,4,IF(U32>=CQ$5,1,IF(U32>=CQ$4,2,3)))) -> 1 | AL32: 96.9321 | AM32: 0.4055 | AN32: 2.6623 | AO32: 0.46 | AP32: 0.84 | AQ32: 7.51 | AR32: 0.56
A33: Sundaram Ultra Short Duration Fund(G) | B33: 39444 | C33: 1907.3357 | D33: 1454.2422 | E33: 2797.1289 | F33: -0.074 | G33: 1.0439 | H33: 4.0975 | I33: 6.5318 | J33: 5.5056 | K33: 4.7618 | L33: 4.7596 | M33: 5.1566 | N33: 5.865 | O33: 5.9662 | P33: 5.692 | Q33: 5.0871 | R33: 4.9326 | S33: 4.9375 | T33: 6.3288 | U33: 5.7653 | V33: =IF(F33="",0,IF(F33<=CB$3,4,IF(F33>=CB$5,1,IF(F33>=CB$4,2,3)))) -> 4 | W33: =IF(G33="",0,IF(G33<=CC$3,4,IF(G33>=CC$5,1,IF(G33>=CC$4,2,3)))) -> 4 | X33: =IF(H33="",0,IF(H33<=CD$3,4,IF(H33>=CD$5,1,IF(H33>=CD$4,2,3)))) -> 4 | Y33: =IF(I33="",0,IF(I33<=CE$3,4,IF(I33>=CE$5,1,IF(I33>=CE$4,2,3)))) -> 4 | Z33: =IF(J33="",0,IF(J33<=CF$3,4,IF(J33>=CF$5,1,IF(J33>=CF$4,2,3)))) -> 4 | AA33: =IF(K33="",0,IF(K33<=CG$3,4,IF(K33>=CG$5,1,IF(K33>=CG$4,2,3)))) -> 4 | AB33: =IF(L33="",0,IF(L33<=CH$3,4,IF(L33>=CH$5,1,IF(L33>=CH$4,2,3)))) -> 4 | AC33: =IF(M33="",0,IF(M33<=CI$3,4,IF(M33>=CI$5,1,IF(M33>=CI$4,2,3)))) -> 4 | ... AK33: =IF(U33="",0,IF(U33<=CQ$3,4,IF(U33>=CQ$5,1,IF(U33>=CQ$4,2,3)))) -> 4 | AL33: 104.8579 | AM33: 0.4764 | AN33: -5.3947 | AO33: 0.72 | AP33: 0.75 | AQ33: 7.53 | AR33: 1.43
A34: Tata Ultra Short Term Fund-Reg(G) | B34: 43487 | C34: 3793.0239 | D34: 3955.3721 | E34: 14.8563 | F34: 1.7204 | G34: 2.0021 | H34: 5.0453 | I34: 7.5615 | J34: 6.5944 | K34: 5.6689 | L34: 5.7748 | M34: 5.9258 | N34: 6.5476 | O34: 6.5814 | P34: 6.2242 | Q34: 5.6188 | R34: 5.5174 | U34: 5.5926 | V34: =IF(F34="",0,IF(F34<=CB$3,4,IF(F34>=CB$5,1,IF(F34>=CB$4,2,3)))) -> 1 | W34: =IF(G34="",0,IF(G34<=CC$3,4,IF(G34>=CC$5,1,IF(G34>=CC$4,2,3)))) -> 3 | X34: =IF(H34="",0,IF(H34<=CD$3,4,IF(H34>=CD$5,1,IF(H34>=CD$4,2,3)))) -> 2 | Y34: =IF(I34="",0,IF(I34<=CE$3,4,IF(I34>=CE$5,1,IF(I34>=CE$4,2,3)))) -> 2 | Z34: =IF(J34="",0,IF(J34<=CF$3,4,IF(J34>=CF$5,1,IF(J34>=CF$4,2,3)))) -> 2 | AA34: =IF(K34="",0,IF(K34<=CG$3,4,IF(K34>=CG$5,1,IF(K34>=CG$4,2,3)))) -> 2 | AB34: =IF(L34="",0,IF(L34<=CH$3,4,IF(L34>=CH$5,1,IF(L34>=CH$4,2,3)))) -> 2 | AC34: =IF(M34="",0,IF(M34<=CI$3,4,IF(M34>=CI$5,1,IF(M34>=CI$4,2,3)))) -> 3 | ... AK34: =IF(U34="",0,IF(U34<=CQ$3,4,IF(U34>=CQ$5,1,IF(U34>=CQ$4,2,3)))) -> 4 | AL34: 92.5321 | AM34: 0.3231 | AN34: 7.1448 | AO34: 0.4858 | AP34: 0.75 | AQ34: 7.45 | AR34: 1.15
A35: UTI Ultra Short Duration Fund-Reg(G) | B35: 37862 | C35: 3946.2723 | D35: 3130.0149 | E35: 4440.1589 | F35: 1.3863 | G35: 2.1596 | H35: 4.6496 | I35: 7.1301 | J35: 6.0431 | K35: 5.4552 | L35: 5.4143 | M35: 5.8799 | N35: 6.5902 | O35: 6.6973 | P35: 6.3562 | Q35: 6.3154 | R35: 5.5337 | S35: 6.0558 | T35: 7.0032 | U35: 6.792 | V35: =IF(F35="",0,IF(F35<=CB$3,4,IF(F35>=CB$5,1,IF(F35>=CB$4,2,3)))) -> 2 | W35: =IF(G35="",0,IF(G35<=CC$3,4,IF(G35>=CC$5,1,IF(G35>=CC$4,2,3)))) -> 2 | X35: =IF(H35="",0,IF(H35<=CD$3,4,IF(H35>=CD$5,1,IF(H35>=CD$4,2,3)))) -> 3 | Y35: =IF(I35="",0,IF(I35<=CE$3,4,IF(I35>=CE$5,1,IF(I35>=CE$4,2,3)))) -> 3 | Z35: =IF(J35="",0,IF(J35<=CF$3,4,IF(J35>=CF$5,1,IF(J35>=CF$4,2,3)))) -> 4 | AA35: =IF(K35="",0,IF(K35<=CG$3,4,IF(K35>=CG$5,1,IF(K35>=CG$4,2,3)))) -> 3 | AB35: =IF(L35="",0,IF(L35<=CH$3,4,IF(L35>=CH$5,1,IF(L35>=CH$4,2,3)))) -> 4 | AC35: =IF(M35="",0,IF(M35<=CI$3,4,IF(M35>=CI$5,1,IF(M35>=CI$4,2,3)))) -> 3 | ... AK35: =IF(U35="",0,IF(U35<=CQ$3,4,IF(U35>=CQ$5,1,IF(U35>=CQ$4,2,3)))) -> 2 | AL35: 99.564 | AM35: 0.415 | AN35: -0.0355 | AO35: 0.5507 | AP35: 0.6411 | AQ35: 7.8 | AR35: 0.97
A36: WOC Ultra Short Duration Fund-Reg(G) | B36: 43622 | C36: 540.7151 | D36: 586.0298 | E36: 1424.1863 | F36: 0.4295 | G36: 1.7527 | H36: 5.2239 | I36: 7.92 | J36: 6.4117 | K36: 5.3635 | L36: 5.4172 | M36: 5.6732 | N36: 6.3501 | O36: 6.4201 | P36: 6.0664 | Q36: 5.5367 | U36: 5.255 | V36: =IF(F36="",0,IF(F36<=CB$3,4,IF(F36>=CB$5,1,IF(F36>=CB$4,2,3)))) -> 4 | W36: =IF(G36="",0,IF(G36<=CC$3,4,IF(G36>=CC$5,1,IF(G36>=CC$4,2,3)))) -> 4 | X36: =IF(H36="",0,IF(H36<=CD$3,4,IF(H36>=CD$5,1,IF(H36>=CD$4,2,3)))) -> 1 | Y36: =IF(I36="",0,IF(I36<=CE$3,4,IF(I36>=CE$5,1,IF(I36>=CE$4,2,3)))) -> 1 | Z36: =IF(J36="",0,IF(J36<=CF$3,4,IF(J36>=CF$5,1,IF(J36>=CF$4,2,3)))) -> 3 | AA36: =IF(K36="",0,IF(K36<=CG$3,4,IF(K36>=CG$5,1,IF(K36>=CG$4,2,3)))) -> 4 | AB36: =IF(L36="",0,IF(L36<=CH$3,4,IF(L36>=CH$5,1,IF(L36>=CH$4,2,3)))) -> 4 | AC36: =IF(M36="",0,IF(M36<=CI$3,4,IF(M36>=CI$5,1,IF(M36>=CI$4,2,3)))) -> 4 | ... AK36: =IF(U36="",0,IF(U36<=CQ$3,4,IF(U36>=CQ$5,1,IF(U36>=CQ$4,2,3)))) -> 4 | AL36: 95.1174 | AM36: 0.2641 | AN36: 4.6185 | AO36: 0.39 | AP36: 0.43 | AQ36: 7.37 | AR36: 1.02
A37: Category Average (Weighted) | F37: =SUMPRODUCT($D12:$D36,F12:F36)/SUMIF(F12:F36,"<>"&"",$D12:$D36) -> 1.8015416 | G37: =SUMPRODUCT($D12:$D36,G12:G36)/SUMIF(G12:G36,"<>"&"",$D12:$D36) -> 2.4076993 | H37: =SUMPRODUCT($D12:$D36,H12:H36)/SUMIF(H12:H36,"<>"&"",$D12:$D36) -> 5.0718718 | I37: =SUMPRODUCT($D12:$D36,I12:I36)/SUMIF(I12:I36,"<>"&"",$D12:$D36) -> 6.8498355 | J37: =SUMPRODUCT($D12:$D36,J12:J36)/SUMIF(J12:J36,"<>"&"",$D12:$D36) -> 6.4333905 | K37: =SUMPRODUCT($D12:$D36,K12:K36)/SUMIF(K12:K36,"<>"&"",$D12:$D36) -> 5.6790969 | L37: =SUMPRODUCT($D12:$D36,L12:L36)/SUMIF(L12:L36,"<>"&"",$D12:$D36) -> 5.6679864 | M37: =SUMPRODUCT($D12:$D36,M12:M36)/SUMIF(M12:M36,"<>"&"",$D12:$D36) -> 6.160709 | ... U37: =SUMPRODUCT($D12:$D36,U12:U36)/SUMIF(U12:U36,"<>"&"",$D12:$D36) -> 6.7398272
A38: Minimum | F38: =MIN(F12:F36) -> -0.2086 | G38: =MIN(G12:G36) -> 0.9338 | H38: =MIN(H12:H36) -> 4.0494 | I38: =MIN(I12:I36) -> 6.1109 | J38: =MIN(J12:J36) -> 5.5056 | K38: =MIN(K12:K36) -> 4.7618 | L38: =MIN(L12:L36) -> 4.7596 | M38: =MIN(M12:M36) -> 5.1566 | ... U38: =MIN(U12:U36) -> 4.366
A39: Maximum | F39: =MAX(F12:F36) -> 3.8506 | G39: =MAX(G12:G36) -> 3.4237 | H39: =MAX(H12:H36) -> 6.1256 | I39: =MAX(I12:I36) -> 8.2187 | J39: =MAX(J12:J36) -> 6.8894 | K39: =MAX(K12:K36) -> 5.951 | L39: =MAX(L12:L36) -> 6.0206 | M39: =MAX(M12:M36) -> 6.4532 | ... U39: =MAX(U12:U36) -> 7.3877
A40: Median | F40: =MEDIAN(F12:F36) -> 1.3593 | G40: =MEDIAN(G12:G36) -> 2.1436 | H40: =MEDIAN(H12:H36) -> 5.0431 | I40: =MEDIAN(I12:I36) -> 7.3106 | J40: =MEDIAN(J12:J36) -> 6.4824 | K40: =MEDIAN(K12:K36) -> 5.6395 | L40: =MEDIAN(L12:L36) -> 5.6927 | M40: =MEDIAN(M12:M36) -> 6.057 | ... U40: =MEDIAN(U12:U36) -> 6.2858
A42: # : "In the Quartile System, the "performance range" of the entire category for a given time period, is divided into 4 parts. Schemes with returns in the top 25% of that range
A43: in the next 25% of the range have been ranked Quartile 2 and so on. Quartile 4 shows the schemes whose returns are in the bottom 25% of the range."

Sheet Low Duration Fund
A1: Main Page | E1: Data Source: ACEMF | CA1: Quartile code | CB1: 7 Days | CC1: 14 Days | CD1: 21 Days | CE1: 1 Month | CF1: 3 Month | CG1: 6 Months | CH1: YTD | CI1: 1 Year | CJ1: 2 Year | CK1: 3 Year | CL1: 4 Years | CM1: 5 Years | CN1: 7 Years | CO1: 10 Years | CP1: 15 Years | CQ1: Inception
CA2: 0 | CB2: =_xlfn.QUARTILE.INC(F$12:F$34,$CA2) -> -4.2205 | CC2: =_xlfn.QUARTILE.INC(G$12:G$34,$CA2) -> -2.1605 | CD2: =_xlfn.QUARTILE.INC(H$12:H$34,$CA2) -> 2.5515 | CE2: =_xlfn.QUARTILE.INC(I$12:I$34,$CA2) -> 5.4234 | CF2: =_xlfn.QUARTILE.INC(J$12:J$34,$CA2) -> 4.6601 | CG2: =_xlfn.QUARTILE.INC(K$12:K$34,$CA2) -> 4.1877 | CH2: =_xlfn.QUARTILE.INC(L$12:L$34,$CA2) -> 3.8827 | CI2: =_xlfn.QUARTILE.INC(M$12:M$34,$CA2) -> 5.3391 | ... CQ2: =_xlfn.QUARTILE.INC(U$12:U$34,$CA2) -> 4.7058
CA3: 1 | CB3: =_xlfn.QUARTILE.INC(F$12:F$34,$CA3) -> -2.00005 | CC3: =_xlfn.QUARTILE.INC(G$12:G$34,$CA3) -> -0.25365 | CD3: =_xlfn.QUARTILE.INC(H$12:H$34,$CA3) -> 3.59115 | CE3: =_xlfn.QUARTILE.INC(I$12:I$34,$CA3) -> 6.3397 | CF3: =_xlfn.QUARTILE.INC(J$12:J$34,$CA3) -> 5.46215 | CG3: =_xlfn.QUARTILE.INC(K$12:K$34,$CA3) -> 4.8368 | CH3: =_xlfn.QUARTILE.INC(L$12:L$34,$CA3) -> 4.6483 | CI3: =_xlfn.QUARTILE.INC(M$12:M$34,$CA3) -> 5.66715 | ... CQ3: =_xlfn.QUARTILE.INC(U$12:U$34,$CA3) -> 6.57945
CA4: 2 | CB4: =_xlfn.QUARTILE.INC(F$12:F$34,$CA4) -> -0.932 | CC4: =_xlfn.QUARTILE.INC(G$12:G$34,$CA4) -> 0.5444 | CD4: =_xlfn.QUARTILE.INC(H$12:H$34,$CA4) -> 4.0946 | CE4: =_xlfn.QUARTILE.INC(I$12:I$34,$CA4) -> 6.7867 | CF4: =_xlfn.QUARTILE.INC(J$12:J$34,$CA4) -> 5.7151 | CG4: =_xlfn.QUARTILE.INC(K$12:K$34,$CA4) -> 4.92 | CH4: =_xlfn.QUARTILE.INC(L$12:L$34,$CA4) -> 4.822 | CI4: =_xlfn.QUARTILE.INC(M$12:M$34,$CA4) -> 5.8266 | ... CQ4: =_xlfn.QUARTILE.INC(U$12:U$34,$CA4) -> 7.1237
CA5: 3 | CB5: =_xlfn.QUARTILE.INC(F$12:F$34,$CA5) -> -0.5527 | CC5: =_xlfn.QUARTILE.INC(G$12:G$34,$CA5) -> 0.67275 | CD5: =_xlfn.QUARTILE.INC(H$12:H$34,$CA5) -> 4.32785 | CE5: =_xlfn.QUARTILE.INC(I$12:I$34,$CA5) -> 7.1418 | CF5: =_xlfn.QUARTILE.INC(J$12:J$34,$CA5) -> 5.8682 | CG5: =_xlfn.QUARTILE.INC(K$12:K$34,$CA5) -> 5.1694 | CH5: =_xlfn.QUARTILE.INC(L$12:L$34,$CA5) -> 5.0297 | CI5: =_xlfn.QUARTILE.INC(M$12:M$34,$CA5) -> 5.98075 | ... CQ5: =_xlfn.QUARTILE.INC(U$12:U$34,$CA5) -> 7.2482
CB6: =_xlfn.QUARTILE.INC(F$12:F$34,$CA6) -> -4.2205 | CC6: =_xlfn.QUARTILE.INC(G$12:G$34,$CA6) -> -2.1605 | CD6: =_xlfn.QUARTILE.INC(H$12:H$34,$CA6) -> 2.5515 | CE6: =_xlfn.QUARTILE.INC(I$12:I$34,$CA6) -> 5.4234 | CF6: =_xlfn.QUARTILE.INC(J$12:J$34,$CA6) -> 4.6601 | CG6: =_xlfn.QUARTILE.INC(K$12:K$34,$CA6) -> 4.1877 | CH6: =_xlfn.QUARTILE.INC(L$12:L$34,$CA6) -> 3.8827 | CI6: =_xlfn.QUARTILE.INC(M$12:M$34,$CA6) -> 5.3391 | ... CQ6: =_xlfn.QUARTILE.INC(U$12:U$34,$CA6) -> 4.7058
A7: Fund Barometer - Low Duration Fund | CA7: 4 | CB7: =_xlfn.QUARTILE.INC(F$12:F$34,$CA7) -> 1.8316 | CC7: =_xlfn.QUARTILE.INC(G$12:G$34,$CA7) -> 2.9907 | CD7: =_xlfn.QUARTILE.INC(H$12:H$34,$CA7) -> 4.9447 | CE7: =_xlfn.QUARTILE.INC(I$12:I$34,$CA7) -> 7.702 | CF7: =_xlfn.QUARTILE.INC(J$12:J$34,$CA7) -> 6.3758 | CG7: =_xlfn.QUARTILE.INC(K$12:K$34,$CA7) -> 5.7102 | CH7: =_xlfn.QUARTILE.INC(L$12:L$34,$CA7) -> 5.8847 | CI7: =_xlfn.QUARTILE.INC(M$12:M$34,$CA7) -> 6.4206 | ... CQ7: =_xlfn.QUARTILE.INC(U$12:U$34,$CA7) -> 7.6676
A8: ='Short Duration Fund'!A8 -> (As on 30 Apr 2026) | B8: Value Information | F8: Simple Annualized (%) | M8: Compound Annualized (%) | U8: Since Inception | V8: Quartile | AL8: Credit Quality | AO8: Modified Duration (Years) | AP8: Average Maturity (Years) | AQ8: YTM | AR8: Expense Ratio(%)
